Workbook

Sheet RESUMEN
A1: DISTRIBUIDORA CASTILLO YAÑEZ C.A | G1: F | H1: FACTURA | I1: =TODAY() -> 46057 | L1: 51364.043 | M1: 3860.551
A2: J-40214875-5 | G2: T | H2: TRANSFERENCIA | L2: 6090.28 | M2: =20*4.71 -> 94.2
A3: CEP 22405697 | G3: E | H3: EFECTIVO | I3: BCV | L3: =+L1-L2 -> 45273.763 | M3: =+M1-M2 -> 3766.351
A4: V72151 ZONA 1728 INICIO RUTA 4-6-2025 | G4: P | H4: PRESTADO | I4: 370.2544 | L4: 152.2 | M4: =2*4.71 -> 9.42
A5: =TODAY() -> 46057 | G5: O | H5: OBSEQUIO | L5: =+L3-L4 -> 45121.563 | M5: =+M3+M4 -> 3775.771
B6: TOTAL | D6: =SUM(D$10:D$1048576) -> 55145.994 | E6: =+E9*E7 -> 3961.3412 | F6: =+F7*F9 -> 31.842971 | G6: =+G7*G9 -> -217.41808 | H6: =(E6+F6+G6) -> 3775.7661 | L6: 412.68
B7: SUB TOTAL | E7: =SUM(E$10:E$1048576) -> 841 | F7: =SUM(F$10:F$1048576) -> 3 | G7: =SUM(G$10:G$1048576) -> -23 | H7: =SUM(H$10:H$1048576) -> 138.188 | L7: =+L5-L6 -> 44708.883
B8: DEUDOR | D8: MONTO | E8: VACIO 1/4 | F8: VACIO 355 | G8: VACIO 1.25 | H8: RETENCION | I8: VENDEDOR | J8: ULTIMO P O C | L8: 302.1
B9: RAZON SOCIAL | C9: NOMBRE CLIENTE | E9: =1744/I4 -> 4.7102749 | F9: =3930/I4 -> 10.614324 | G9: =3500/I4 -> 9.4529599 | H9: =+'MINI ABASTO EL SOL'!$G$5 -> 0 | L9: 5407.33
A10: 1 | B10: =+'ABASTO ANTONY'!$B$1 -> ABASTO ANTONY | C10: =+'ABASTO ANTONY'!$B$2 -> 0 | D10: =+'ABASTO ANTONY'!$C$3 -> 452.01 | E10: =+'ABASTO ANTONY'!$D$3 -> 1 | F10: =+'ABASTO ANTONY'!$E$3 -> 0 | G10: =+'ABASTO ANTONY'!$F$3 -> 0 | H10: =+'ABASTO ANTONY'!$G$3 -> 0 | I10: MENOR | J10: =MAX('ABASTO ANTONY'!A2:A1000) -> 46052 | L10: =+L7-L8+L9 -> 49814.113
A11: 2 | B11: =+'ABASTO DON MARCOS'!$B$1 -> ABASTO DON MARCOS | C11: =+'ABASTO DON MARCOS'!$B$2 -> ANA ZAMBRANO | D11: =+'ABASTO DON MARCOS'!$C$3 -> 98.01 | E11: =+'ABASTO DON MARCOS'!$D$3 -> 0 | F11: =+'ABASTO DON MARCOS'!$E$3 -> 0 | G11: =+'ABASTO DON MARCOS'!$F$3 -> 0 | H11: =+'ABASTO DON MARCOS'!$G$3 -> 0 | I11: WILLI | J11: =MAX('ABASTO DON MARCOS'!A2:A1000) -> 46055 | L11: 106.16
A12: 3 | B12: =+'ABASTO GLORIMAR'!$B$1 -> ABASTO GLORIMAR | C12: =+'ABASTO GLORIMAR'!$B$2 -> 0 | D12: =+'ABASTO GLORIMAR'!$C$3 -> 110.22 | E12: =+'ABASTO GLORIMAR'!$D$3 -> 2 | F12: =+'ABASTO GLORIMAR'!$E$3 -> 0 | G12: =+'ABASTO GLORIMAR'!$F$3 -> 0 | H12: =+'ABASTO GLORIMAR'!$G$3 -> 0 | I12: MENOR | J12: =MAX('ABASTO GLORIMAR'!A2:A1001) -> 46050 | L12: =+L10-L11 -> 49707.953
A13: 4 | B13: =+'ABASTO JAVER'!$B$1 -> ABASTO JAVER | C13: =+'ABASTO JAVER'!$B$2 -> JAVER OVALLES | D13: =+'ABASTO JAVER'!$C$3 -> 0 | E13: =+'ABASTO JAVER'!$D$3 -> 0 | F13: =+'ABASTO JAVER'!$E$3 -> 0 | G13: =+'ABASTO JAVER'!$F$3 -> 0 | H13: =+'ABASTO JAVER'!$G$3 -> 0 | I13: WILLI | J13: =MAX('ABASTO JAVER'!A2:A1002) -> 45979 | L13: 22.18
A14: 5 | B14: =+'ABASTO KLEIDI'!$B$1 -> ABASTO KLEIDI | C14: =+'ABASTO KLEIDI'!$B$2 -> KLEIDI | D14: =+'ABASTO KLEIDI'!$C$3 -> 1.35 | E14: =+'ABASTO KLEIDI'!$D$3 -> 0 | F14: =+'ABASTO KLEIDI'!$E$3 -> 0 | G14: =+'ABASTO KLEIDI'!$F$3 -> 0 | H14: =+'ABASTO KLEIDI'!$G$3 -> 0 | I14: MENOR | J14: =MAX('ABASTO KLEIDI'!A2:A1000) -> 46052 | L14: 46.28
A15: 6 | B15: =+'ABASTO LAUDA'!$B$1 -> ABASTO LAUDA | C15: =+'ABASTO LAUDA'!$B$2 -> ANDRES | D15: =+'ABASTO LAUDA'!$C$3 -> 816.14 | E15: =+'ABASTO LAUDA'!$D$3 -> 0 | F15: =+'ABASTO LAUDA'!$E$3 -> 0 | G15: =+'ABASTO LAUDA'!$F$3 -> 0 | H15: =+'ABASTO LAUDA'!$G$3 -> 0 | I15: MENOR | J15: =MAX('ABASTO LAUDA'!A2:A1000) -> 46050 | L15: 27.12
A16: 7 | B16: =+'ABASTO LAS CUADRAS'!$B$1 -> ABASTO LAS CUADRAS | C16: =+'ABASTO LAS CUADRAS'!$B$2 -> WILFREDO CHACON | D16: =+'ABASTO LAS CUADRAS'!$C$3 -> 128.3 | E16: =+'ABASTO LAS CUADRAS'!$D$3 -> 1 | F16: =+'ABASTO LAS CUADRAS'!$E$3 -> 0 | G16: =+'ABASTO LAS CUADRAS'!$F$3 -> 0 | H16: =+'ABASTO LAS CUADRAS'!$G$3 -> 0 | I16: WILLI | J16: =MAX('ABASTO LAS CUADRAS'!A2:A1000) -> 46051 | L16: 28.13
A17: 8 | B17: =+'ABASTO LAS MORENAS'!$B$1 -> ABASTO LAS MORENAS | C17: =+'ABASTO LAS MORENAS'!$B$2 -> CECILIO | D17: =+'ABASTO LAS MORENAS'!$C$3 -> 367.41 | E17: =+'ABASTO LAS MORENAS'!$D$3 -> 0 | F17: =+'ABASTO LAS MORENAS'!$E$3 -> 0 | G17: =+'ABASTO LAS MORENAS'!$F$3 -> 0 | H17: =+'ABASTO LAS MORENAS'!$G$3 -> 0 | I17: WILLI | J17: =MAX('ABASTO LAS MORENAS'!A2:A1000) -> 46052 | L17: 3093.39
A18: 9 | B18: =+'ABASTO LAS PILAS'!$B$1 -> ABASTO LAS PILAS | C18: =+'ABASTO LAS PILAS'!$B$2 -> 0 | D18: =+'ABASTO LAS PILAS'!$C$3 -> 46 | E18: =+'ABASTO LAS PILAS'!$D$3 -> 1 | F18: =+'ABASTO LAS PILAS'!$E$3 -> 0 | G18: =+'ABASTO LAS PILAS'!$F$3 -> 0 | H18: =+'ABASTO LAS PILAS'!$G$3 -> 0 | I18: MENOR | J18: =MAX('ABASTO LAS PILAS'!A2:A1000) -> 46051 | L18: =+L12-L13-L14-L15+L17-L16 -> 52677.633
A19: 10 | B19: =+'ABASTO LUZ VALERO'!$B$1 -> ABASTO LUZ VALERO | C19: =+'ABASTO LUZ VALERO'!$B$2 -> 0 | D19: =+'ABASTO LUZ VALERO'!$C$3 -> 187.67 | E19: =+'ABASTO LUZ VALERO'!$D$3 -> 0 | F19: =+'ABASTO LUZ VALERO'!$E$3 -> 0 | G19: =+'ABASTO LUZ VALERO'!$F$3 -> 0 | H19: =+'ABASTO LUZ VALERO'!$G$3 -> 0 | I19: MENOR | J19: =MAX('ABASTO LUZ VALERO'!A2:A1000) -> 46052 | L19: 260.75
A20: 11 | B20: =+'ABASTO LUZMAR'!$B$1 -> ABASTO LUZMAR | C20: =+'ABASTO LUZMAR'!$B$2 -> MARINA LUZ SANCHEZ | D20: =+'ABASTO LUZMAR'!$C$3 -> 0 | E20: =+'ABASTO LUZMAR'!$D$3 -> 0 | F20: =+'ABASTO LUZMAR'!$E$3 -> 0 | G20: =+'ABASTO LUZMAR'!$F$3 -> 0 | H20: =+'ABASTO LUZMAR'!$G$3 -> 0 | I20: WILLI | J20: =MAX('ABASTO LUZMAR'!A2:A1000) -> 45912 | L20: 844.35
A21: 12 | B21: =+'ABASTO MIS ANGELES'!$B$1 -> ABASTO MIS ANGELES | C21: =+'ABASTO MIS ANGELES'!$B$2 -> 0 | D21: =+'ABASTO MIS ANGELES'!$C$3 -> 50.18 | E21: =+'ABASTO MIS ANGELES'!$D$3 -> 0 | F21: =+'ABASTO MIS ANGELES'!$E$3 -> 0 | G21: =+'ABASTO MIS ANGELES'!$F$3 -> 0 | H21: =+'ABASTO MIS ANGELES'!$G$3 -> 0 | I21: MENOR | J21: =MAX('ABASTO MIS ANGELES'!A2:A1000) -> 46052 | L21: 4805.57
A22: 13 | B22: =+'ABASTO VANESA'!$B$1 -> ABASTO VANESA | C22: =+'ABASTO VANESA'!$B$2 -> 0 | D22: =+'ABASTO VANESA'!$C$3 -> 336.13 | E22: =+'ABASTO VANESA'!$D$3 -> 2 | F22: =+'ABASTO VANESA'!$E$3 -> 0 | G22: =+'ABASTO VANESA'!$F$3 -> 0 | H22: =+'ABASTO VANESA'!$G$3 -> 0 | I22: MENOR | J22: =MAX('ABASTO VANESA'!A2:A1000) -> 46052 | L22: =+L18-L19-L20+L21 -> 56378.103
A23: 14 | B23: =+'ABASTO Y CHARCUTERIA WILMARY'!$B$1 -> ABASTO Y CHARCUTERIA WILMARY | C23: =+'ABASTO Y CHARCUTERIA WILMARY'!$B$2 -> ANA CONTRERAS | D23: =+'ABASTO Y CHARCUTERIA WILMARY'!$C$3 -> 54.72 | E23: =+'ABASTO Y CHARCUTERIA WILMARY'!$D$3 -> 0 | F23: =+'ABASTO Y CHARCUTERIA WILMARY'!$E$3 -> 0 | G23: =+'ABASTO Y CHARCUTERIA WILMARY'!$F$3 -> 0 | H23: =+'ABASTO Y CHARCUTERIA WILMARY'!$G$3 -> 0 | I23: MENOR | J23: =MAX('ABASTO Y CHARCUTERIA WILMARY'!A2:A1000) -> 46051 | L23: 1232.14
A24: 15 | B24: =+'ABASTO YUDERLI'!$B$1 -> ABASTO YUDERLI | C24: =+'ABASTO YUDERLI'!$B$2 -> 0 | D24: =+'ABASTO YUDERLI'!$C$3 -> 0.02 | E24: =+'ABASTO YUDERLI'!$D$3 -> 1 | F24: =+'ABASTO YUDERLI'!$E$3 -> 0 | G24: =+'ABASTO YUDERLI'!$F$3 -> 0 | H24: =+'ABASTO YUDERLI'!$G$3 -> 0 | I24: MENOR | J24: =MAX('ABASTO YUDERLI'!A2:A1000) -> 45996 | L24: =+L22-L23 -> 55145.963
A25: 16 | B25: =+'ABASTO ZORANNY'!$B$1 -> ABASTO ZORANNY | C25: =+'ABASTO ZORANNY'!$B$2 -> ZORAIDA | D25: =+'ABASTO ZORANNY'!$C$3 -> 0 | E25: =+'ABASTO ZORANNY'!$D$3 -> 0 | F25: =+'ABASTO ZORANNY'!$E$3 -> 0 | G25: =+'ABASTO ZORANNY'!$F$3 -> 0 | H25: =+'ABASTO ZORANNY'!$G$3 -> 0 | I25: WILLI | J25: =MAX('ABASTO ZORANNY'!A2:A1000) -> 46050
A26: 17 | B26: =+'ALAS COMPAS'!$B$1 -> ALAS COMPRAS | C26: =+'ALAS COMPAS'!$B$2 -> ELICEO GARCIA | D26: =+'ALAS COMPAS'!$C$3 -> 541.04 | E26: =+'ALAS COMPAS'!$D$3 -> 0 | F26: =+'ALAS COMPAS'!$E$3 -> 0 | G26: =+'ALAS COMPAS'!$F$3 -> 0 | H26: =+'ALAS COMPAS'!$G$3 -> 0 | I26: WILLI | J26: =MAX('ALAS COMPAS'!A2:A1000) -> 46052
A27: 18 | B27: =+'ALVARO RINCON'!$B$1 -> ALVARO RINCON | C27: =+'ALVARO RINCON'!$B$2 -> 0 | D27: =+'ALVARO RINCON'!$C$3 -> 0 | E27: =+'ALVARO RINCON'!$D$3 -> 0 | F27: =+'ALVARO RINCON'!$E$3 -> 0 | G27: =+'ALVARO RINCON'!$F$3 -> 0 | H27: =+'ALVARO RINCON'!$G$3 -> 0 | I27: MENOR | J27: =MAX('ALVARO RINCON'!A2:A1000) -> 0
A28: 19 | B28: =+'ALEJANDRA NIETO'!$B$1 -> ALEJANDRA NIETO | C28: =+'ALEJANDRA NIETO'!$B$2 -> 0 | D28: =+'ALEJANDRA NIETO'!$C$3 -> -2.21 | E28: =+'ALEJANDRA NIETO'!$D$3 -> 0 | F28: =+'ALEJANDRA NIETO'!$E$3 -> 0 | G28: =+'ALEJANDRA NIETO'!$F$3 -> 0 | H28: =+'ALEJANDRA NIETO'!$G$3 -> 0 | I28: MENOR | J28: =MAX('ALEJANDRA NIETO'!A2:A1000) -> 46055
A29: 20 | B29: =+AMALUBE!$B$1 -> AMALUBE | C29: =+AMALUBE!$B$2 -> 0 | D29: =+AMALUBE!$C$3 -> 33.85 | E29: =+AMALUBE!$D$3 -> 0 | F29: =+AMALUBE!$E$3 -> 0 | G29: =+AMALUBE!$F$3 -> 0 | H29: =+AMALUBE!$G$3 -> 0 | I29: MENOR | J29: =MAX(AMALUBE!A2:A1000) -> 46050
A30: 21 | B30: =+'AMEZQUITA BODEGON'!$B$1 -> AMEZQUITA BODEGON | C30: =+'AMEZQUITA BODEGON'!$B$2 -> 0 | D30: =+'AMEZQUITA BODEGON'!$C$3 -> 335.58 | E30: =+'AMEZQUITA BODEGON'!$D$3 -> 1 | F30: =+'AMEZQUITA BODEGON'!$E$3 -> 0 | G30: =+'AMEZQUITA BODEGON'!$F$3 -> 0 | H30: =+'AMEZQUITA BODEGON'!$G$3 -> 0 | I30: WILLI
A31: 22 | B31: =+'ANDERZON POLAR'!$B$1 -> ANDERZON POLAR | C31: =+'ANDERZON POLAR'!$B$2 -> 0 | D31: =+'ANDERZON POLAR'!$C$3 -> 0.25 | E31: =+'ANDERZON POLAR'!$D$3 -> 0 | F31: =+'ANDERZON POLAR'!$E$3 -> 0 | G31: =+'ANDERZON POLAR'!$F$3 -> 0 | H31: =+'ANDERZON POLAR'!$G$3 -> 0 | I31: WILLI | J31: =MAX('ANDERZON POLAR'!A2:A1000) -> 46036
A32: 23 | B32: =+'ANDERZON RODRIGUEZ'!$B$1 -> ANDERZON RODRIGUEZ | C32: =+'ANDERZON RODRIGUEZ'!$B$2 -> 0 | D32: =+'ANDERZON RODRIGUEZ'!$C$3 -> 127.18 | E32: =+'ANDERZON RODRIGUEZ'!$D$3 -> 0 | F32: =+'ANDERZON RODRIGUEZ'!$E$3 -> -1 | G32: =+'ANDERZON RODRIGUEZ'!$F$3 -> -2 | H32: =+'ANDERZON RODRIGUEZ'!$G$3 -> 0 | I32: MENOR | J32: =MAX('ANDERZON RODRIGUEZ'!A2:A1000) -> 46056
A33: 24 | B33: =+'ANDREA URDANETA'!$B$1 -> ANDREA URDANETA | C33: =+'ANDREA URDANETA'!$B$2 -> 0 | D33: =+'ANDREA URDANETA'!$C$3 -> 368.59 | E33: =+'ANDREA URDANETA'!$D$3 -> 0 | F33: =+'ANDREA URDANETA'!$E$3 -> 0 | G33: =+'ANDREA URDANETA'!$F$3 -> 0 | H33: =+'ANDREA URDANETA'!$G$3 -> 0 | I33: MENOR | J33: =MAX('ANDREA URDANETA'!A2:A1000) -> 46052
A34: 25 | B34: =+APRICOT!$B$1 -> APRICOT | C34: =+APRICOT!$B$2 -> 0 | D34: =+APRICOT!$C$3 -> 440.72 | E34: =+APRICOT!$D$3 -> 12 | F34: =+APRICOT!$E$3 -> 0 | G34: =+APRICOT!$F$3 -> 0 | H34: =+APRICOT!$G$3 -> 0 | I34: ROBERTO | J34: =MAX(APRICOT!A2:A1000) -> 46045
A35: 26 | B35: =+'AURA VIVAS'!$B$1 -> AURA VIVAS | C35: =+'AURA VIVAS'!$B$2 -> 0 | D35: =+'AURA VIVAS'!$C$3 -> -0.002 | E35: =+'AURA VIVAS'!$D$3 -> 0 | F35: =+'AURA VIVAS'!$E$3 -> 0 | G35: =+'AURA VIVAS'!$F$3 -> 0 | H35: =+'AURA VIVAS'!$G$3 -> 0 | I35: WILLI | J35: =MAX('AURA VIVAS'!A2:A1000) -> 45950
B36: =+'AVENTURA INFLABLE'!$B$1 -> AVENTURA INFLABLE | C36: =+'AVENTURA INFLABLE'!$B$2 -> 0 | D36: =+'AVENTURA INFLABLE'!$C$3 -> 1.9539925e-13 | E36: =+'AVENTURA INFLABLE'!$D$3 -> 2 | F36: =+'AVENTURA INFLABLE'!$E$3 -> 0 | G36: =+'AVENTURA INFLABLE'!$F$3 -> 0 | H36: =+'AVENTURA INFLABLE'!$G$3 -> 0 | I36: MENOR
B37: =+'BARBERIA SPARTA'!$B$1 -> BARBERIA SPARTA | C37: =+'BARBERIA SPARTA'!$B$2 -> 0 | D37: =+'BARBERIA SPARTA'!$C$3 -> 0 | E37: =+'BARBERIA SPARTA'!$D$3 -> 0 | F37: =+'BARBERIA SPARTA'!$E$3 -> 0 | G37: =+'BARBERIA SPARTA'!$F$3 -> 0 | H37: =+'BARBERIA SPARTA'!$G$3 -> 0 | I37: MENOR
A38: 27 | B38: =+'BAKAI MACHIRI'!$B$1 -> BAKAI MACHIRI | C38: =+'BAKAI MACHIRI'!$B$2 -> 0 | D38: =+'BAKAI MACHIRI'!$C$3 -> 71.28 | E38: =+'BAKAI MACHIRI'!$D$3 -> 0 | F38: =+'BAKAI MACHIRI'!$E$3 -> 0 | G38: =+'BAKAI MACHIRI'!$F$3 -> 0 | H38: =+'BAKAI MACHIRI'!$G$3 -> 44.73 | I38: MENOR | J38: =MAX('BAKAI MACHIRI'!A2:A1000) -> 46056
A39: 28 | B39: =+'BELKIS MONSALVE'!$B$1 -> BELKIS MONSALVE | C39: =+'BELKIS MONSALVE'!$B$2 -> 0 | D39: =+'BELKIS MONSALVE'!$C$3 -> 0 | E39: =+'BELKIS MONSALVE'!$D$3 -> 0 | F39: =+'BELKIS MONSALVE'!$E$3 -> 0 | G39: =+'BELKIS MONSALVE'!$F$3 -> 0 | H39: =+'BELKIS MONSALVE'!$G$3 -> 0 | I39: WILLI | J39: =MAX('BELKIS MONSALVE'!A2:A1000) -> 0
A40: 29 | B40: =+'BOD ALTOS PARAMILLO'!$B$1 -> BOD ALTOS PARAMILLO | C40: =+'BOD ALTOS PARAMILLO'!$B$2 -> CIRA PERDOMO | D40: =+'BOD ALTOS PARAMILLO'!$C$3 -> -0.02 | E40: =+'BOD ALTOS PARAMILLO'!$D$3 -> 0 | F40: =+'BOD ALTOS PARAMILLO'!$E$3 -> 0 | G40: =+'BOD ALTOS PARAMILLO'!$F$3 -> 0 | H40: =+'BOD ALTOS PARAMILLO'!$G$3 -> 0 | I40: WILLI | J40: =MAX('BOD ALTOS PARAMILLO'!A2:A1000) -> 45958
A41: 30 | B41: =+'BOD MARBELYS ROA'!$B$1 -> BOD MARBELYS ROA | C41: =+'BOD MARBELYS ROA'!$B$2 -> MARBELYS ROA | D41: =+'BOD MARBELYS ROA'!$C$3 -> 0.01 | E41: =+'BOD MARBELYS ROA'!$D$3 -> 0 | F41: =+'BOD MARBELYS ROA'!$E$3 -> 0 | G41: =+'BOD MARBELYS ROA'!$F$3 -> 0 | H41: =+'BOD MARBELYS ROA'!$G$3 -> 0 | I41: WILLI | J41: =MAX('BOD MARBELYS ROA'!A2:A1000) -> 46056
A42: 31 | B42: =+'BOD SOLMAR PINTO'!$B$1 -> BOD SOLMAR PINTO | C42: =+'BOD SOLMAR PINTO'!$B$2 -> 0 | D42: =+'BOD SOLMAR PINTO'!$C$3 -> 211.19 | E42: =+'BOD SOLMAR PINTO'!$D$3 -> 1 | F42: =+'BOD SOLMAR PINTO'!$E$3 -> 0 | G42: =+'BOD SOLMAR PINTO'!$F$3 -> 0 | H42: =+'BOD SOLMAR PINTO'!$G$3 -> 0 | I42: WILLI | J42: =MAX('BOD SOLMAR PINTO'!A2:A1000) -> 46051
A43: 32 | B43: =+'BOD TOICO CLEIBER'!$B$1 -> BOD TOICO CLEIBER | C43: =+'BOD TOICO CLEIBER'!$B$2 -> CLEIBER ANDRADE | D43: =+'BOD TOICO CLEIBER'!$C$3 -> 3.5527137e-14 | E43: =+'BOD TOICO CLEIBER'!$D$3 -> 0 | F43: =+'BOD TOICO CLEIBER'!$E$3 -> 0 | G43: =+'BOD TOICO CLEIBER'!$F$3 -> 0 | H43: =+'BOD TOICO CLEIBER'!$G$3 -> 0 | I43: WILLI | J43: =MAX('BOD TOICO CLEIBER'!A2:A1000) -> 46055
A44: 33 | B44: =+'BOD TOICO OSMAR'!$B$1 -> BOD TOICO OSMAR | C44: =+'BOD TOICO OSMAR'!$B$2 -> OSMAR SUAREZ | D44: =+'BOD TOICO OSMAR'!$C$3 -> -0.057 | E44: =+'BOD TOICO OSMAR'!$D$3 -> 1 | F44: =+'BOD TOICO OSMAR'!$E$3 -> 0 | G44: =+'BOD TOICO OSMAR'!$F$3 -> 0 | H44: =+'BOD TOICO OSMAR'!$G$3 -> 0 | I44: WILLI | J44: =MAX('BOD TOICO OSMAR'!A2:A1000) -> 46043
A45: 34 | B45: =+'BODEGA DE ORO'!$B$1 -> BODEGA DE ORO | C45: =+'BODEGA DE ORO'!$B$2 -> 0 | D45: =+'BODEGA DE ORO'!$C$3 -> 240.943 | E45: =+'BODEGA DE ORO'!$D$3 -> 0 | F45: =+'BODEGA DE ORO'!$E$3 -> 0 | G45: =+'BODEGA DE ORO'!$F$3 -> 0 | H45: =+'BODEGA DE ORO'!$G$3 -> 0 | I45: MENOR | J45: =MAX('BODEGA DE ORO'!A2:A1000) -> 46051
A46: 35 | B46: =+'BODEGA EL ARBOLITO'!$B$1 -> BODEGA EL ARBOLITO | C46: =+'BODEGA EL ARBOLITO'!$B$2 -> 0 | D46: =+'BODEGA EL ARBOLITO'!$C$3 -> 96.43 | E46: =+'BODEGA EL ARBOLITO'!$D$3 -> 0 | F46: =+'BODEGA EL ARBOLITO'!$E$3 -> 0 | G46: =+'BODEGA EL ARBOLITO'!$F$3 -> 0 | H46: =+'BODEGA EL ARBOLITO'!$G$3 -> 0 | I46: WILLI | J46: =MAX('BODEGA EL ARBOLITO'!A2:A1000) -> 46045
A47: 36 | B47: =+'BODEGA EL GATO'!$B$1 -> BODEGA EL GATO | C47: =+'BODEGA EL GATO'!$B$2 -> YOLYMAR DELGADO | D47: =+'BODEGA EL GATO'!$C$3 -> 13.42 | E47: =+'BODEGA EL GATO'!$D$3 -> 0 | F47: =+'BODEGA EL GATO'!$E$3 -> 0 | G47: =+'BODEGA EL GATO'!$F$3 -> 0 | H47: =+'BODEGA EL GATO'!$G$3 -> 0 | I47: WILLI | J47: =MAX('BODEGA EL GATO'!A2:A1000) -> 46044
A48: 37 | B48: =+'BODEGA EL SOL'!$B$1 -> BODEGA EL SOL | C48: =+'BODEGA EL SOL'!$B$2 -> ROSA VALERO | D48: =+'BODEGA EL SOL'!$C$3 -> 29.52 | E48: =+'BODEGA EL SOL'!$D$3 -> 0 | F48: =+'BODEGA EL SOL'!$E$3 -> 0 | G48: =+'BODEGA EL SOL'!$F$3 -> 0 | H48: =+'BODEGA EL SOL'!$G$3 -> 0 | I48: WILLI | J48: =MAX('BODEGA EL SOL'!A2:A1000) -> 46049
A49: 38 | B49: =+'BODEGA EXPRESS'!$B$1 -> BODEGA EXPRESS | C49: =+'BODEGA EXPRESS'!$B$2 -> GERMAN CALDERON | D49: =+'BODEGA EXPRESS'!$C$3 -> 441.92 | E49: =+'BODEGA EXPRESS'!$D$3 -> 0 | F49: =+'BODEGA EXPRESS'!$E$3 -> 0 | G49: =+'BODEGA EXPRESS'!$F$3 -> -1 | H49: =+'BODEGA EXPRESS'!$G$3 -> 0 | I49: MENOR | J49: =MAX('BODEGA EXPRESS'!A2:A1000) -> 46048
A50: 39 | B50: =+'BODEGA DE CECI'!$B$1 -> BODEGA DE CECI | C50: =+'BODEGA DE CECI'!$B$2 -> 0 | D50: =+'BODEGA DE CECI'!$C$3 -> 0 | E50: =+'BODEGA DE CECI'!$D$3 -> 0 | F50: =+'BODEGA DE CECI'!$E$3 -> 0 | G50: =+'BODEGA DE CECI'!$F$3 -> 0 | H50: =+'BODEGA DE CECI'!$G$3 -> 0 | I50: MENOR | J50: =MAX('BODEGA DE CECI'!A2:A1000) -> 45855
A51: 40 | B51: =+'BODEGA DONITA'!$B$1 -> BODEGA DONITA | C51: =+'BODEGA DONITA'!$B$2 -> YUDY NINO | D51: =+'BODEGA DONITA'!$C$3 -> -0.05 | E51: =+'BODEGA DONITA'!$D$3 -> 0 | F51: =+'BODEGA DONITA'!$E$3 -> 0 | G51: =+'BODEGA DONITA'!$F$3 -> 0 | H51: =+'BODEGA DONITA'!$G$3 -> 0 | I51: WILLI | J51: =MAX('BODEGA DONITA'!A2:A1000) -> 46013
A52: 41 | B52: =+'BODEGA EL GUARO'!$B$1 -> BODEGA EL GUARO | C52: =+'BODEGA EL GUARO'!$B$2 -> SORANYL VILLAMIZAR | D52: =+'BODEGA EL GUARO'!$C$3 -> -0.4 | E52: =+'BODEGA EL GUARO'!$D$3 -> 0 | F52: =+'BODEGA EL GUARO'!$E$3 -> 0 | G52: =+'BODEGA EL GUARO'!$F$3 -> 0 | H52: =+'BODEGA EL GUARO'!$G$3 -> 0 | I52: WILLI | J52: =MAX('BODEGA EL GUARO'!A2:A1000) -> 45999
A53: 42 | B53: =+'BODEGA ESCALANTE'!$B$1 -> BODEGA ESCALANTE | C53: =+'BODEGA ESCALANTE'!$B$2 -> MARIA BAUTISTA | D53: =+'BODEGA ESCALANTE'!$C$3 -> -1.2 | E53: =+'BODEGA ESCALANTE'!$D$3 -> 0 | F53: =+'BODEGA ESCALANTE'!$E$3 -> 0 | G53: =+'BODEGA ESCALANTE'!$F$3 -> 0 | H53: =+'BODEGA ESCALANTE'!$G$3 -> 0 | I53: WILLI | J53: =MAX('BODEGA ESCALANTE'!A2:A1000) -> 45996
A54: 43 | B54: =+'BODEGA LOS CHACAROS'!$B$1 -> BODEGA LOS CHACAROS | C54: =+'BODEGA LOS CHACAROS'!$B$2 -> YANET | D54: =+'BODEGA LOS CHACAROS'!$C$3 -> 0 | E54: =+'BODEGA LOS CHACAROS'!$D$3 -> 2 | F54: =+'BODEGA LOS CHACAROS'!$E$3 -> 0 | G54: =+'BODEGA LOS CHACAROS'!$F$3 -> 0 | H54: =+'BODEGA LOS CHACAROS'!$G$3 -> 0 | I54: WILLI | J54: =MAX('BODEGA LOS CHACAROS'!A2:A1000) -> 46055
A55: 44 | B55: =+'BODEGA MARIA'!$B$1 -> BODEGA MARIA | C55: =+'BODEGA MARIA'!$B$2 -> JANCITO BELLO | D55: =+'BODEGA MARIA'!$C$3 -> 0 | E55: =+'BODEGA MARIA'!$D$3 -> 0 | F55: =+'BODEGA MARIA'!$E$3 -> 0 | G55: =+'BODEGA MARIA'!$F$3 -> 0 | H55: =+'BODEGA MARIA'!$G$3 -> 0 | I55: WILLI | J55: =MAX('BODEGA MARIA'!A2:A1000) -> 45917
A56: 45 | B56: =+'BODEGA MARITZA'!$B$1 -> BODEGA MARITZA | C56: =+'BODEGA MARITZA'!$B$2 -> ROJAS | D56: =+'BODEGA MARITZA'!$C$3 -> 166.64 | E56: =+'BODEGA MARITZA'!$D$3 -> 0 | F56: =+'BODEGA MARITZA'!$E$3 -> 0 | G56: =+'BODEGA MARITZA'!$F$3 -> 0 | H56: =+'BODEGA MARITZA'!$G$3 -> 0 | I56: MENOR | J56: =MAX('BODEGA MARITZA'!A2:A1000) -> 46056
A57: 46 | B57: =+'BODEGA MILAGRO'!$B$1 -> BODEGA MILAGRO | C57: =+'BODEGA MILAGRO'!$B$2 -> MILAGRO BARRETO | D57: =+'BODEGA MILAGRO'!$C$3 -> 0.09 | E57: =+'BODEGA MILAGRO'!$D$3 -> 0 | F57: =+'BODEGA MILAGRO'!$E$3 -> 0 | G57: =+'BODEGA MILAGRO'!$F$3 -> 0 | H57: =+'BODEGA MILAGRO'!$G$3 -> 0 | I57: WILLI | J57: =MAX('BODEGA MILAGRO'!A2:A1000) -> 46055
A58: 47 | B58: =+'BODEGA MILAGROS'!$B$1 -> BODEGA MILAGROS | C58: =+'BODEGA MILAGROS'!$B$2 -> MILAGROS ZAMBRANO | D58: =+'BODEGA MILAGROS'!$C$3 -> 0.96 | E58: =+'BODEGA MILAGROS'!$D$3 -> 0 | F58: =+'BODEGA MILAGROS'!$E$3 -> 0 | G58: =+'BODEGA MILAGROS'!$F$3 -> 0 | H58: =+'BODEGA MILAGROS'!$G$3 -> 0 | I58: MENOR | J58: =MAX('BODEGA MILAGROS'!A2:A1000) -> 46013
A59: 48 | B59: =+'BODEGA NANCYTA'!$B$1 -> BODEGA NANCYTA | C59: =+'BODEGA NANCYTA'!$B$2 -> NANCY MONSALVE | D59: =+'BODEGA NANCYTA'!$C$3 -> 63.67 | E59: =+'BODEGA NANCYTA'!$D$3 -> 0 | F59: =+'BODEGA NANCYTA'!$E$3 -> 0 | G59: =+'BODEGA NANCYTA'!$F$3 -> 0 | H59: =+'BODEGA NANCYTA'!$G$3 -> 0 | I59: WILLI | J59: =MAX('BODEGA NANCYTA'!A2:A1000) -> 46056
A60: 49 | B60: =+'BODEGA NAZARENO'!$B$1 -> BODEGA NAZARENO | C60: =+'BODEGA NAZARENO'!$B$2 -> CAROLINA SANCHEZ | D60: =+'BODEGA NAZARENO'!$C$3 -> 305.47 | E60: =+'BODEGA NAZARENO'!$D$3 -> 0 | F60: =+'BODEGA NAZARENO'!$E$3 -> 0 | G60: =+'BODEGA NAZARENO'!$F$3 -> 0 | H60: =+'BODEGA NAZARENO'!$G$3 -> 0 | I60: WILLI | J60: =MAX('BODEGA NAZARENO'!A2:A1000) -> 46050
A61: 50 | B61: =+'BODEGA Y PAPELERIA REY'!$B$1 -> BODEGA Y PAPELERIA REY | C61: =+'BODEGA Y PAPELERIA REY'!$B$2 -> EUDES REY | D61: =+'BODEGA Y PAPELERIA REY'!$C$3 -> 230.945 | E61: =+'BODEGA Y PAPELERIA REY'!$D$3 -> 0 | F61: =+'BODEGA Y PAPELERIA REY'!$E$3 -> 0 | G61: =+'BODEGA Y PAPELERIA REY'!$F$3 -> 0 | H61: =+'BODEGA Y PAPELERIA REY'!$G$3 -> 0 | I61: WILLI | J61: =MAX('BODEGA Y PAPELERIA REY'!A2:A1000) -> 46052
A62: 51 | B62: =+'BODEGON AGUA LINDA'!$B$1 -> BODEGON AGUA LINDA | C62: =+'BODEGON AGUA LINDA'!$B$2 -> 0 | D62: =+'BODEGON AGUA LINDA'!$C$3 -> 171.7 | E62: =+'BODEGON AGUA LINDA'!$D$3 -> 1 | F62: =+'BODEGON AGUA LINDA'!$E$3 -> 0 | G62: =+'BODEGON AGUA LINDA'!$F$3 -> 0 | H62: =+'BODEGON AGUA LINDA'!$G$3 -> 0 | I62: MENOR | J62: =MAX('BODEGON AGUA LINDA'!A2:A1000) -> 46045
A63: 52 | B63: =+'BODEGON ANDREA''S'!$B$1 -> BODEGON ANDREA'S | C63: =+'BODEGON ANDREA''S'!$B$2 -> 0 | D63: =+'BODEGON ANDREA''S'!$C$3 -> 0 | E63: =+'BODEGON ANDREA''S'!$D$3 -> 0 | F63: =+'BODEGON ANDREA''S'!$E$3 -> 0 | G63: =+'BODEGON ANDREA''S'!$F$3 -> 0 | H63: =+'BODEGON ANDREA''S'!$G$3 -> 0 | I63: MENOR | J63: =MAX('BODEGON ANDREA''S'!A2:A1000) -> 46042
A64: 53 | B64: =+'BODEGON DE ELIDA'!$B$1 -> BODEGON DE ELIDA | C64: =+'BODEGON DE ELIDA'!$B$2 -> 0 | D64: =+'BODEGON DE ELIDA'!$C$3 -> 41.73 | E64: =+'BODEGON DE ELIDA'!$D$3 -> 1 | F64: =+'BODEGON DE ELIDA'!$E$3 -> 0 | G64: =+'BODEGON DE ELIDA'!$F$3 -> 0 | H64: =+'BODEGON DE ELIDA'!$G$3 -> 0 | I64: MENOR
A65: 54 | B65: =+'BODEGON DE OLGA'!$B$1 -> BODEGON DE OLGA | C65: =+'BODEGON DE OLGA'!$B$2 -> ANTONIO DELGADO | D65: =+'BODEGON DE OLGA'!$C$3 -> 344.36 | E65: =+'BODEGON DE OLGA'!$D$3 -> 6 | F65: =+'BODEGON DE OLGA'!$E$3 -> 0 | G65: =+'BODEGON DE OLGA'!$F$3 -> 0 | H65: =+'BODEGON DE OLGA'!$G$3 -> 0 | I65: ROBERTO WILLI | J65: =MAX('BODEGON DE OLGA'!A2:A1000) -> 46056
A66: 55 | B66: =+'BODEGON D KSA'!$B$1 -> BODEGON D KSA | C66: =+'BODEGON D KSA'!$B$2 -> FERNANDO HERNANDEZ | D66: =+'BODEGON D KSA'!$C$3 -> 78.29 | E66: =+'BODEGON D KSA'!$D$3 -> 0 | F66: =+'BODEGON D KSA'!$E$3 -> 0 | G66: =+'BODEGON D KSA'!$F$3 -> 0 | H66: =+'BODEGON D KSA'!$G$3 -> 0 | I66: WILLI | J66: =MAX('BODEGON D KSA'!A2:A1000) -> 46056
A67: 56 | B67: =+'BODEGON D Y JD'!$B$1 -> BODEGON D Y JD | C67: =+'BODEGON D Y JD'!$B$2 -> GLORIA PERNIA | D67: =+'BODEGON D Y JD'!$C$3 -> 0 | E67: =+'BODEGON D Y JD'!$D$3 -> 0 | F67: =+'BODEGON D Y JD'!$E$3 -> 0 | G67: =+'BODEGON D Y JD'!$F$3 -> 0 | H67: =+'BODEGON D Y JD'!$G$3 -> 0 | I67: WILLI | J67: =MAX('BODEGON D Y JD'!A3:A1001) -> 46055
A68: 57 | B68: =+'BODEGON EL COMPADRE'!$B$1 -> BODEGON EL COMPADRE | C68: =+'BODEGON EL COMPADRE'!$B$2 -> 0 | D68: =+'BODEGON EL COMPADRE'!$C$3 -> 147.59 | E68: =+'BODEGON EL COMPADRE'!$D$3 -> 0 | F68: =+'BODEGON EL COMPADRE'!$E$3 -> 0 | G68: =+'BODEGON EL COMPADRE'!$F$3 -> 0 | H68: =+'BODEGON EL COMPADRE'!$G$3 -> 0 | I68: ROBERTO | J68: =MAX('BODEGON EL COMPADRE'!A2:A1000) -> 46044
A69: 58 | B69: =+'BODEGON ENDER GUERRERO'!$B$1 -> BODEGON ENDER | C69: =+'BODEGON ENDER GUERRERO'!$B$2 -> ENDER GUERRERO | D69: =+'BODEGON ENDER GUERRERO'!$C$3 -> 1521.34 | E69: =+'BODEGON ENDER GUERRERO'!$D$3 -> 0 | F69: =+'BODEGON ENDER GUERRERO'!$E$3 -> 0 | G69: =+'BODEGON ENDER GUERRERO'!$F$3 -> 0 | H69: =+'BODEGON ENDER GUERRERO'!$G$3 -> 0 | I69: WILLI | J69: =MAX('BODEGON ENDER GUERRERO'!A2:A1000) -> 46052
A70: 59 | B70: =+'BODEGON ENZO'!$B$1 -> BODEGON ENZO | C70: =+'BODEGON ENZO'!$B$2 -> 0 | D70: =+'BODEGON ENZO'!$C$3 -> 120.58 | E70: =+'BODEGON ENZO'!$D$3 -> 0 | F70: =+'BODEGON ENZO'!$E$3 -> 0 | G70: =+'BODEGON ENZO'!$F$3 -> 0 | H70: =+'BODEGON ENZO'!$G$3 -> 0 | I70: WILLI | J70: =MAX('BODEGON ENZO'!A2:A1000) -> 46056
A71: 60 | B71: =+'BODEGON EXPRESS'!$B$1 -> BODEGON EXPRESS | C71: =+'BODEGON EXPRESS'!$B$2 -> NORLAIDA | D71: =+'BODEGON EXPRESS'!$C$3 -> 76.964 | E71: =+'BODEGON EXPRESS'!$D$3 -> 0 | F71: =+'BODEGON EXPRESS'!$E$3 -> 0 | G71: =+'BODEGON EXPRESS'!$F$3 -> 0 | H71: =+'BODEGON EXPRESS'!$G$3 -> 0 | I71: MENOR | J71: =MAX('BODEGON EXPRESS'!A2:A1000) -> 46056
A72: 61 | B72: =+'BODEGON EXPRESS LA ESMERALDA'!$B$1 -> BODEGON EXPRESS LA ESMERALDA | C72: =+'BODEGON EXPRESS LA ESMERALDA'!$B$2 -> 0 | D72: =+'BODEGON EXPRESS LA ESMERALDA'!$C$3 -> 377.91 | E72: =+'BODEGON EXPRESS LA ESMERALDA'!$D$3 -> 1 | F72: =+'BODEGON EXPRESS LA ESMERALDA'!$E$3 -> 0 | G72: =+'BODEGON EXPRESS LA ESMERALDA'!$F$3 -> 0 | H72: =+'BODEGON EXPRESS LA ESMERALDA'!$G$3 -> 0 | I72: WILLI | J72: =MAX('BODEGON EXPRESS LA ESMERALDA'!A2:A1000) -> 46050
A73: 62 | B73: =+'BODEGON EXPRESS MARI'!$B$1 -> BODEGON EXPRESS MOLINA | C73: =+'BODEGON EXPRESS MARI'!$B$2 -> MARIFLOR MOLINA | D73: =+'BODEGON EXPRESS MARI'!$C$3 -> 50.19 | E73: =+'BODEGON EXPRESS MARI'!$D$3 -> -1 | F73: =+'BODEGON EXPRESS MARI'!$E$3 -> 0 | G73: =+'BODEGON EXPRESS MARI'!$F$3 -> 0 | H73: =+'BODEGON EXPRESS MARI'!$G$3 -> 0 | I73: WILLI | J73: =MAX('BODEGON EXPRESS MARI'!A2:A1000) -> 46055
A74: 63 | B74: =+'BODEGON EXPRESS GREGORI'!$B$1 -> BODEGON EXPRESS GREGORI | C74: =+'BODEGON EXPRESS GREGORI'!$B$2 -> NEILA | D74: =+'BODEGON EXPRESS GREGORI'!$C$3 -> 223.69 | E74: =+'BODEGON EXPRESS GREGORI'!$D$3 -> 0 | F74: =+'BODEGON EXPRESS GREGORI'!$E$3 -> 0 | G74: =+'BODEGON EXPRESS GREGORI'!$F$3 -> 0 | H74: =+'BODEGON EXPRESS GREGORI'!$G$3 -> 0 | I74: WILLI | J74: =MAX('BODEGON EXPRESS GREGORI'!A2:A1000) -> 46045
A75: 64 | B75: =+'BODEGON ESQUINA PARAMILLO'!$B$1 -> BODEGON ESQUINA PARAMILLO | C75: =+'BODEGON ESQUINA PARAMILLO'!$B$2 -> BIANCA MASERATI | D75: =+'BODEGON ESQUINA PARAMILLO'!$C$3 -> 327.72 | E75: =+'BODEGON ESQUINA PARAMILLO'!$D$3 -> 0 | F75: =+'BODEGON ESQUINA PARAMILLO'!$E$3 -> 0 | G75: =+'BODEGON ESQUINA PARAMILLO'!$F$3 -> 0 | H75: =+'BODEGON ESQUINA PARAMILLO'!$G$3 -> 0 | I75: WILLI | J75: =MAX('BODEGON ESQUINA PARAMILLO'!A2:A1000) -> 46056
A76: 65 | B76: =+'BODEGON GARCIAS'!$B$1 -> BODEGON GARCIAS | C76: =+'BODEGON GARCIAS'!$B$2 -> GENESIS GARCIAS | D76: =+'BODEGON GARCIAS'!$C$3 -> 45.35 | E76: =+'BODEGON GARCIAS'!$D$3 -> 0 | F76: =+'BODEGON GARCIAS'!$E$3 -> 0 | G76: =+'BODEGON GARCIAS'!$F$3 -> 0 | H76: =+'BODEGON GARCIAS'!$G$3 -> 0 | I76: WILLI | J76: =MAX('BODEGON GARCIAS'!A2:A1000) -> 46052
A77: 66 | B77: =+'BODEGON JUANCHO'!$B$1 -> BODEGON JUANCHO | C77: =+'BODEGON JUANCHO'!$B$2 -> 0 | D77: =+'BODEGON JUANCHO'!$C$3 -> 7.2 | E77: =+'BODEGON JUANCHO'!$D$3 -> 0 | F77: =+'BODEGON JUANCHO'!$E$3 -> 0 | G77: =+'BODEGON JUANCHO'!$F$3 -> 0 | H77: =+'BODEGON JUANCHO'!$G$3 -> 0 | I77: MENOR | J77: =MAX('BODEGON JUANCHO'!A2:A1000) -> 46013
A78: 67 | B78: =+'BODEGON KATERIN'!$B$1 -> BODEGON KATERIN | C78: =+'BODEGON KATERIN'!$B$2 -> ROMERO | D78: =+'BODEGON KATERIN'!$C$3 -> -0.96 | E78: =+'BODEGON KATERIN'!$D$3 -> 0 | F78: =+'BODEGON KATERIN'!$E$3 -> 0 | G78: =+'BODEGON KATERIN'!$F$3 -> 0 | H78: =+'BODEGON KATERIN'!$G$3 -> 0 | I78: MENOR | J78: =MAX('BODEGON KATERIN'!A2:A1000) -> 45840
A79: 68 | B79: =+'BODEGON LA ESQUINA DE LUIS'!$B$1 -> BODEGON LA ESQUINA DE LUIS | C79: =+'BODEGON LA ESQUINA DE LUIS'!$B$2 -> DIANA CALDERON | D79: =+'BODEGON LA ESQUINA DE LUIS'!$C$3 -> 136.54 | E79: =+'BODEGON LA ESQUINA DE LUIS'!$D$3 -> 0 | F79: =+'BODEGON LA ESQUINA DE LUIS'!$E$3 -> 0 | G79: =+'BODEGON LA ESQUINA DE LUIS'!$F$3 -> 0 | H79: =+'BODEGON LA ESQUINA DE LUIS'!$G$3 -> 0 | I79: WILLI | J79: =MAX('BODEGON LA ESQUINA DE LUIS'!A2:A1000) -> 45995
A80: 69 | B80: =+'BODEGON LINARES'!$B$1 -> BODEGON LINARES | C80: =+'BODEGON LINARES'!$B$2 -> JUAN PABON | D80: =+'BODEGON LINARES'!$C$3 -> 36.07 | E80: =+'BODEGON LINARES'!$D$3 -> 1 | F80: =+'BODEGON LINARES'!$E$3 -> 0 | G80: =+'BODEGON LINARES'!$F$3 -> 0 | H80: =+'BODEGON LINARES'!$G$3 -> 0 | I80: WILLI | J80: =MAX('BODEGON LINARES'!A2:A1000) -> 46052
A81: 70 | B81: =+'BODEGON LOS NONOS'!$B$1 -> BODEGON LOS NONOS | C81: =+'BODEGON LOS NONOS'!$B$2 -> 0 | D81: =+'BODEGON LOS NONOS'!$C$3 -> 2853.59 | E81: =+'BODEGON LOS NONOS'!$D$3 -> 0 | F81: =+'BODEGON LOS NONOS'!$E$3 -> 0 | G81: =+'BODEGON LOS NONOS'!$F$3 -> 0 | H81: =+'BODEGON LOS NONOS'!$G$3 -> 0 | I81: MENOR | J81: =MAX('BODEGON LOS NONOS'!A2:A1000) -> 46056
A82: 71 | B82: =+'BODEGON MACHIRI'!$B$1 -> BODEGON MACHIRI | C82: =+'BODEGON MACHIRI'!$B$2 -> 0 | D82: =+'BODEGON MACHIRI'!$C$3 -> 0 | E82: =+'BODEGON MACHIRI'!$D$3 -> 0 | F82: =+'BODEGON MACHIRI'!$E$3 -> 0 | G82: =+'BODEGON MACHIRI'!$F$3 -> 0 | H82: =+'BODEGON MACHIRI'!$G$3 -> 0 | I82: ROBERTO | J82: =MAX('BODEGON MACHIRI'!A2:A1000) -> 45839
A83: 72 | B83: =+'BODEGON MKM'!$B$1 -> BODEGON MKM | C83: =+'BODEGON MKM'!$B$2 -> KARINA CHAO | D83: =+'BODEGON MKM'!$C$3 -> 0.69 | E83: =+'BODEGON MKM'!$D$3 -> 2 | F83: =+'BODEGON MKM'!$E$3 -> 0 | G83: =+'BODEGON MKM'!$F$3 -> 0 | H83: =+'BODEGON MKM'!$G$3 -> 0 | I83: WILLI | J83: =MAX('BODEGON MKM'!A2:A1000) -> 46056
A84: 73 | B84: =+'BODEGON SEVILLANA'!$B$1 -> BODEGON SEVILLANA | C84: =+'BODEGON SEVILLANA'!$B$2 -> YUSMARVIC | D84: =+'BODEGON SEVILLANA'!$C$3 -> 1198.2 | E84: =+'BODEGON SEVILLANA'!$D$3 -> 5 | F84: =+'BODEGON SEVILLANA'!$E$3 -> 0 | G84: =+'BODEGON SEVILLANA'!$F$3 -> 0 | H84: =+'BODEGON SEVILLANA'!$G$3 -> 0 | I84: ROBERTO | J84: =MAX('BODEGON SEVILLANA'!A2:A1000) -> 46056
A85: 74 | B85: =+'BODEGON TERESITA'!$B$1 -> BODEGON TERESITA | C85: =+'BODEGON TERESITA'!$B$2 -> TERESA ALBARRACIN | D85: =+'BODEGON TERESITA'!$C$3 -> -0.16 | E85: =+'BODEGON TERESITA'!$D$3 -> 0 | F85: =+'BODEGON TERESITA'!$E$3 -> 0 | G85: =+'BODEGON TERESITA'!$F$3 -> 0 | H85: =+'BODEGON TERESITA'!$G$3 -> 0 | I85: WILLI | J85: =MAX('BODEGON TERESITA'!A2:A1000) -> 46050
A86: 75 | B86: =+'BODEGON UNICO'!$B$1 -> BODEGON UNICO | C86: =+'BODEGON UNICO'!$B$2 -> 0 | D86: =+'BODEGON UNICO'!$C$3 -> 555.45 | E86: =+'BODEGON UNICO'!$D$3 -> 2 | F86: =+'BODEGON UNICO'!$E$3 -> 0 | G86: =+'BODEGON UNICO'!$F$3 -> 0 | H86: =+'BODEGON UNICO'!$G$3 -> 0 | I86: MENOR | J86: =MAX('BODEGON UNICO'!A2:A1000) -> 46049
A87: 76 | B87: =+'CAFE RACER'!$B$1 -> CAFE RACER | C87: =+'CAFE RACER'!$B$2 -> 0 | D87: =+'CAFE RACER'!$C$3 -> 434.46 | E87: =+'CAFE RACER'!$D$3 -> 3 | F87: =+'CAFE RACER'!$E$3 -> 0 | G87: =+'CAFE RACER'!$F$3 -> 0 | H87: =+'CAFE RACER'!$G$3 -> 0 | I87: ROBERTO | J87: =MAX('CAFE RACER'!A2:A1000) -> 46055
A88: 77 | B88: =+'CAMPO MARKET'!$B$1 -> CAMPO MARKET | C88: =+'CAMPO MARKET'!$B$2 -> ESCARLET LOPEZ | D88: =+'CAMPO MARKET'!$C$3 -> 184.73 | E88: =+'CAMPO MARKET'!$D$3 -> 0 | F88: =+'CAMPO MARKET'!$E$3 -> 0 | G88: =+'CAMPO MARKET'!$F$3 -> 0 | H88: =+'CAMPO MARKET'!$G$3 -> 0 | I88: WILLI | J88: =MAX('CAMPO MARKET'!A2:A1000) -> 46051
A89: 78 | B89: =+'CARNICERIA 2009'!$B$1 -> CARNICERIA 2009 | C89: =+'CARNICERIA 2009'!$B$2 -> 0 | D89: =+'CARNICERIA 2009'!$C$3 -> -2.107 | E89: =+'CARNICERIA 2009'!$D$3 -> 0 | F89: =+'CARNICERIA 2009'!$E$3 -> 0 | G89: =+'CARNICERIA 2009'!$F$3 -> 0 | H89: =+'CARNICERIA 2009'!$G$3 -> 0 | I89: MENOR | J89: =MAX('CARNICERIA 2009'!A2:A1000) -> 46051
A90: 79 | B90: =+'CARNICERIA KARINA'!$B$1 -> CARNICERIA KARINA | C90: =+'CARNICERIA KARINA'!$B$2 -> KARLA | D90: =+'CARNICERIA KARINA'!$C$3 -> 126.63 | E90: =+'CARNICERIA KARINA'!$D$3 -> 0 | F90: =+'CARNICERIA KARINA'!$E$3 -> 0 | G90: =+'CARNICERIA KARINA'!$F$3 -> 0 | H90: =+'CARNICERIA KARINA'!$G$3 -> 0 | I90: MENOR | J90: =MAX('CARNICERIA KARINA'!A2:A1000) -> 46052
A91: 80 | B91: =+'CARNICERIA MARTA'!$B$1 -> CARNICERIA MARTA | C91: =+'CARNICERIA MARTA'!$B$2 -> 0 | D91: =+'CARNICERIA MARTA'!$C$3 -> -0.01 | E91: =+'CARNICERIA MARTA'!$D$3 -> 0 | F91: =+'CARNICERIA MARTA'!$E$3 -> 0 | G91: =+'CARNICERIA MARTA'!$F$3 -> 0 | H91: =+'CARNICERIA MARTA'!$G$3 -> 0 | I91: MENOR | J91: =MAX('CARNICERIA MARTA'!A2:A1000) -> 45848
A92: 81 | B92: =+'CAROL KARDEIGON'!$B$1 -> CAROL KARDEIGON | C92: =+'CAROL KARDEIGON'!$B$2 -> 0 | D92: =+'CAROL KARDEIGON'!$C$3 -> 641.71 | E92: =+'CAROL KARDEIGON'!$D$3 -> 0 | F92: =+'CAROL KARDEIGON'!$E$3 -> 0 | G92: =+'CAROL KARDEIGON'!$F$3 -> 0 | H92: =+'CAROL KARDEIGON'!$G$3 -> 0 | I92: WILLI | J92: =MAX('CAROL KARDEIGON'!A2:A1000) -> 46052
A93: 82 | B93: =+'CASA EXPRESS'!$B$1 -> CASA EXPRESS | C93: =+'CASA EXPRESS'!$B$2 -> DURAN | D93: =+'CASA EXPRESS'!$C$3 -> -1.02 | E93: =+'CASA EXPRESS'!$D$3 -> 0 | F93: =+'CASA EXPRESS'!$E$3 -> 0 | G93: =+'CASA EXPRESS'!$F$3 -> 0 | H93: =+'CASA EXPRESS'!$G$3 -> 0 | I93: MENOR | J93: =MAX('CASA EXPRESS'!A2:A1000) -> 45993
A94: 83 | B94: =+'CCP PARAMILLO'!$B$1 -> CCP PARAMILLO | C94: =+'CCP PARAMILLO'!$B$2 -> FREDDY JAUREGY | D94: =+'CCP PARAMILLO'!$C$3 -> 118.62 | E94: =+'CCP PARAMILLO'!$D$3 -> 0 | F94: =+'CCP PARAMILLO'!$E$3 -> 0 | G94: =+'CCP PARAMILLO'!$F$3 -> 0 | H94: =+'CCP PARAMILLO'!$G$3 -> 9.84 | I94: WILLI | J94: =MAX('CCP PARAMILLO'!A2:A1000) -> 46035
A95: 84 | B95: =+'CECILIA EMPANADAS'!$B$1 -> CECILIA EMPANADAS | C95: =+'CECILIA EMPANADAS'!$B$2 -> 0 | D95: =+'CECILIA EMPANADAS'!$C$3 -> 29 | E95: =+'CECILIA EMPANADAS'!$D$3 -> 0 | F95: =+'CECILIA EMPANADAS'!$E$3 -> 0 | G95: =+'CECILIA EMPANADAS'!$F$3 -> 0 | H95: =+'CECILIA EMPANADAS'!$G$3 -> 0 | I95: MENOR | J95: =MAX('CECILIA EMPANADAS'!A2:A1000) -> 46052
A96: 85 | B96: =+CEMUCA!$B$1 -> CEMUCA | C96: =+CEMUCA!$B$2 -> 0 | D96: =+CEMUCA!$C$3 -> 0.26 | E96: =+CEMUCA!$D$3 -> 0 | F96: =+CEMUCA!$E$3 -> 0 | G96: =+CEMUCA!$F$3 -> 0 | H96: =+CEMUCA!$G$3 -> 0 | I96: WILLI | J96: =MAX(CEMUCA!A2:A1000) -> 45942
A97: 86 | B97: =+'CHARCUTERIA LA TOICA'!$B$1 -> CHARCUTERIA LA TOICA | C97: =+'CHARCUTERIA LA TOICA'!$B$2 -> YELSI CAMARGO | D97: =+'CHARCUTERIA LA TOICA'!$C$3 -> 297.01 | E97: =+'CHARCUTERIA LA TOICA'!$D$3 -> 0 | F97: =+'CHARCUTERIA LA TOICA'!$E$3 -> 0 | G97: =+'CHARCUTERIA LA TOICA'!$F$3 -> 0 | H97: =+'CHARCUTERIA LA TOICA'!$G$3 -> 0 | I97: WILLI | J97: =MAX('CHARCUTERIA LA TOICA'!A2:A1000) -> 46052
A98: 87 | B98: =+'CHACARO CREAM'!$B$1 -> CHACARO CREAM | C98: =+'CHACARO CREAM'!$B$2 -> 0 | D98: =+'CHACARO CREAM'!$C$3 -> 0 | E98: =+'CHACARO CREAM'!$D$3 -> 1 | F98: =+'CHACARO CREAM'!$E$3 -> 0 | G98: =+'CHACARO CREAM'!$F$3 -> 0 | H98: =+'CHACARO CREAM'!$G$3 -> 0 | I98: MENOR
A99: 88 | B99: =+'COLEGIO SANTISIMA TRINIDAD'!$B$1 -> COLEGIO SANTISIMA TRINIDAD | C99: =+'COLEGIO SANTISIMA TRINIDAD'!$B$2 -> 0 | D99: =+'COLEGIO SANTISIMA TRINIDAD'!$C$3 -> 3.42 | E99: =+'COLEGIO SANTISIMA TRINIDAD'!$D$3 -> 0 | F99: =+'COLEGIO SANTISIMA TRINIDAD'!$E$3 -> 0 | G99: =+'COLEGIO SANTISIMA TRINIDAD'!$F$3 -> 0 | H99: =+'COLEGIO SANTISIMA TRINIDAD'!$G$3 -> 0 | I99: MENOR | J99: =MAX('COLEGIO SANTISIMA TRINIDAD'!A2:A1000) -> 46052
A100: 89 | B100: =+'COLEGIO SANTO CRISTO'!$B$1 -> COLEGIO SANTO CRISTO | C100: =+'COLEGIO SANTO CRISTO'!$B$2 -> 0 | D100: =+'COLEGIO SANTO CRISTO'!$C$3 -> 0 | E100: =+'COLEGIO SANTO CRISTO'!$D$3 -> 0 | F100: =+'COLEGIO SANTO CRISTO'!$E$3 -> 0 | G100: =+'COLEGIO SANTO CRISTO'!$F$3 -> 0 | H100: =+'COLEGIO SANTO CRISTO'!$G$3 -> 0 | I100: MENOR
...

Sheet ABASTO ANTONY
A1: CLIENTE | B1: ABASTO ANTONY
A2: NOMBRE
A3: TOTALES | C3: =SUM(C$4:C$1048576) -> 452.01 | D3: =SUM(D$4:D$1048576) -> 1 | E3: =SUM(E$5:E$1048576) -> 0 | F3: =SUM(F$5:F$1048576) -> 0 | G3: =SUM(G$5:G$1048576) -> 0
A4: FECHA | B4: F- E- T- | C4: DEUDA Y ABONOS | D4: VACIO 1/4 | E4: VACIO 350 | F4: VACIO 1.25 | G4: RETECION
A5: 45815 | B5: F | C5: 53.29 | D5: 1
A6: 45815 | B6: F | C6: 70.6
A7: 45815 | B7: F | C7: 47.6
A8: 45821 | B8: T | C8: -171.49
A9: 45821 | B9: F | C9: 48.5
A10: 45821 | B10: F | C10: 18.5
A11: 45821 | B11: F | C11: 245.76
A12: 45828 | B12: F | C12: 30.8 | D12: -1
A13: 45828 | B13: F | C13: 52.06
A14: 45828 | B14: F | C14: 60.4
A15: 45831 | B15: T | C15: -312.75
A16: 45838 | B16: T | C16: -143.26
A17: 45842 | B17: F | C17: 82.23
A18: 45842 | B18: F | C18: 93.28
A19: 45842 | B19: F | C19: 16.62
A20: 45849 | B20: T | C20: -192.13
A21: 45849 | B21: F | C21: 96.57
A22: 45849 | B22: F | C22: 18.29
A23: 45849 | B23: F | C23: 39.32
A24: 45849 | B24: F | C24: 62.4 | D24: 3
A25: 45859 | B25: T | C25: -216.59
A26: 45859 | B26: T | C26: -181.58
A27: 45856 | B27: F | C27: 105.03 | D27: -2
A28: 45856 | B28: F | C28: =72.61+3.91 -> 76.52
A29: 45863 | B29: F | C29: 58.9
A30: 45863 | B30: F | C30: 92.16
A31: 45867 | B31: T | C31: -1029.72
A32: 45867 | B32: T | C32: -151.06
A33: 45867 | B33: F | C33: 39
A34: 45867 | B34: F | C34: 863.4
A35: 45867 | B35: F | C35: 117.32
A36: 45870 | B36: F | C36: 137.01
A37: 45870 | B37: F | C37: 148.71
A38: 45870 | B38: F | C38: 9.86
A39: 45877 | B39: T | C39: -295.58
A40: 45877 | B40: T | C40: -384.42
... A62: 45905 | B62: F | C62: 23.08
A63: 45905 | B63: F | C63: 20.8 | D63: 1
A64: 45911 | B64: T | C64: -190.2
A65: 45912 | B65: T | C65: -157.3
A66: 45916 | B66: T | C66: -249.3
A67: 45912 | B67: F | D67: -2
A68: 45912 | B68: F | C68: 413.32
A69: 45912 | B69: F | C69: 23.8
A70: 45915 | B70: T | C70: -186.98
A71: 45917 | B71: T | C71: -154.43
A72: 45918 | B72: T | C72: -244.14
A73: 45919 | B73: F | C73: 57.15
A74: 45919 | B74: F | C74: 461.08
A75: 45919 | B75: F | C75: 10.34
A76: 45922 | B76: T | C76: -549.82
A77: 45926 | B77: F | C77: 38.65
A78: 45926 | B78: F | C78: 125.88
A79: 45926 | B79: F | C79: 8.04
... A85: 45936 | B85: T | C85: -841.77
A86: 45940 | B86: F | C86: 77.58 | D86: 1
A87: 45940 | B87: F | C87: 302.36
A88: 45940 | B88: F | C88: 31.7
A89: 45940 | B89: F | C89: 46
A90: 45947 | B90: F | C90: 75.26
A91: 45947 | B91: F | C91: 118.08
A92: 45947 | B92: F | C92: 21.36
A93: 45950 | B93: T | C93: -291.72
A94: 45950 | B94: T | C94: -395.61
A95: 45954 | B95: F | C95: 51.18
A96: 45954 | B96: F | C96: 447.25
A97: 45954 | B97: F | C97: 73.83
A98: 45961 | B98: T | C98: -567.28
... A135: 46052 | B135: % | C135: -7.2

Sheet ABASTO DON MARCOS
A1: CLIENTE | B1: ABASTO DON MARCOS
A2: NOMBRE | B2: ANA ZAMBRANO
A3: TOTALES | C3: =SUM(C$4:C$1048576) -> 98.01 | D3: =SUM(D$4:D$1048576) -> 0 | E3: =SUM(E$5:E$1048576) -> 0 | F3: =SUM(F$5:F$1048576) -> 0 | G3: =SUM(G$5:G$1048576) -> 0
A4: FECHA | B4: F- E- T- | C4: DEUDA Y ABONOS | D4: VACIO 1/4 | E4: VACIO 350 | F4: VACIO 1.25 | G4: RETECION
A5: 45848 | B5: F | C5: 15.85
A6: 45863 | B6: T | C6: -15.86
A7: 45869 | B7: F | C7: 41
A8: 45880 | B8: T | C8: -40.42
A9: 45877 | B9: F | C9: 34.98
A10: 45889 | B10: T | C10: -29.62
A11: 45893 | B11: T | C11: -62.47
A12: 45891 | B12: F | C12: 113.83
A13: 45899 | B13: F | C13: 46.83
A14: 45901 | B14: T | C14: -46.83
A15: 45901 | B15: T | C15: -25.73
A16: 45901 | B16: T | C16: -31.27
... A53: 46055 | B53: T | C53: -130

Sheet ABASTO GLORIMAR
A1: CLIENTE | B1: ABASTO GLORIMAR
A2: NOMBRE
A3: TOTALES | C3: =SUM(C$4:C$1048576) -> 110.22 | D3: =SUM(D$4:D$1048576) -> 2 | E3: =SUM(E$5:E$1048576) -> 0 | F3: =SUM(F$5:F$1048576) -> 0 | G3: =SUM(G$5:G$1048576) -> 0
A4: FECHA | B4: F- E- T- | C4: DEUDA Y ABONOS | D4: VACIO 1/4 | E4: VACIO 350 | F4: VACIO 1.25 | G4: RETECION
A5: 45815 | B5: F | C5: 44.6
A6: 45815 | B6: F | C6: 61.9
A7: 45817 | B7: T | C7: -106.54
A8: 45820 | B8: F | C8: 48.2
A9: 45820 | B9: F | C9: 35.6
A10: 45827 | B10: T | C10: -83.28
A11: 45827 | B11: F | C11: 1514 | D11: 11
A12: 45827 | B12: F | C12: 15.85
A13: 45834 | B13: T | C13: -1529.85
A14: 45834 | B14: F | C14: 579.8 | D14: -7
A15: 45834 | B15: F | C15: 29.34
A16: 45835 | B16: T | C16: -459.14
A17: 45841 | B17: T | C17: -150
A18: 45841 | B18: V | D18: -4
A19: 45841 | B19: F | C19: 31.7
A20: 45845 | B20: T | C20: -31.78
A21: 45848 | B21: F | C21: 1472.6 | D21: 24
A22: 45848 | B22: F | C22: 25.69
A23: 45848 | B23: F | C23: 15.1
A24: 45848 | B24: F | C24: 145.28
A25: 45848 | B25: F | C25: 21.56
A26: 45852 | B26: E | C26: -1497.29
A27: 45860 | B27: F | C27: 385.5 | D27: -24
A28: 45860 | B28: F | C28: 62.7
A29: 45866 | B29: T | C29: -182.4
A30: 45866 | B30: T | C30: -449.14
A31: 45868 | B31: F | C31: 363.6
A32: 45873 | B32: T | C32: -363.6
A33: 45875 | B33: F | C33: 1129.2
A34: 45875 | B34: F | C34: 96.44
A35: 45876 | B35: T | C35: -612.82
A36: 45876 | B36: T | C36: -612.82
A37: 45876 | B37: T | C37: -542.41
A38: 45877 | B38: T | C38: -390.39
A39: 45877 | B39: F | C39: 932.8 | D39: 46
A40: 45882 | B40: F | C40: 35.4 | D40: -33
A41: 45882 | B41: F | C41: 9
A42: 45888 | B42: T | C42: -44.4
A43: 45889 | B43: F | C43: 666.6 | D43: -13
A44: 45889 | B44: F | C44: 31.7
A45: 45891 | B45: T | C45: -342.77
A46: 45891 | B46: T | C46: -355.47
A47: 45895 | B47: T | C47: -572.1
A48: 45895 | B48: F | C48: 540.4
A49: 45895 | B49: F | C49: 31.7
A50: 45897 | B50: T | C50: -58.44
A51: 45897 | B51: F | C51: 58.44
A52: 45904 | B52: F | C52: 915.2
A53: 45904 | B53: F | C53: 9
A54: 45904 | B54: F | C54: 15
A55: 45905 | B55: T | C55: -15
... A94: 45985 | B94: T | C94: -122.86
A95: 45988 | B95: F | C95: 1147.52 | D95: 2
A96: 45988 | B96: F | C96: 83.56
A97: 45992 | B97: T | C97: -424.53
A98: 45992 | B98: T | C98: -606.55
A99: 45992 | B99: T | C99: -200
A100: 46002 | B100: F | C100: 889.52
A101: 46009 | B101: T | C101: -169.62
A102: 46009 | B102: T | C102: -715.4
A103: 46009 | B103: T | C103: -4.5
A104: 46010 | B104: T | C104: -530.95
A105: 46010 | B105: T | C105: -113.05
A106: 46013 | B106: F | C106: 1172
A107: 46014 | B107: T | C107: -341.36
... A118: 46050 | B118: F | C118: 60.72

Sheet ABASTO JAVER
A1: CLIENTE | B1: ABASTO JAVER
A2: NOMBRE | B2: JAVER OVALLES
A3: TOTALES | C3: =SUM(C$4:C$1048576) -> 0 | D3: =SUM(D$4:D$1048576) -> 0 | E3: =SUM(E$5:E$1048576) -> 0 | F3: =SUM(F$5:F$1048576) -> 0 | G3: =SUM(G$5:G$1048576) -> 0
A4: FECHA | B4: F- E- T- | C4: DEUDA Y ABONOS | D4: VACIO 1/4 | E4: VACIO 350 | F4: VACIO 1.25 | G4: RETECION
A5: 45831 | B5: F | C5: 59.18
A6: 45835 | B6: F | C6: 12.1
A7: 45839 | B7: T | C7: -79.41
A8: 45839 | B8: T | C8: -87.1
A9: 45839 | B9: F | C9: 87.1
A10: 45846 | B10: F | C10: 54.18
A11: 45847 | B11: F | C11: 90
A12: 45848 | B12: T | C12: -90
A13: 45853 | B13: E | C13: -46.06
A14: 45853 | B14: F | C14: 26.15
A15: 45860 | B15: T | C15: -167.13
A16: 45860 | B16: F | C16: 389.72
... A40: 45979 | B40: T | C40: -16.31

Sheet ABASTO KLEIDI
A1: CLIENTE | B1: ABASTO KLEIDI
A2: NOMBRE | B2: KLEIDI
A3: TOTALES | C3: =SUM(C$4:C$1048576) -> 1.35 | D3: =SUM(D$4:D$1048576) -> 0 | E3: =SUM(E$5:E$1048576) -> 0 | F3: =SUM(F$5:F$1048576) -> 0 | G3: =SUM(G$5:G$1048576) -> 0
A4: FECHA | B4: F- E- T- | C4: DEUDA Y ABONOS | D4: VACIO 1/4 | E4: VACIO 350 | F4: VACIO 1.25 | G4: RETECION
A5: 45815 | B5: T | C5: -15.85
A6: 45815 | B6: F | C6: 15.85
A7: 45870 | B7: F | C7: 15.85
A8: 45870 | B8: F | C8: 47.76
A9: 45884 | B9: E | C9: -63.61
A10: 45884 | B10: F | C10: 33.6
A11: 45898 | B11: F | C11: 20.93
A12: 45903 | B12: T | C12: -33.81
A13: 45912 | B13: E | C13: -20.93
A14: 45912 | B14: F | C14: 24.93
A15: 45933 | B15: E | C15: -24.73
A16: 45933 | B16: F | C16: 31.16
... A27: 46052 | B27: E | C27: -17.24

Sheet ABASTO LAUDA
A1: don | B1: ABASTO LAUDA
A2: NOMBRE | B2: ANDRES
A3: TOTALES | C3: =SUM(C$4:C$1048576) -> 816.14 | D3: =SUM(D$4:D$1048576) -> 0 | E3: =SUM(E$5:E$1048576) -> 0 | F3: =SUM(F$5:F$1048576) -> 0 | G3: =SUM(G$5:G$1048576) -> 0
A4: FECHA | B4: F- E- T- | C4: DEUDA Y ABONOS | D4: VACIO 1/4 | E4: VACIO 350 | F4: VACIO 1.25 | G4: RETECION
A5: 45820 | B5: F | C5: 27.48
A6: 45820 | B6: F | C6: 360.98
A7: 45824 | B7: T | C7: -384.37
A8: 45833 | B8: F | C8: 19.68
A9: 45833 | B9: F | C9: 185.25
A10: 45834 | B10: T | C10: -209.05
A11: 45840 | B11: F | C11: 31.7
A12: 45840 | B12: F | C12: 160.46
A13: 45841 | B13: T | C13: -192.16
A14: 45854 | B14: T | C14: -170.73
A15: 45854 | B15: F | C15: 61.22
A16: 45854 | B16: F | C16: 109.48
... A36: 45931 | B36: T | C36: -335.87
A37: 45931 | B37: F | C37: 92.92 | D37: 4
A38: 45931 | B38: F | C38: 194.96
A39: 45932 | B39: V | D39: -3
A40: 45938 | B40: T | C40: -179.15
A41: 45938 | B41: F | C41: 13.5
A42: 45938 | B42: F | C42: 119.65
A43: 45938 | B43: F | C43: 46
A44: 45945 | B44: T | C44: -20.59
A45: 45945 | B45: T | C45: -100.45
A46: 45945 | B46: F | C46: 19.68
A47: 45945 | B47: F | C47: 78.36
A48: 45945 | B48: F | C48: 23
A49: 45947 | B49: T | C49: -117
A50: 45947 | B50: V | D50: -1
A51: 45947 | B51: F | C51: 117
A52: 45952 | B52: T | C52: -597.46
A53: 45952 | B53: F | C53: 360.06
A54: 45952 | B54: F | C54: 191.4
A55: 45952 | B55: F | C55: 46
A56: 45959 | B56: T | C56: -152.9
A57: 45959 | B57: F | C57: 35.28
A58: 45959 | B58: F | C58: 94.62
A59: 45959 | B59: F | C59: 23
A60: 45966 | B60: F | C60: 59.04
A61: 45966 | B61: F | C61: 41.76
A62: 45966 | B62: F | C62: 23
... A85: 46050 | B85: F | C85: 801.08

Sheet ABASTO LAS CUADRAS
A1: CLIENTE | B1: ABASTO LAS CUADRAS
A2: NOMBRE | B2: WILFREDO CHACON
A3: TOTALES | C3: =SUM(C$4:C$1048576) -> 128.3 | D3: =SUM(D$4:D$1048576) -> 1 | E3: =SUM(E$5:E$1048576) -> 0 | F3: =SUM(F$5:F$1048576) -> 0 | G3: =SUM(G$5:G$1048576) -> 0
A4: FECHA | B4: F- E- T- | C4: DEUDA Y ABONOS | D4: VACIO 1/4 | E4: VACIO 350 | F4: VACIO 1.25 | G4: RETECION
A5: 45820 | B5: F | C5: 15.85
A6: 45820 | B6: F | C6: 109.42
A7: 45825 | B7: T | C7: -125.26
A8: 45828 | B8: F | C8: 9.84
A9: 45828 | B9: F | C9: 173.62
A10: 45831 | B10: T | C10: -183.46
A11: 45841 | B11: F | C11: 125.58
A12: 45848 | B12: T | C12: -125.58
A13: 45860 | B13: F | C13: 15.85 | D13: 1
A14: 45860 | B14: F | C14: 236.24
A15: 45862 | B15: T | C15: -252.07
A16: 45866 | B16: T | C16: -140.64
A17: 45867 | B17: F | C17: 140.64
A18: 45869 | B18: F | C18: 17.46
A19: 45869 | B19: F | C19: 189.85
A20: 45874 | B20: T | C20: -236.02
A21: 45876 | B21: F | C21: 25.34
A22: 45876 | B22: F | C22: 3.21
A23: 45883 | B23: F | C23: 15
A24: 45883 | B24: F | C24: 82.26
A25: 45883 | B25: F | C25: 30.04
A26: 45887 | B26: T | C26: -127.3
A27: 45889 | B27: F | C27: 43.27 | D27: 1
A28: 45889 | B28: F | C28: 445.32
A29: 45889 | B29: F | C29: 77.2
A30: 45890 | B30: T | C30: -110.14
A31: 45894 | B31: T | C31: -457.64
A32: 45897 | B32: F | C32: 15
A33: 45897 | B33: F | C33: 118.44
A34: 45897 | B34: F | C34: 17.7
A35: 45898 | B35: F | C35: 21.9
A36: 45898 | B36: D | C36: -17.7
A37: 45898 | B37: T | C37: -21.9
A38: 45901 | B38: T | C38: -133.7
A39: 45912 | B39: F | C39: 30.85
... A50: 45946 | B50: T | C50: -47.49
A51: 45946 | B51: F | C51: 31.38 | D51: -1
A52: 45946 | B52: F | C52: 56.51
A53: 45950 | B53: T | C53: -87.89
A54: 45953 | B54: F | C54: 23 | D54: -1
A55: 45953 | B55: F | C55: 22.38
A56: 45953 | B56: F | C56: 177.78
A57: 45958 | B57: T | C57: -223.16
A58: 45967 | B58: F | C58: 66.8
A59: 45967 | B59: F | C59: 117.54
A60: 45974 | B60: T | C60: -107.04
A61: 45974 | B61: F | C61: 288.06
A62: 45976 | B62: T | C62: -77.03
A63: 45981 | B63: T | C63: -288.06
A64: 45981 | B64: F | C64: 50.8
A65: 45987 | B65: T | C65: -50.98
A66: 45988 | B66: F | C66: 391.4
... A73: 46010 | B73: F | C73: 108.02
A74: 46015 | B74: F | C74: 79.74 | D74: 1
A75: 46028 | B75: T | C75: -79.74
A76: 46030 | B76: F | C76: 183
A77: 46034 | B77: T | C77: -181.61
A78: 46037 | B78: F | C78: 43.12
A79: 46042 | B79: T | C79: -43.12
A80: 46042 | B80: F | C80: 215.53
A81: 46050 | B81: T | C81: -217.37
A82: 46051 | B82: F | C82: 128.3

Sheet ABASTO LAS MORENAS
A1: CLIENTE | B1: ABASTO LAS MORENAS
A2: NOMBRE | B2: CECILIO
A3: TOTALES | C3: =SUM(C$4:C$1048576) -> 367.41 | D3: =SUM(D$4:D$1048576) -> 0 | E3: =SUM(E$5:E$1048576) -> 0 | F3: =SUM(F$5:F$1048576) -> 0 | G3: =SUM(G$5:G$1048576) -> 0
A4: FECHA | B4: F- E- T- | C4: DEUDA Y ABONOS | D4: VACIO 1/4 | E4: VACIO 350 | F4: VACIO 1.25 | G4: RETECION
A5: 45815 | B5: F | C5: 33.39
A6: 45815 | B6: F | C6: 82.1
A7: 45824 | B7: T | C7: -115.49
A8: 45828 | B8: F | C8: 28.55
A9: 45828 | B9: F | C9: 156.82
A10: 45835 | B10: T | C10: -185
A11: 45835 | B11: F | C11: 19.68
A12: 45835 | B12: F | C12: 98.86
A13: 45842 | B13: T | C13: -67.84
A14: 45842 | B14: F | C14: 15.85
A15: 45842 | B15: F | C15: 95.88
A16: 45848 | B16: T | C16: -51.08
... A109: 46052 | B109: F | C109: 294.15

Sheet ABASTO LAS PILAS
A1: CLIENTE | B1: ABASTO LAS PILAS
A2: NOMBRE
A3: TOTALES | C3: =SUM(C$4:C$1048576) -> 46 | D3: =SUM(D$4:D$1048576) -> 1 | E3: =SUM(E$5:E$1048576) -> 0 | F3: =SUM(F$5:F$1048576) -> 0 | G3: =SUM(G$5:G$1048576) -> 0
A4: FECHA | B4: F- E- T- | C4: DEUDA Y ABONOS | D4: VACIO 1/4 | E4: VACIO 350 | F4: VACIO 1.25 | G4: RETECION
A5: 45820 | B5: F | C5: 33.49
A6: 45820 | B6: F | C6: 12.8
A7: 45826 | B7: E | C7: -46.29
A8: 45826 | B8: F | C8: 19.5
A9: 45826 | B9: F | C9: 20.8
A10: 45831 | B10: T | C10: -40.3
A11: 45833 | B11: F | C11: 31.7
A12: 45834 | B12: T | C12: -31.7
A13: 45840 | B13: F | C13: 41.6
A14: 45847 | B14: T | C14: -41.6
A15: 45848 | B15: F | C15: 33.49
A16: 45848 | B16: F | C16: 20.8
A17: 45854 | B17: E | C17: -54.31
A18: 45862 | B18: F | C18: 35.53 | D18: 1
A19: 45862 | B19: F | C19: 41.6
A20: 45869 | B20: E | C20: -77.13
A21: 45869 | B21: F | C21: 20.8 | D21: -1
A22: 45876 | B22: E | C22: -20.8
A23: 45883 | B23: F | C23: 41.54
A24: 45883 | B24: F | C24: 20.8
A25: 45890 | B25: T | C25: -62.35
A26: 45890 | B26: F | C26: 20.8
A27: 45895 | B27: T | C27: -20.8
A28: 45909 | B28: F | C28: 62.83 | D28: 1
A29: 45909 | B29: F | C29: 62.4
A30: 45912 | B30: T | C30: -125.23
A31: 45918 | B31: F | C31: 20.8 | D31: -1
A32: 45924 | B32: T | C32: -20.8
A33: 45925 | B33: F | C33: 15.85
A34: 45925 | B34: F | C34: 20.8
A35: 45932 | B35: T | C35: -36.65
A36: 45932 | B36: F | C36: 25.69
A37: 45940 | B37: T | C37: -25.69
A38: 45940 | B38: F | C38: 23
A39: 45942 | B39: T | C39: -23
A40: 45947 | B40: F | C40: 26.25
A41: 45947 | B41: F | C41: 23
A42: 45951 | B42: T | C42: -49.22
A43: 45960 | B43: F | C43: 24.18
... A54: 46020 | B54: T | C54: -100.42
A55: 46021 | B55: F | C55: 46 | D55: 1
A56: 46024 | B56: T | C56: -46
A57: 46031 | B57: F | C57: 57.02
A58: 46034 | B58: T | C58: -57.02
A59: 46037 | B59: F | C59: 31.44
A60: 46042 | B60: T | C60: -31.44
A61: 46044 | B61: F | C61: 46.8
A62: 46047 | B62: T | C62: -46.8
A63: 46051 | B63: F | C63: 46

Sheet ABASTO LUZ VALERO
A1: CLIENTE | B1: ABASTO LUZ VALERO
A2: NOMBRE
A3: TOTALES | C3: =SUM(C$4:C$1048576) -> 187.67 | D3: =SUM(D$4:D$1048576) -> 0 | E3: =SUM(E$5:E$1048576) -> 0 | F3: =SUM(F$5:F$1048576) -> 0 | G3: =SUM(G$5:G$1048576) -> 0
A4: FECHA | B4: F- E- T- | C4: DEUDA Y ABONOS | D4: VACIO 1/4 | E4: VACIO 350 | F4: VACIO 1.25 | G4: RETECION
A5: 45929 | B5: F | C5: 25.69
A6: 45929 | B6: F | C6: 21.4
A7: 45933 | B7: T | C7: -47.09
A8: 45933 | B8: F | C8: 22.5
A9: 45933 | B9: F | C9: 67.28
A10: 45939 | B10: T | C10: -45.46
A11: 45940 | B11: F | C11: 103.33
A12: 45942 | B12: T | C12: -44.32
A13: 45945 | B13: T | C13: -66.97
A14: 45947 | B14: F | C14: 116.86
A15: 45950 | B15: T | C15: -128.86
A16: 45961 | B16: T | C16: -36.36
... A39: 46052 | B39: F | C39: 187.7

Sheet ABASTO LUZMAR
A1: CLIENTE | B1: ABASTO LUZMAR
A2: NOMBRE | B2: MARINA LUZ SANCHEZ
A3: TOTALES | C3: =SUM(C$4:C$1048576) -> 0 | D3: =SUM(D$4:D$1048576) -> 0 | E3: =SUM(E$5:E$1048576) -> 0 | F3: =SUM(F$5:F$1048576) -> 0 | G3: =SUM(G$5:G$1048576) -> 0
A4: FECHA | B4: F- E- T- | C4: DEUDA Y ABONOS | D4: VACIO 1/4 | E4: VACIO 350 | F4: VACIO 1.25 | G4: RETECION
A5: 45821 | B5: F | C5: 15.4
A6: 45828 | B6: T | C6: -15.4
A7: 45912 | B7: T | C7: -38.14
A8: 45912 | B8: F | C8: 20.8
A9: 45912 | B9: F | C9: 17.34

Sheet ABASTO MIS ANGELES
A1: CLIENTE | B1: ABASTO MIS ANGELES
A2: NOMBRE
A3: TOTALES | C3: =SUM(C$4:C$1048576) -> 50.18 | D3: =SUM(D$4:D$1048576) -> 0 | E3: =SUM(E$5:E$1048576) -> 0 | F3: =SUM(F$5:F$1048576) -> 0 | G3: =SUM(G$5:G$1048576) -> 0
A4: FECHA | B4: F- E- T- | C4: DEUDA Y ABONOS | D4: VACIO 1/4 | E4: VACIO 350 | F4: VACIO 1.25 | G4: RETECION
A5: 45870 | B5: F | C5: 48.78
A6: 45877 | B6: E | C6: -8
A7: 45891 | B7: E | C7: -40.8
A8: 45891 | B8: F | C8: 29.92
A9: 45898 | B9: E | C9: -29.93
A10: 45898 | B10: F | C10: 15.12
A11: 45912 | B11: E | C11: -15.12
A12: 45912 | B12: F | C12: 15.85
A13: 45912 | B13: F | C13: 22.8
A14: 45926 | B14: E | C14: -38.67
A15: 45926 | B15: F | C15: 23.42
A16: 45940 | B16: E | C16: -23.42
... A30: 46052 | B30: E | C30: -13.1

Sheet ABASTO VANESA
A1: CLIENTE | B1: ABASTO VANESA
A2: NOMBRE
A3: TOTALES | C3: =SUM(C$4:C$1048576) -> 336.13 | D3: =SUM(D$4:D$1048576) -> 2 | E3: =SUM(E$5:E$1048576) -> 0 | F3: =SUM(F$5:F$1048576) -> 0 | G3: =SUM(G$5:G$1048576) -> 0
A4: FECHA | B4: F- E- T- | C4: DEUDA Y ABONOS | D4: VACIO 1/4 | E4: VACIO 350 | F4: VACIO 1.25 | G4: RETECION
A5: 45815 | B5: F | C5: 12.7
A6: 45815 | B6: F | C6: 144
A7: 45821 | B7: T | C7: -156.7
A8: 45828 | B8: F | C8: 28.55
A9: 45828 | B9: F | C9: 24.84
A10: 45828 | B10: F | C10: 20.8
A11: 45835 | B11: T | C11: -74.19
A12: 45835 | B12: F | C12: 145.6
A13: 45835 | B13: F | C13: 51.38
A14: 45835 | B14: F | C14: 9.45
A15: 45842 | B15: T | C15: -206.43
A16: 45842 | B16: F | C16: 34.04
... A58: 45933 | B58: T | C58: -221.2
A59: 45933 | B59: F | C59: 27.85 | D59: 1
A60: 45933 | B60: F | C60: 94.12
A61: 45933 | B61: F | C61: 184.8
A62: 45940 | B62: T | C62: -306.77
A63: 45940 | B63: F | C63: 230
A64: 45947 | B64: T | C64: -489.02
A65: 45947 | B65: F | C65: 32.76
A66: 45947 | B66: F | C66: 70.2
A67: 45947 | B67: F | C67: 386.06
A68: 45954 | B68: T | C68: -230
A69: 45954 | B69: F | C69: 37.98
A70: 45954 | B70: F | C70: 47.2
A71: 45954 | B71: F | C71: 69
... A79: 45975 | B79: T | C79: -182.41
A80: 45975 | B80: F | C80: 231.71 | D80: 1
A81: 45982 | B81: F | C81: 361.52
A82: 45985 | B82: T | C82: -230.25
A83: 45989 | B83: T | C83: -361.52
A84: 45989 | B84: F | C84: 302.67
A85: 45998 | B85: T | C85: -302.67
A86: 45996 | B86: F | C86: 431.36
A87: 46003 | B87: F | C87: 332.49
A88: 46004 | B88: T | C88: -25.14
A89: 46010 | B89: T | C89: -406.22
A90: 46010 | B90: T | C90: -332.49
A91: 46010 | B91: F | C91: 488.79
A92: 46017 | B92: T | C92: -488.79
... A101: 46052 | B101: F | C101: 336.13

Sheet ABASTO Y CHARCUTERIA WILMARY
A1: CLIENTE | B1: ABASTO Y CHARCUTERIA WILMARY
A2: NOMBRE | B2: ANA CONTRERAS
A3: TOTALES | C3: =SUM(C$4:C$1048576) -> 54.72 | D3: =SUM(D$4:D$1048576) -> 0 | E3: =SUM(E$5:E$1048576) -> 0 | F3: =SUM(F$5:F$1048576) -> 0 | G3: =SUM(G$5:G$1048576) -> 0
A4: FECHA | B4: F- E- T- | C4: DEUDA Y ABONOS | D4: VACIO 1/4 | E4: VACIO 350 | F4: VACIO 1.25 | G4: RETECION
A5: 45932 | B5: F | C5: 25.45
A6: 45932 | B6: F | C6: 29.18
A7: 45939 | B7: T | C7: -54.63
A8: 45939 | B8: F | C8: 25.98
A9: 45939 | B9: F | C9: 21.27
A10: 45946 | B10: T | C10: -46.7
A11: 45946 | B11: F | C11: 16.38
A12: 45946 | B12: F | C12: 34.29
A13: 45952 | B13: T | C13: -50.67
A14: 45953 | B14: F | C14: 25.98
A15: 45953 | B15: F | C15: 25.71
A16: 45959 | B16: T | C16: -52.24
... A44: 46051 | B44: F | C44: 54.72

Sheet ABASTO YUDERLI
A1: CLIENTE | B1: ABASTO YUDERLI
A2: NOMBRE
A3: TOTALES | C3: =SUM(C$4:C$1048576) -> 0.02 | D3: =SUM(D$4:D$1048576) -> 1 | E3: =SUM(E$5:E$1048576) -> 0 | F3: =SUM(F$5:F$1048576) -> 0 | G3: =SUM(G$5:G$1048576) -> 0
A4: FECHA | B4: F- E- T- | C4: DEUDA Y ABONOS | D4: VACIO 1/4 | E4: VACIO 350 | F4: VACIO 1.25 | G4: RETECION
A5: 45821 | B5: F | C5: 15.85 | D5: 1
A6: 45846 | B6: T | C6: -15.84
A7: 45849 | B7: F | C7: 7.5
A8: 45849 | B8: F | C8: 16.56 | D8: -1
A9: 45856 | B9: E | C9: -24.1
A10: 45856 | B10: F | C10: 23.35
A11: 45856 | B11: F | C11: =82.62+0.3 -> 82.92
A12: 45862 | B12: T | C12: -10.25
A13: 45863 | B13: E | C13: -80.64
A14: 45863 | B14: F | C14: 7.5
A15: 45863 | B15: F | C15: 4.25
A16: 45863 | B16: F | C16: 12.2
A17: 45870 | B17: E | C17: -39.29
A18: 45870 | B18: F | C18: 40.5
A19: 45884 | B19: E | C19: -29.03
A20: 45891 | B20: E | C20: -11.48
A21: 45919 | B21: F | C21: 15.85
A22: 45926 | B22: E | C22: -12.9
A23: 45926 | B23: F | C23: 16.62
A24: 45926 | B24: F | C24: 20.8 | D24: 1
A25: 45933 | B25: E | C25: -30.77
A26: 45940 | B26: E | C26: -9.58
A27: 45940 | B27: F | C27: 11.7
A28: 45940 | B28: F | C28: 14.6
A29: 45954 | B29: F | C29: 16.38
A30: 45954 | B30: F | C30: 43.06
A31: 45954 | B31: E | C31: -22.22
A32: 45961 | B32: E | C32: -14.81
A33: 45975 | B33: E | C33: -24.28
A34: 45996 | B34: E | C34: -24.43

Sheet ABASTO ZORANNY
A1: CLIENTE | B1: ABASTO ZORANNY
A2: NOMBRE | B2: ZORAIDA
A3: TOTALES | C3: =SUM(C$4:C$1048576) -> 0 | D3: =SUM(D$4:D$1048576) -> 0 | E3: =SUM(E$5:E$1048576) -> 0 | F3: =SUM(F$5:F$1048576) -> 0 | G3: =SUM(G$5:G$1048576) -> 0
A4: FECHA | B4: F- E- T- | C4: DEUDA Y ABONOS | D4: VACIO 1/4 | E4: VACIO 350 | F4: VACIO 1.25 | G4: RETECION
A5: 45814 | B5: F | C5: 23.42
A6: 45826 | B6: T | C6: -23.42
A7: 45826 | B7: F | C7: 27.18
A8: 45832 | B8: T | C8: -27.14
A9: 45833 | B9: F | C9: 14.44
A10: 45833 | B10: F | C10: 27.41
A11: 45840 | B11: T | C11: -41.74
A12: 45840 | B12: E | C12: -0.15
A13: 45840 | B13: F | C13: 4.6
A14: 45840 | B14: F | C14: 9.27
A15: 45842 | B15: T | C15: -13.87
A16: 45854 | B16: F | C16: 31.22
... A76: 46050 | B76: T | C76: -27.21

Sheet ALAS COMPAS
A1: CLIENTE | B1: ALAS COMPRAS
A2: NOMBRE | B2: ELICEO GARCIA
A3: TOTALES | C3: =SUM(C$4:C$1048576) -> 541.04 | D3: =SUM(D$4:D$1048576) -> 0 | E3: =SUM(E$5:E$1048576) -> 0 | F3: =SUM(F$5:F$1048576) -> 0 | G3: =SUM(G$5:G$1048576) -> 0
A4: FECHA | B4: F- E- T- | C4: DEUDA Y ABONOS | D4: VACIO 1/4 | E4: VACIO 350 | F4: VACIO 1.25 | G4: RETECION
A5: 45820 | B5: F | C5: 60.87
A6: 45820 | B6: F | C6: 435.5
A7: 45820 | B7: F | C7: 12.32
A8: 45831 | B8: T | C8: -508.68
A9: 45832 | B9: T | C9: -1.38
A10: 45834 | B10: F | C10: 15
A11: 45834 | B11: F | C11: 548.14
A12: 45834 | B12: F | C12: 6.69
A13: 45846 | B13: T | C13: -569.83
A14: 45846 | B14: F | C14: 123.31
A15: 45846 | B15: F | C15: 600.26
A16: 45846 | B16: F | C16: 12.9
... A19: 45869 | B19: F | C19: 88.63
A20: 45869 | B20: F | C20: 16.47 | I20: WILLI
A21: 45873 | B21: T | C21: -182.4
A22: 45876 | B22: F | C22: 43.33
A23: 45876 | B23: F | C23: 106.8
A24: 45887 | B24: T | C24: -261.92
A25: 45890 | B25: F | C25: 75.85
A26: 45890 | B26: F | C26: 112.27
A27: 45890 | B27: F | C27: 13.38
A28: 45893 | B28: T | C28: -98.67
A29: 45898 | B29: F | C29: 23.65
A30: 45898 | B30: F | C30: 45.54
A31: 45908 | B31: T | C31: -163.96
A32: 45911 | B32: F | C32: 29.52
... A68: 46052 | B68: T | C68: -239.66

Sheet ALVARO RINCON
A1: CLIENTE | B1: ALVARO RINCON
A2: NOMBRE
A3: TOTALES | C3: =SUM(C$4:C$1048576) -> 0 | D3: =SUM(D$4:D$1048576) -> 0 | E3: =SUM(E$5:E$1048576) -> 0 | F3: =SUM(F$5:F$1048576) -> 0 | G3: =SUM(G$5:G$1048576) -> 0
A4: FECHA | B4: F- E- T- | C4: DEUDA Y ABONOS | D4: VACIO 1/4 | E4: VACIO 350 | F4: VACIO 1.25 | G4: RETECION
A5: - | B5: F
B6: F
B7: T

Sheet ALEJANDRA NIETO
A1: CLIENTE | B1: ALEJANDRA NIETO
A2: NOMBRE
A3: TOTALES | C3: =SUM(C$4:C$1048576) -> -2.21 | D3: =SUM(D$4:D$1048576) -> 0 | E3: =SUM(E$5:E$1048576) -> 0 | F3: =SUM(F$5:F$1048576) -> 0 | G3: =SUM(G$5:G$1048576) -> 0
A4: FECHA | B4: F- E- T- | C4: DEUDA Y ABONOS | D4: VACIO 1/4 | E4: VACIO 350 | F4: VACIO 1.25 | G4: RETECION
A5: 45814 | B5: F | C5: 21
A6: 45825 | B6: E | C6: -21
A7: 45825 | B7: F | C7: 141.16
A8: 45834 | B8: E | C8: -141.19
A9: 45834 | B9: F | C9: 25.69
A10: 45834 | B10: F | C10: 101.86
A11: 45853 | B11: F | C11: 93.08
A12: 45854 | B12: E | C12: -100
A13: 45877 | B13: E | C13: -120.55
A14: 45877 | B14: F | C14: 15.84
A15: 45877 | B15: F | C15: 119.05
A16: 45896 | B16: E | C16: -134.16
... A34: 46055 | B34: T | C34: -8

Sheet AMALUBE
A1: CLIENTE | B1: AMALUBE
A2: NOMBRE
A3: TOTALES | C3: =SUM(C$4:C$1048576) -> 33.85 | D3: =SUM(D$4:D$1048576) -> 0 | E3: =SUM(E$5:E$1048576) -> 0 | F3: =SUM(F$5:F$1048576) -> 0 | G3: =SUM(G$5:G$1048576) -> 0
A4: FECHA | B4: F- E- T- | C4: DEUDA Y ABONOS | D4: VACIO 1/4 | E4: VACIO 350 | F4: VACIO 1.25 | G4: RETECION
A5: 45826 | B5: F | C5: 25.69
A6: 45826 | B6: F | C6: 199.04
A7: 45841 | B7: T | C7: -174.73
A8: 45846 | B8: T | C8: -50
A9: 45847 | B9: F | C9: 25.69
A10: 45847 | B10: F | C10: 292.09
A11: 45847 | B11: F | C11: 47.6
A12: 45861 | B12: T | C12: -165.38
A13: 45862 | B13: T | C13: -79.39
A14: 45863 | B14: T | C14: -90
A15: 45868 | B15: T | C15: -25
A16: 45868 | B16: F | C16: 20
... A51: 45980 | B51: T | C51: -163.91
A52: 45980 | B52: F | C52: 206.74 | D52: 1
A53: 45986 | B53: T | C53: -207.18
A54: 45987 | B54: F | C54: 150.59
A55: 45998 | B55: T | C55: -148.8
A56: 46001 | B56: F | C56: 123.12 | D56: -1
A57: 46009 | B57: T | C57: -123.59
A58: 46014 | B58: F | C58: 240.74
A59: 46020 | B59: T | C59: -118.66
A60: 46020 | B60: T | C60: -101.71
A61: 46020 | B61: T | C61: -20.38
A62: 46029 | B62: F | C62: 98.76
A63: 46031 | B63: T | C63: -98.76
A64: 46036 | B64: F | C64: 237.06
A65: 46042 | B65: T | C65: -237.06
A66: 46043 | B66: F | C66: 54.7
A67: 46048 | B67: T | C67: -54.7
A68: 46050 | B68: F | C68: 32.3 | L68: =38450.32/355.5528 -> 108.14236
L69: =+L68-56.25 -> 51.892363
L70: =+L69*355.5528 -> 18450.475
L73: =54.7*355.5528 -> 19448.738
L74: =38450.32-L73 -> 19001.582

Sheet AMEZQUITA BODEGON
A1: CLIENTE | B1: AMEZQUITA BODEGON
A2: NOMBRE
A3: TOTALES | C3: =SUM(C$4:C$1048576) -> 335.58 | D3: =SUM(D$4:D$1048576) -> 1 | E3: =SUM(E$5:E$1048576) -> 0 | F3: =SUM(F$5:F$1048576) -> 0 | G3: =SUM(G$5:G$1048576) -> 0
A4: FECHA | B4: F- E- T- | C4: DEUDA Y ABONOS | D4: VACIO 1/4 | E4: VACIO 350 | F4: VACIO 1.25 | G4: RETECION
A5: 45826 | B5: F | C5: 25.69
A6: 45826 | B6: F | C6: 199.04
A7: 45841 | B7: T | C7: -174.73
A8: 45846 | B8: T | C8: -50
A9: 45847 | B9: F | C9: 25.69
A10: 45847 | B10: F | C10: 292.09
A11: 45847 | B11: F | C11: 47.6
A12: 45861 | B12: T | C12: -165.38
A13: 45862 | B13: T | C13: -79.39
A14: 45863 | B14: T | C14: -90
A15: 45868 | B15: T | C15: -25
A16: 45868 | B16: F | C16: 20
... A51: 45980 | B51: T | C51: -163.91
A52: 45980 | B52: F | C52: 206.74 | D52: 1
A53: 45986 | B53: T | C53: -207.18
A54: 45998 | B54: T | C54: -267.62
A55: 45996 | B55: F | C55: 265.59 | D55: 1
A56: 46003 | B56: F | C56: 17.34 | D56: -1
A57: 46010 | B57: T | C57: -17.34
A58: 46010 | B58: F | C58: 22.5
A59: 46017 | B59: T | C59: -22.5
A60: 46017 | B60: F | C60: 303.97
A61: 46024 | B61: T | C61: -303.97
A62: 46031 | B62: F | C62: 63.74
A63: 46038 | B63: T | C63: -61.95
A64: 46038 | B64: F | C64: 51.76
A65: 46044 | B65: T | C65: -51.76
A66: 46052 | B66: F | C66: 335.58

Sheet ANDERZON POLAR
A1: CLIENTE | B1: ANDERZON POLAR
A2: NOMBRE | M2: =4319.86-100 -> 4219.86
A3: TOTALES | C3: =SUM(C$4:C$1048576) -> 0.25 | D3: =SUM(D$4:D$1048576) -> 0 | E3: =SUM(E$5:E$1048576) -> 0 | F3: =SUM(F$5:F$1048576) -> 0 | G3: =SUM(G$5:G$1048576) -> 0
A4: FECHA | B4: F- E- T- | C4: DEUDA Y ABONOS | D4: VACIO 1/4 | E4: VACIO 350 | F4: VACIO 1.25 | G4: RETECION
A5: 45912 | B5: F | C5: 22.12
A6: 45958 | B6: V | C6: -108.75
A7: 45961 | B7: T | C7: -22.12
A8: 45961 | B8: F | C8: 115 | D8: 5
A9: 45964 | B9: T | C9: -6
A10: 46036 | B10: v | D10: -5

Sheet ANDERZON RODRIGUEZ
A1: CLIENTE | B1: ANDERZON RODRIGUEZ
A2: NOMBRE | M2: =4319.86-100 -> 4219.86
A3: TOTALES | C3: =SUM(C$4:C$1048576) -> 127.18 | D3: =SUM(D$4:D$1048576) -> 0 | E3: =SUM(E$5:E$1048576) -> -1 | F3: =SUM(F$5:F$1048576) -> -2 | G3: =SUM(G$5:G$1048576) -> 0
A4: FECHA | B4: F- E- T- | C4: DEUDA Y ABONOS | D4: VACIO 1/4 | E4: VACIO 350 | F4: VACIO 1.25 | G4: RETECION
A5: 45815 | B5: F | C5: 23.55 | D5: 1
A6: 45815 | B6: F | C6: 44.6
A7: 45815 | B7: F | C7: 9.15
A8: 45824 | B8: T | C8: -77.78
A9: 45826 | B9: F | C9: 71.12
A10: 45833 | B10: F | C10: 55.35
A11: 45833 | B11: F | C11: 5.66
A12: 45840 | B12: T | C12: -61
A13: 45840 | B13: T | C13: -71.12
A14: 45840 | B14: F | C14: 15.85
A15: 45840 | B15: F | C15: 63.95
A16: 45847 | B16: F | C16: 46.11
A17: 45854 | B17: T | C17: -11.23
... A24: 45863 | B24: T | C24: -17.28
A25: 45868 | B25: F | C25: 15.85 | D25: -1
A26: 45868 | B26: F | C26: 58.62
A27: 45869 | B27: T | C27: -9.72
A28: 45869 | B28: F | C28: 13.68
A29: 45876 | B29: T | C29: -40.16
A30: 45876 | B30: T | C30: -61.99
A31: 45876 | B31: F | C31: 4.5
A32: 45876 | B32: F | C32: 45.58
A33: 45880 | B33: T | C33: -26.16
A34: 45883 | B34: T | C34: -37.18
A35: 45883 | B35: F | C35: 18.6
A36: 45883 | B36: F | C36: 39.53
A37: 45887 | B37: T | C37: -13.55
... A110: 46009 | B110: T | C110: -25.04
A111: 46009 | B111: F | C111: 139.92 | E111: -1
A112: 46013 | B112: T | C112: -15.77
A113: 46014 | B113: T | C113: -10.4
A114: 46017 | B114: T | C114: -23.8
A115: 46020 | B115: T | C115: -27.12
A116: 46024 | B116: T | C116: -19.91
A117: 46024 | B117: T | C117: -21.57
A118: 46030 | B118: T | C118: -6.23
A119: 46030 | B119: F | C119: 75.7 | F119: -2
A120: 46034 | B120: T | C120: -6.05
A121: 46034 | B121: T | C121: -18.78
A122: 46035 | B122: T | C122: -9.08
A123: 46036 | B123: T | C123: -4.42
A124: 46037 | B124: T | C124: -55.32
A125: 46037 | B125: F | C125: 165.59
A126: 46042 | B126: T | C126: -43.54
A127: 46042 | B127: T | C127: -7.55
A128: 46043 | B128: T | C128: -115.19
A129: 46045 | B129: T | C129: -28.35
A130: 46045 | B130: T | C130: -8.57
A131: 46045 | B131: F | C131: 95.15
... A137: 46056 | B137: T | C137: -13.44

Sheet ANDREA URDANETA
A1: CLIENTE | B1: ANDREA URDANETA
A2: NOMBRE
A3: TOTALES | C3: =SUM(C$4:C$1048576) -> 368.59 | D3: =SUM(D$4:D$1048576) -> 0 | E3: =SUM(E$5:E$1048576) -> 0 | F3: =SUM(F$5:F$1048576) -> 0 | G3: =SUM(G$5:G$1048576) -> 0
A4: FECHA | B4: F- E- T- | C4: DEUDA Y ABONOS | D4: VACIO 1/4 | E4: VACIO 350 | F4: VACIO 1.25 | G4: RETECION
A5: 45875 | B5: F | C5: 18.84
A6: 45875 | B6: F | C6: 105.43
A7: 45875 | B7: F | C7: 18.3
A8: 45876 | B8: T | C8: -65
A9: 45880 | B9: T | C9: -50
A10: 45882 | B10: T | C10: -27.85
A11: 45883 | B11: T | C11: -74.36
A12: 45882 | B12: F | C12: 9.6
A13: 45882 | B13: F | C13: 97.81
A14: 45882 | B14: F | C14: 59.29
A15: 45884 | B15: T | C15: -92.33
A16: 45889 | B16: F | C16: 40.78
... A109: 46052 | B109: F | C109: 87

Sheet APRICOT
A1: CLIENTE | B1: APRICOT
A2: NOMBRE
A3: TOTALES | C3: =SUM(C$4:C$1048576) -> 440.72 | D3: =SUM(D$4:D$1048576) -> 12 | E3: =SUM(E$5:E$1048576) -> 0 | F3: =SUM(F$5:F$1048576) -> 0 | G3: =SUM(G$5:G$1048576) -> 0
A4: FECHA | B4: F- E- T- | C4: DEUDA Y ABONOS | D4: VACIO 1/4 | E4: VACIO 350 | F4: VACIO 1.25 | G4: RETECION
A5: 45828 | B5: F | C5: 123.41
A6: 45848 | B6: T | C6: -89
A7: 45856 | B7: T | C7: -34.41
A8: 45856 | B8: F | C8: 44.2
A9: 45873 | B9: T | C9: -19.4
A10: 45875 | B10: T | C10: -15.6
A11: 45877 | B11: F | C11: 53.95
A12: 45880 | B12: T | C12: -13.67
A13: 45896 | B13: T | C13: -49.01
A14: 45897 | B14: F | C14: 33.8
A15: 45908 | B15: F | C15: 208 | D15: 10
A16: 45911 | B16: T | C16: -33.8
A17: 45912 | B17: F | C17: 342 | D17: =12-10 -> 2
A18: 45912 | B18: F | C18: 21.7
A19: 45918 | B19: T | C19: -104
A20: 45919 | B20: T | C20: -38
A21: 45922 | B21: T | C21: -363.69
A22: 45923 | B22: T | C22: -104.9
A23: 45923 | B23: F | C23: 322.8
A24: 45923 | B24: F | C24: 7.5
A25: 45931 | B25: T | C25: -62.36
A26: 45932 | B26: T | C26: -80
A27: 45933 | B27: F | C27: 41.5
A28: 45933 | B28: F | C28: 21.7
A29: 45940 | B29: T | C29: -49.5
... A39: 46045 | B39: F | C39: 440

Sheet AURA VIVAS
A1: CLIENTE | B1: AURA VIVAS
A2: NOMBRE
A3: TOTALES | C3: =SUM(C$4:C$1048576) -> -0.002 | D3: =SUM(D$4:D$1048576) -> 0 | E3: =SUM(E$5:E$1048576) -> 0 | F3: =SUM(F$5:F$1048576) -> 0 | G3: =SUM(G$5:G$1048576) -> 0
A4: FECHA | B4: F- E- T- | C4: DEUDA Y ABONOS | D4: VACIO 1/4 | E4: VACIO 350 | F4: VACIO 1.25 | G4: RETECION
A5: 45912 | B5: T | C5: -49.98
A6: 45912 | B6: F | C6: 7.5
A7: 45912 | B7: F | C7: 42.48
A8: 45920 | B8: F | C8: 7.5
A9: 45920 | B9: F | C9: 68.94
A10: 45922 | B10: T | C10: -76.44
A11: 45933 | B11: F | C11: 79.28
A12: 45938 | B12: T | C12: -40.99
A13: 45940 | B13: F | C13: 52.368
A14: 45947 | B14: E | C14: -52.69
A15: 45950 | B15: T | C15: -37.97

Sheet AVENTURA INFLABLE
A1: CLIENTE | B1: AVENTURA INFLABLE
A2: NOMBRE
A3: TOTALES | C3: =SUM(C$4:C$1048576) -> 1.9539925e-13 | D3: =SUM(D$4:D$1048576) -> 2 | E3: =SUM(E$5:E$1048576) -> 0 | F3: =SUM(F$5:F$1048576) -> 0 | G3: =SUM(G$5:G$1048576) -> 0
A4: FECHA | B4: F- E- T- | C4: DEUDA Y ABONOS | D4: VACIO 1/4 | E4: VACIO 350 | F4: VACIO 1.25 | G4: RETECION
A5: 46017 | B5: F | C5: 709.9 | D5: 2
A6: 46020 | B6: T | C6: -709.88
A7: 46020 | B7: F | C7: 719.44
A8: 46021 | B8: F | C8: 113.23
A9: 46022 | B9: T | C9: -832.67
A10: 46030 | B10: F | C10: 1938.84
A11: 46031 | B11: T | C11: -1014.17
A12: 46037 | B12: F | C12: 773.4
A13: 46044 | B13: T | C13: -924.67
A14: 46045 | B14: T | C14: -767.51
A15: 46052 | B15: T | C15: -5.91

Sheet BARBERIA SPARTA
A1: CLIENTE | B1: BARBERIA SPARTA
A2: NOMBRE
A3: TOTALES | C3: =SUM(C$4:C$1048576) -> 0 | D3: =SUM(D$4:D$1048576) -> 0 | E3: =SUM(E$5:E$1048576) -> 0 | F3: =SUM(F$5:F$1048576) -> 0 | G3: =SUM(G$5:G$1048576) -> 0
A4: FECHA | B4: F- E- T- | C4: DEUDA Y ABONOS | D4: VACIO 1/4 | E4: VACIO 350 | F4: VACIO 1.25 | G4: RETECION
A5: 46042 | B5: T | C5: -39.31
A6: 46042 | B6: F | C6: 39.31

Sheet BAKAI MACHIRI
A1: CLIENTE | B1: BAKAI MACHIRI
A2: NOMBRE
A3: TOTALES | C3: =SUM(C$4:C$1048576) -> 71.28 | D3: =SUM(D$4:D$1048576) -> 0 | E3: =SUM(E$5:E$1048576) -> 0 | F3: =SUM(F$5:F$1048576) -> 0 | G3: =SUM(G$5:G$1048576) -> 44.73
A4: FECHA | B4: F- E- T- | C4: DEUDA Y ABONOS | D4: VACIO 1/4 | E4: VACIO 350 | F4: VACIO 1.25 | G4: RETECION
A5: 45819 | B5: F | C5: =39.2-G5 -> 35.15 | G5: 4.05
A6: 45819 | B6: F | C6: 27.96
A7: 45819 | B7: F | C7: 19.88
A8: 45827 | B8: T | C8: -83.2 | G8: -4.05
A9: 45834 | B9: F | C9: 59.85
A10: 45834 | B10: F | C10: 40.68
A11: 45834 | B11: F | C11: 20.8
A12: 45853 | B12: T | C12: -121.32
A13: 45854 | B13: F | C13: =59.55-G13 -> 51.81 | G13: 7.74
A14: 45854 | B14: F | C14: 43.28
A15: 45854 | B15: F | C15: 40.7
A16: 45862 | B16: R | G16: -7.74
A17: 45866 | B17: T | C17: -129.99
A18: 45869 | B18: F | C18: =52.68-G18 -> 47.24 | G18: 5.44
A19: 45869 | B19: F | C19: 36.57
A20: 45880 | B20: T | C20: -91.39 | G20: -5.44
A21: 45881 | B21: F | C21: =67.28-G21 -> 62.14 | G21: 5.14
A22: 45881 | B22: F | C22: =86.74-G22 -> 78.85 | G22: 7.89
A23: 45890 | B23: R | G23: -13.03
A24: 45894 | B24: T | C24: -138.09
A25: 45897 | B25: F | C25: =77.28-G25 -> 69.29 | G25: 7.99
A26: 45897 | B26: F | C26: =37.05-G26 -> 33.23 | G26: 3.82
A27: 45897 | B27: F | C27: 63.9
A28: 45903 | B28: T | C28: -166.42
A29: 45904 | B29: F | C29: =36.6-G29 -> 32.82 | G29: 3.78
A30: 45904 | B30: F | C30: =134.74-G30 -> 123.7 | G30: 11.04
A31: 45904 | B31: F | C31: 33.16
A32: 45917 | B32: T | C32: -154.99
A33: 45918 | B33: F | C33: =44.25-G33 -> 39.68 | G33: 4.57
A34: 45918 | B34: F | C34: =130.82-G34 -> 118.74 | G34: 12.08
A35: 45918 | B35: F | C35: 9.96
A36: 45925 | B36: F | C36: =46.68-G36 -> 41.86 | G36: 4.82
A37: 45925 | B37: F | C37: =115.5-G37 -> 105 | G37: 10.5
A38: 45925 | B38: F | C38: 9.96
A39: 45930 | B39: T | C39: -34.69
A40: 45930 | B40: T | C40: -203.98
A41: 45931 | B41: T | C41: -98.99
A42: 45932 | B42: T | C42: -56.81 | G42: -14.82
A43: 45932 | B43: F | C43: =51.9-G43 -> 46.54 | G43: 5.36
A44: 45932 | B44: F | C44: =63.58-G44 -> 57 | G44: 6.58
A45: 45932 | B45: F | C45: 9.96 | G45: -11.81
A46: 45939 | B46: R | G46: -15.32
A47: 45939 | B47: R | G47: -16.65
A48: 45940 | B48: T | C48: -85.84
A49: 45940 | B49: F | C49: =56.28-G49 -> 50.46 | G49: 5.82
A50: 45940 | B50: F | C50: =29.96-G50 -> 28.39 | G50: 1.57
A51: 45940 | B51: F | C51: 4.56
A52: 45945 | B52: T | C52: -77.41
A53: 45946 | B53: F | C53: =71.1-G53 -> 71.1
A54: 45946 | B54: F | C54: =22.18-G54 -> 22.18
A55: 45946 | B55: F | C55: 4.56
A56: 45953 | B56: T | C56: -88.2
A57: 45953 | B57: F | C57: =47.5-G57 -> 42.59 | G57: 4.91
A58: 45953 | B58: F | C58: =125.91-G58 -> 114.41 | G58: 11.5
A59: 45953 | B59: F | C59: 25.87
A60: 45959 | B60: R | G60: -11.94
A61: 45960 | B61: F | C61: =37.26-G61 -> 33.41 | G61: 3.85
A62: 45960 | B62: F | C62: =91.98-G62 -> 83.88 | G62: 8.1
A63: 45960 | B63: F | C63: 27.57
A64: 45964 | B64: T | C64: -181.06 | G64: -7.39
A65: 45967 | B65: F | C65: =37-G65 -> 33.18 | G65: 3.82
A66: 45967 | B66: F | C66: =107.75-G66 -> 98.01 | G66: 9.74
A67: 45967 | B67: F | C67: 10.79
A68: 45978 | B68: T | C68: -146.67
A69: 45980 | B69: T | C69: -141.98
A70: 45981 | B70: F | C70: =166.07-G70 -> 148.9 | G70: 17.17
A71: 45988 | B71: R | G71: -11.95
A72: 45988 | B72: R | G72: -13.56
A73: 45988 | B73: F | C73: =200.82-G73 -> 184.71 | G73: 16.11
A74: 45994 | B74: T | C74: -143
A75: 45995 | B75: T | C75: -196.5
A76: 45995 | B76: F | C76: =166.35-G76 -> 159.26 | G76: 7.09
A77: 46002 | B77: T | C77: -163.01
A78: 46002 | B78: F | C78: =188.52-G78 -> 181.52 | G78: 7
A79: 46006 | B79: R | G79: -17.17
A80: 46009 | B80: F | C80: =180.7-G80 -> 178.17 | G80: 2.53
A81: 46020 | B81: T | C81: -170 | G81: -16.11
A82: 46020 | B82: T | C82: -11.52 | G82: -7.09
A83: 46020 | B83: T | C83: -178.19
A84: 46021 | B84: F | C84: =250.8-G84 -> 229.27 | G84: 21.53
A85: 46027 | B85: R | G85: -7
A86: 46037 | B86: F | C86: =203.74-G86 -> 182.67 | G86: 21.07
A87: 46042 | B87: T | C87: -229.27
A88: 46044 | B88: R | G88: -16.41 | N88: =755.94/298.1431 -> 2.5354939
A89: 46044 | B89: R | G89: -2.53
A90: 46044 | B90: F | C90: =150.46-G90 -> 134.9 | G90: 15.56
A91: 46045 | B91: T | C91: -182.67 | G91: -21.53
A92: 46051 | B92: F | C92: =94.5-G92 -> 86.4 | G92: 8.1
A93: 46056 | B93: T | C93: -150 | K93: =7359.35/339.1495 -> 21.699428
O96: =1958.18/279.5629 -> 7.0044344

Sheet BELKIS MONSALVE
A1: CLIENTE | B1: BELKIS MONSALVE
A2: NOMBRE
A3: TOTALES | C3: =SUM(C$4:C$1048576) -> 0 | D3: =SUM(D$4:D$1048576) -> 0 | E3: =SUM(E$5:E$1048576) -> 0 | F3: =SUM(F$5:F$1048576) -> 0 | G3: =SUM(G$5:G$1048576) -> 0
A4: FECHA | B4: F- E- T- | C4: DEUDA Y ABONOS | D4: VACIO 1/4 | E4: VACIO 350 | F4: VACIO 1.25 | G4: RETECION
B5: F
B6: F
B7: F
B8: T

Sheet BOD ALTOS PARAMILLO
A1: 3.64 | B1: BOD ALTOS PARAMILLO
A2: NOMBRE | B2: CIRA PERDOMO
A3: TOTALES | C3: =SUM(C$4:C$1048576) -> -0.02 | D3: =SUM(D$4:D$1048576) -> 0 | E3: =SUM(E$5:E$1048576) -> 0 | F3: =SUM(F$5:F$1048576) -> 0 | G3: =SUM(G$5:G$1048576) -> 0
A4: FECHA | B4: F- E- T- | C4: DEUDA Y ABONOS | D4: VACIO 1/4 | E4: VACIO 350 | F4: VACIO 1.25 | G4: RETECION
A5: 45888 | B5: F | C5: 20.8
A6: 45888 | B6: F | C6: 5
A7: 45902 | B7: F | C7: 4.5
A8: 45902 | B8: F | C8: 12.1
A9: 45909 | B9: E | C9: -16.61
A10: 45929 | B10: T | C10: -25.79
A11: 45958 | B11: T | C11: -44
A12: 45958 | B12: F | C12: 26.7
A13: 45958 | B13: F | C13: 4.6
A14: 45958 | B14: F | C14: 12.68

Sheet BOD MARBELYS ROA
A1: CLIENTE | B1: BOD MARBELYS ROA
A2: NOMBRE | B2: MARBELYS ROA
A3: TOTALES | C3: =SUM(C$4:C$1048576) -> 0.01 | D3: =SUM(D$4:D$1048576) -> 0 | E3: =SUM(E$5:E$1048576) -> 0 | F3: =SUM(F$5:F$1048576) -> 0 | G3: =SUM(G$5:G$1048576) -> 0
A4: FECHA | B4: F- E- T- | C4: DEUDA Y ABONOS | D4: VACIO 1/4 | E4: VACIO 350 | F4: VACIO 1.25 | G4: RETECION
A5: 45813 | B5: F | C5: 28.19
A6: 45817 | B6: T | C6: -28.19
A7: 45818 | B7: F | C7: 15.85
A8: 45820 | B8: T | C8: -15.84
A9: 45825 | B9: T | C9: -17.8
A10: 45825 | B10: F | C10: 7.8
A11: 45825 | B11: F | C11: 10
A12: 45832 | B12: F | C12: 10
A13: 45833 | B13: T | C13: -10
A14: 45839 | B14: T | C14: -19.04
A15: 45839 | B15: F | C15: 19.04
A16: 45846 | B16: T | C16: -46.65
... A29: 46056 | B29: F | C29: 17.28

Sheet BOD SOLMAR PINTO
A1: CLIENTE | B1: BOD SOLMAR PINTO
A2: NOMBRE
A3: TOTALES | C3: =SUM(C$4:C$1048576) -> 211.19 | D3: =SUM(D$4:D$1048576) -> 1 | E3: =SUM(E$5:E$1048576) -> 0 | F3: =SUM(F$5:F$1048576) -> 0 | G3: =SUM(G$5:G$1048576) -> 0
A4: FECHA | B4: F- E- T- | C4: DEUDA Y ABONOS | D4: VACIO 1/4 | E4: VACIO 350 | F4: VACIO 1.25 | G4: RETECION
A5: 45814 | B5: F | C5: 15.85
A6: 45814 | B6: F | C6: 85.99
A7: 45825 | B7: T | C7: -46.99
A8: 45841 | B8: T | C8: -55.95
A9: 45841 | B9: F | C9: 41.6
A10: 45841 | B10: F | C10: 15.85
A11: 45847 | B11: T | C11: -57.45
A12: 45848 | B12: F | C12: 62.4
A13: 45848 | B13: F | C13: 20.34
A14: 45855 | B14: T | C14: -9.54
A15: 45855 | B15: T | C15: -34.24
A16: 45855 | B16: T | C16: -38.97
... A27: 45873 | B27: T | C27: -16.34
A28: 45876 | B28: F | C28: 83.2 | D28: 1
A29: 45890 | B29: T | C29: -74.96
A30: 45890 | B30: T | C30: -24.11
A31: 45890 | B31: F | C31: 41.6
A32: 45890 | B32: F | C32: 25.69
A33: 45898 | B33: F | C33: 62.4
A34: 45898 | B34: F | C34: 9.84
A35: 45898 | B35: F | C35: 13.4
A36: 45903 | B36: T | C36: -23.77
A37: 45903 | B37: T | C37: -36.13
A38: 45903 | B38: T | C38: -7.21
A39: 45903 | B39: T | C39: -85.64
A40: 45904 | B40: F | C40: 62.4
... A94: 46051 | B94: T | C94: 155.12

Sheet BOD TOICO CLEIBER
A1: CLIENTE | B1: BOD TOICO CLEIBER
A2: NOMBRE | B2: CLEIBER ANDRADE
A3: TOTALES | C3: =SUM(C$4:C$1048576) -> 3.5527137e-14 | D3: =SUM(D$4:D$1048576) -> 0 | E3: =SUM(E$5:E$1048576) -> 0 | F3: =SUM(F$5:F$1048576) -> 0 | G3: =SUM(G$5:G$1048576) -> 0
A4: FECHA | B4: F- E- T- | C4: DEUDA Y ABONOS | D4: VACIO 1/4 | E4: VACIO 350 | F4: VACIO 1.25 | G4: RETECION
A5: 45813 | B5: F | C5: 7.8
A6: 45813 | B6: F | C6: 154.51
A7: 45818 | B7: F | C7: 17.54
A8: 45818 | B8: F | C8: 106.99
A9: 45818 | B9: F | C9: 13.76
A10: 45820 | B10: T | C10: -162.32
A11: 45825 | B11: T | C11: -139.36
A12: 45825 | B12: F | C12: 28.69
A13: 45825 | B13: F | C13: 57.48
A14: 45825 | B14: F | C14: 2.74
A15: 45832 | B15: T | C15: -88.89
A16: 45832 | B16: F | C16: 23.65
... A111: 46055 | B111: T | C111: -27.3

Sheet BOD TOICO OSMAR
A1: CLIENTE | B1: BOD TOICO OSMAR
A2: NOMBRE | B2: OSMAR SUAREZ
A3: TOTALES | C3: =SUM(C$4:C$1048576) -> -0.057 | D3: =SUM(D$4:D$1048576) -> 1 | E3: =SUM(E$5:E$1048576) -> 0 | F3: =SUM(F$5:F$1048576) -> 0 | G3: =SUM(G$5:G$1048576) -> 0
A4: FECHA | B4: F- E- T- | C4: DEUDA Y ABONOS | D4: VACIO 1/4 | E4: VACIO 350 | F4: VACIO 1.25 | G4: RETECION
A5: 45813 | B5: F | C5: 7.8
A6: 45813 | B6: F | C6: 102.63
A7: 45817 | B7: T | C7: -83.8
A8: 45818 | B8: F | C8: 20.8
A9: 45818 | B9: F | C9: 53.45
A10: 45820 | B10: T | C10: -19.93
A11: 45826 | B11: T | C11: -19.45
A12: 45827 | B12: T | C12: -19.28
A13: 45835 | B13: T | C13: -18.72
A14: 45835 | B14: T | C14: -18.72
A15: 45838 | B15: T | C15: -7.13
A16: 45839 | B16: F | C16: 33.19
... A33: 45881 | B33: E | C33: -1.29
A34: 45881 | B34: F | C34: 15.85 | D34: 1
A35: 45881 | B35: F | C35: 77.45
A36: 45890 | B36: T | C36: -17.93
A37: 45891 | B37: T | C37: -19.53
A38: 45895 | B38: T | C38: -55.82
A39: 45895 | B39: F | C39: 19.46
A40: 45895 | B40: F | C40: 57.48
A41: 45895 | B41: F | C41: 10.46
A42: 45909 | B42: T | C42: -19.36
A43: 45911 | B43: T | C43: -30.31
A44: 45916 | B44: T | C44: -21.81
A45: 45916 | B45: T | C45: -23.83
A46: 45916 | B46: F | C46: 33.19
... A75: 46043 | B75: T | C75: -23.5

Sheet BODEGA DE ORO
A1: CLIENTE | B1: BODEGA DE ORO
A2: NOMBRE
A3: TOTALES | C3: =SUM(C$4:C$1048576) -> 240.943 | D3: =SUM(D$4:D$1048576) -> 0 | E3: =SUM(E$5:E$1048576) -> 0 | F3: =SUM(F$5:F$1048576) -> 0 | G3: =SUM(G$5:G$1048576) -> 0
A4: FECHA | B4: F- E- T- | C4: DEUDA Y ABONOS | D4: VACIO 1/4 | E4: VACIO 350 | F4: VACIO 1.25 | G4: RETECION
A5: 45819 | B5: F | C5: 9.84
A6: 45819 | B6: F | C6: 53.31
A7: 45831 | B7: T | C7: -63.21
A8: 45834 | B8: T | C8: -65.7
A9: 45833 | B9: F | C9: 36.8
A10: 45833 | B10: F | C10: 25.69
A11: 45833 | B11: F | C11: 3.21
A12: 45840 | B12: F | C12: 53.94
A13: 45840 | B13: F | C13: 18.4
A14: 45848 | B14: F | C14: 7.5
A15: 45848 | B15: F | C15: 23.49
A16: 45848 | B16: F | C16: 16.44
... A124: 46051 | B124: F | C124: 189.19

Sheet BODEGA DE CECI
A1: CLIENTE | B1: BODEGA DE CECI
A2: NOMBRE
A3: TOTALES | C3: =SUM(C$4:C$1048576) -> 0 | D3: =SUM(D$4:D$1048576) -> 0 | E3: =SUM(E$5:E$1048576) -> 0 | F3: =SUM(F$5:F$1048576) -> 0 | G3: =SUM(G$5:G$1048576) -> 0
A4: FECHA | B4: F- E- T- | C4: DEUDA Y ABONOS | D4: VACIO 1/4 | E4: VACIO 350 | F4: VACIO 1.25 | G4: RETECION
A5: 45848 | B5: F | C5: 58.69
A6: 45855 | B6: T | C6: -58.69

Sheet BODEGA EL ARBOLITO
A1: CLIENTE | B1: BODEGA EL ARBOLITO
A2: NOMBRE
A3: TOTALES | C3: =SUM(C$4:C$1048576) -> 96.43 | D3: =SUM(D$4:D$1048576) -> 0 | E3: =SUM(E$5:E$1048576) -> 0 | F3: =SUM(F$5:F$1048576) -> 0 | G3: =SUM(G$5:G$1048576) -> 0
A4: FECHA | B4: F- E- T- | C4: DEUDA Y ABONOS | D4: VACIO 1/4 | E4: VACIO 350 | F4: VACIO 1.25 | G4: RETECION
A5: 45869 | B5: F | C5: 20.8
A6: 45869 | B6: F | C6: 9.2
A7: 45883 | B7: E | C7: -30
A8: 45898 | B8: F | C8: 42.39
A9: 45904 | B9: E | C9: -42.41
A10: 45904 | B10: F | C10: 32.55
A11: 45911 | B11: E | C11: -32.58
A12: 45911 | B12: F | C12: 24.2
A13: 45920 | B13: E | C13: -24.22
A14: 45925 | B14: F | C14: 58.03
A15: 45932 | B15: E | C15: -57.96
A16: 45939 | B16: F | C16: 40.02
... A44: 46045 | B44: T | C44: -60

Sheet BODEGA EL GATO
A1: CLIENTE | B1: BODEGA EL GATO
A2: NOMBRE | B2: YOLYMAR DELGADO
A3: TOTALES | C3: =SUM(C$4:C$1048576) -> 13.42 | D3: =SUM(D$4:D$1048576) -> 0 | E3: =SUM(E$5:E$1048576) -> 0 | F3: =SUM(F$5:F$1048576) -> 0 | G3: =SUM(G$5:G$1048576) -> 0
A4: FECHA | B4: F- E- T- | C4: DEUDA Y ABONOS | D4: VACIO 1/4 | E4: VACIO 350 | F4: VACIO 1.25 | G4: RETECION
A5: 45910 | B5: F | C5: 44.28
A6: 45917 | B6: T | C6: -44.28
A7: 45917 | B7: F | C7: 15
A8: 45917 | B8: F | C8: 51.25
A9: 45924 | B9: E | C9: -66.15
A10: 45924 | B10: F | C10: 12.4
A11: 45924 | B11: F | C11: 12.01
A12: 45932 | B12: T | C12: -24.52
A13: 45938 | B13: F | C13: 12.1
A14: 45938 | B14: F | C14: 33.63
A15: 45945 | B15: E | C15: -45.73
A16: 45967 | B16: F | C16: 19.6
... A30: 46044 | B30: F | C30: 13.45

Sheet BODEGA EL SOL
A1: CLIENTE | B1: BODEGA EL SOL
A2: NOMBRE | B2: ROSA VALERO
A3: TOTALES | C3: =SUM(C$4:C$1048576) -> 29.52 | D3: =SUM(D$4:D$1048576) -> 0 | E3: =SUM(E$5:E$1048576) -> 0 | F3: =SUM(F$5:F$1048576) -> 0 | G3: =SUM(G$5:G$1048576) -> 0
A4: FECHA | B4: F- E- T- | C4: DEUDA Y ABONOS | D4: VACIO 1/4 | E4: VACIO 350 | F4: VACIO 1.25 | G4: RETECION
A5: 45853 | B5: F | C5: 180
A6: 45853 | B6: F | C6: 9.2
A7: 45853 | B7: F | C7: 39.06
A8: 45861 | B8: T | C8: -46.5
A9: 45873 | B9: T | C9: -47.51
A10: 45873 | B10: T | C10: -21.38
A11: 45877 | B11: T | C11: -46.13
A12: 45881 | B12: E | C12: -47
A13: 45881 | B13: F | C13: 161.6
A14: 45882 | B14: T | C14: -7.59
A15: 45882 | B15: T | C15: -12.07
A16: 45887 | B16: T | C16: -73.05
... A33: 46049 | B33: F | C33: 29.52

Sheet BODEGA EXPRESS
A1: CLIENTE | B1: BODEGA EXPRESS
A2: NOMBRE | B2: GERMAN CALDERON
A3: TOTALES | C3: =SUM(C$4:C$1048576) -> 441.92 | D3: =SUM(D$4:D$1048576) -> 0 | E3: =SUM(E$5:E$1048576) -> 0 | F3: =SUM(F$5:F$1048576) -> -1 | G3: =SUM(G$5:G$1048576) -> 0
A4: FECHA | B4: F- E- T- | C4: DEUDA Y ABONOS | D4: VACIO 1/4 | E4: VACIO 350 | F4: VACIO 1.25 | G4: RETECION
A5: 45815 | B5: F | C5: 9.84
A6: 45815 | B6: F | C6: 93.84
A7: 45821 | B7: T | C7: -70
A8: 45821 | B8: F | C8: 41.54
A9: 45821 | B9: F | C9: 243.06
A10: 45827 | B10: T | C10: -269.92
A11: 45828 | B11: F | C11: 191.19
A12: 45842 | B12: T | C12: -212.56
A13: 45845 | B13: T | C13: -26.99
A14: 45842 | B14: F | C14: 15.85
A15: 45842 | B15: F | C15: 234.64
A16: 45849 | B16: F | C16: 15.85
... A31: 45884 | B31: T | C31: -350.46
A32: 45884 | B32: F | C32: 47.55 | D32: 2
A33: 45884 | B33: F | C33: 147.71
A34: 45884 | B34: F | C34: 5.93
A35: 45891 | B35: F | C35: 19.68
A36: 45891 | B36: F | C36: 174.32
A37: 45897 | B37: T | C37: -285
A38: 45898 | B38: F | C38: 9.84
A39: 45898 | B39: F | C39: 282.74
A40: 45905 | B40: T | C40: -372.77
A41: 45905 | B41: F | C41: 27.18 | D41: -1
A42: 45905 | B42: F | C42: 127.22
A43: 45905 | B43: F | C43: 8.76
A44: 45912 | B44: T | C44: -193.16
A45: 45912 | B45: F | C45: 40.7
A46: 45912 | B46: F | C46: 90.12
A47: 45912 | B47: F | C47: 126.82
A48: 45919 | B48: T | C48: -34.86
A49: 45919 | B49: F | C49: 34.9
A50: 45919 | B50: F | C50: 139.21
A51: 45919 | B51: F | C51: 19.68
A52: 45926 | B52: T | C52: -416.57
A53: 45926 | B53: F | C53: 40.69
... A56: 45926 | B56: F | C56: 23.62
A57: 45933 | B57: F | C57: 49.04 | D57: 1
A58: 45933 | B58: F | C58: 143.45
A59: 45933 | B59: F | C59: 79.16
A60: 45933 | B60: F | C60: 12.76
A61: 45940 | B61: F | C61: 110.36
A62: 45942 | B62: T | C62: -400
A63: 45943 | B63: T | C63: -241.52
A64: 45946 | B64: T | C64: -110.36
A65: 45947 | B65: F | C65: 16.38
A66: 45947 | B66: F | C66: 112.66
A67: 45947 | B67: F | C67: 130.08
A68: 45947 | B68: F | C68: 11.68
A69: 45954 | B69: F | C69: 76.63
... A81: 45996 | B81: F | C81: 658.85
A82: 46003 | B82: F | C82: 520.26 | D82: -1 | F82: -1
A83: 46010 | B83: F | C83: 470.43 | D83: -1
A84: 46012 | B84: T | C84: -856
A85: 46017 | B85: T | C85: -417.72
A86: 46017 | B86: T | C86: -165.78
A87: 46017 | B87: F | C87: 678.04 | D87: 1
A88: 46021 | B88: F | C88: 16.38 | D88: 1
A89: 46028 | B89: T | C89: -904.46
A90: 46031 | B90: F | C90: 453.89 | D90: -2
A91: 46038 | B91: F | C91: 441.92
A92: 46048 | B92: T | C92: -453.89

Sheet BODEGA EL GUARO
A1: CLIENTE | B1: BODEGA EL GUARO
A2: NOMBRE | B2: SORANYL VILLAMIZAR
A3: TOTALES | C3: =SUM(C$4:C$1048576) -> -0.4 | D3: =SUM(D$4:D$1048576) -> 0 | E3: =SUM(E$5:E$1048576) -> 0 | F3: =SUM(F$5:F$1048576) -> 0 | G3: =SUM(G$5:G$1048576) -> 0
A4: FECHA | B4: F- E- T- | C4: DEUDA Y ABONOS | D4: VACIO 1/4 | E4: VACIO 350 | F4: VACIO 1.25 | G4: RETECION
A5: 45960 | B5: F | C5: 12.1
A6: 45960 | B6: F | C6: 50.52
A7: 45967 | B7: F | C7: 21.94
A8: 45968 | B8: F | C8: 44.04
A9: 45978 | B9: T | C9: -30
A10: 45992 | B10: T | C10: -67
A11: 45999 | B11: T | C11: -32

Sheet BODEGA DONITA
A1: CLIENTE | B1: BODEGA DONITA
A2: NOMBRE | B2: YUDY NINO
A3: TOTALES | C3: =SUM(C$4:C$1048576) -> -0.05 | D3: =SUM(D$4:D$1048576) -> 0 | E3: =SUM(E$5:E$1048576) -> 0 | F3: =SUM(F$5:F$1048576) -> 0 | G3: =SUM(G$5:G$1048576) -> 0
A4: FECHA | B4: F- E- T- | C4: DEUDA Y ABONOS | D4: VACIO 1/4 | E4: VACIO 350 | F4: VACIO 1.25 | G4: RETECION
A5: 45821 | B5: F | C5: 20.77
A6: 45828 | B6: T | C6: -15.85
A7: 45828 | B7: T | C7: -4.68
A8: 45828 | B8: F | C8: 43.33
A9: 45841 | B9: E | C9: -15.85
A10: 45841 | B10: E | C10: -27.75
A11: 45841 | B11: F | C11: 30.61
A12: 45848 | B12: E | C12: -30.62
A13: 45856 | B13: F | C13: 9.84
A14: 45876 | B14: T | C14: -9.84
A15: 45876 | B15: F | C15: 30.61
A16: 45882 | B16: T | C16: -30.61
... A54: 46013 | B54: T | C54: -51.26

Sheet BODEGA ESCALANTE
A1: CLIENTE | B1: BODEGA ESCALANTE
A2: NOMBRE | B2: MARIA BAUTISTA
A3: TOTALES | C3: =SUM(C$4:C$1048576) -> -1.2 | D3: =SUM(D$4:D$1048576) -> 0 | E3: =SUM(E$5:E$1048576) -> 0 | F3: =SUM(F$5:F$1048576) -> 0 | G3: =SUM(G$5:G$1048576) -> 0
A4: FECHA | B4: F- E- T- | C4: DEUDA Y ABONOS | D4: VACIO 1/4 | E4: VACIO 350 | F4: VACIO 1.25 | G4: RETECION
A5: 45835 | B5: F | C5: 12.1
A6: 45835 | B6: F | C6: 81.76
A7: 45842 | B7: T | C7: -93.86
A8: 45842 | B8: F | C8: 9.84
A9: 45842 | B9: F | C9: 91.14
A10: 45849 | B10: T | C10: -100.98
A11: 45849 | B11: F | C11: 7.5
A12: 45849 | B12: F | C12: 74.66
A13: 45855 | B13: T | C13: -82.16
A14: 45856 | B14: F | C14: 41.6
A15: 45856 | B15: F | C15: 15.85
A16: 45856 | B16: F | C16: 20.52
... A23: 45996 | B23: T | C23: -7.06

Sheet BODEGA LOS CHACAROS
A1: CLIENTE | B1: BODEGA LOS CHACAROS
A2: NOMBRE | B2: YANET
A3: TOTALES | C3: =SUM(C$4:C$1048576) -> 0 | D3: =SUM(D$4:D$1048576) -> 2 | E3: =SUM(E$5:E$1048576) -> 0 | F3: =SUM(F$5:F$1048576) -> 0 | G3: =SUM(G$5:G$1048576) -> 0
A4: FECHA | B4: F- E- T- | C4: DEUDA Y ABONOS | D4: VACIO 1/4 | E4: VACIO 350 | F4: VACIO 1.25 | G4: RETECION
A5: 45817 | B5: T | C5: -25.69
A6: 45815 | B6: F | C6: 25.69
A7: 45821 | B7: T | C7: -16.02
A8: 45821 | B8: F | C8: 15.85
A9: 45838 | B9: T | C9: -25.65
A10: 45835 | B10: F | C10: 25.69
A11: 45849 | B11: T | C11: -15.98
A12: 45849 | B12: F | C12: 15.85
A13: 45859 | B13: T | C13: -19.68
A14: 45860 | B14: F | C14: 19.68
A15: 45873 | B15: T | C15: -25.51
A16: 45870 | B16: F | C16: 25.69
... A56: 45979 | B56: T | C56: -450
A57: 45979 | B57: F | C57: 516.94 | D57: 1
A58: 45980 | B58: T | C58: -86.62
A59: 45989 | B59: T | C59: -445.4 | K59: PENDIENTE EL DEPACHO DE 24 PEPSI COLOCAR DESCUENTO 22.8
A60: 45989 | B60: F | C60: 445.4
A61: 45998 | B61: T | C61: -674.04
A62: 45996 | B62: F | C62: 674.06
A63: 45996 | B63: % | C63: -22.8
A64: 46000 | B64: F | C64: 274.8
A65: 46001 | B65: T | C65: -274.8
A66: 46010 | B66: T | C66: -436.92
A67: 46010 | B67: F | C67: 432.5 | D67: 1
A68: 46017 | B68: T | C68: -481.7
A69: 46017 | B69: F | C69: 475.65
A70: 46038 | B70: T | C70: -74.96
A71: 46038 | B71: F | C71: 110.45
A72: 46055 | B72: T | C72: -538.85
A73: 46052 | B73: F | C73: 538.86

Sheet BODEGA MARIA
A1: CLIENTE | B1: BODEGA MARIA
A2: NOMBRE | B2: JANCITO BELLO
A3: TOTALES | C3: =SUM(C$4:C$1048576) -> 0 | D3: =SUM(D$4:D$1048576) -> 0 | E3: =SUM(E$5:E$1048576) -> 0 | F3: =SUM(F$5:F$1048576) -> 0 | G3: =SUM(G$5:G$1048576) -> 0
A4: FECHA | B4: F- E- T- | C4: DEUDA Y ABONOS | D4: VACIO 1/4 | E4: VACIO 350 | F4: VACIO 1.25 | G4: RETECION
A5: 45917 | B5: T | C5: -55.51
A6: 45917 | B6: F | C6: 25.69
A7: 45917 | B7: F | C7: 29.82

Sheet BODEGA MARITZA
A1: CLIENTE | B1: BODEGA MARITZA
A2: NOMBRE | B2: ROJAS
A3: TOTALES | C3: =SUM(C$4:C$1048576) -> 166.64 | D3: =SUM(D$4:D$1048576) -> 0 | E3: =SUM(E$5:E$1048576) -> 0 | F3: =SUM(F$5:F$1048576) -> 0 | G3: =SUM(G$5:G$1048576) -> 0
A4: FECHA | B4: F- E- T- | C4: DEUDA Y ABONOS | D4: VACIO 1/4 | E4: VACIO 350 | F4: VACIO 1.25 | G4: RETECION
A5: 45833 | B5: F | C5: 32.64
A6: 45833 | B6: F | C6: 144.83
A7: 45839 | B7: T | C7: -143.41
A8: 45840 | B8: T | C8: -34.06
A9: 45840 | B9: F | C9: 19.68
A10: 45840 | B10: F | C10: 145.06
A11: 45846 | B11: T | C11: -164.74
A12: 45847 | B12: F | C12: 7.8
A13: 45847 | B13: F | C13: 82.87
A14: 45847 | B14: F | C14: 5.4
A15: 45853 | B15: T | C15: -96.08
A16: 45854 | B16: F | C16: 7.5
... A103: 46056 | B103: T | C103: -80

Sheet BODEGA MILAGRO
A1: CLIENTE | B1: BODEGA MILAGRO
A2: NOMBRE | B2: MILAGRO BARRETO
A3: TOTALES | C3: =SUM(C$4:C$1048576) -> 0.09 | D3: =SUM(D$4:D$1048576) -> 0 | E3: =SUM(E$5:E$1048576) -> 0 | F3: =SUM(F$5:F$1048576) -> 0 | G3: =SUM(G$5:G$1048576) -> 0
A4: FECHA | B4: F- E- T- | C4: DEUDA Y ABONOS | D4: VACIO 1/4 | E4: VACIO 350 | F4: VACIO 1.25 | G4: RETECION
A5: 45819 | B5: F | C5: 17.54
A6: 45819 | B6: F | C6: 93.91
A7: 45825 | B7: T | C7: -111.44
A8: 45826 | B8: F | C8: 26.46
A9: 45826 | B9: F | C9: 6.42
A10: 45833 | B10: T | C10: -32.88
A11: 45833 | B11: F | C11: 15.85
A12: 45833 | B12: F | C12: 36.14
A13: 45839 | B13: T | C13: -51.61
A14: 45840 | B14: F | C14: 7.5
A15: 45840 | B15: F | C15: 31.55
A16: 45840 | B16: F | C16: 6.42
... A97: 46052 | B97: F | C97: 17.28

Sheet BODEGA MILAGROS
A1: CLIENTE | B1: BODEGA MILAGROS
A2: NOMBRE | B2: MILAGROS ZAMBRANO
A3: TOTALES | C3: =SUM(C$4:C$1048576) -> 0.96 | D3: =SUM(D$4:D$1048576) -> 0 | E3: =SUM(E$5:E$1048576) -> 0 | F3: =SUM(F$5:F$1048576) -> 0 | G3: =SUM(G$5:G$1048576) -> 0
A4: FECHA | B4: F- E- T- | C4: DEUDA Y ABONOS | D4: VACIO 1/4 | E4: VACIO 350 | F4: VACIO 1.25 | G4: RETECION
A5: 45821 | B5: T | C5: -31.7
A6: 45821 | B6: F | C6: 31.7
A7: 45828 | B7: T | C7: -118.64
A8: 45828 | B8: F | C8: 118.64
A9: 45842 | B9: T | C9: -72.52
A10: 45842 | B10: F | C10: 15
A11: 45842 | B11: F | C11: 57.52
A12: 45849 | B12: T | C12: -15.54
A13: 45849 | B13: F | C13: 9.84
A14: 45849 | B14: F | C14: 5.58
A15: 45859 | B15: T | C15: -51.38
A16: 45856 | B16: F | C16: 51.38
... A40: 46013 | B40: T | C40: -61.38

Sheet BODEGA NANCYTA
A1: CLIENTE | B1: BODEGA NANCYTA
A2: NOMBRE | B2: NANCY MONSALVE
A3: TOTALES | C3: =SUM(C$4:C$1048576) -> 63.67 | D3: =SUM(D$4:D$1048576) -> 0 | E3: =SUM(E$5:E$1048576) -> 0 | F3: =SUM(F$5:F$1048576) -> 0 | G3: =SUM(G$5:G$1048576) -> 0
A4: FECHA | B4: F- E- T- | C4: DEUDA Y ABONOS | D4: VACIO 1/4 | E4: VACIO 350 | F4: VACIO 1.25 | G4: RETECION
A5: 45818 | B5: F | C5: 20.8
A6: 45818 | B6: F | C6: 25.69
A7: 45818 | B7: F | C7: 80.63
A8: 45825 | B8: E | C8: -128.53
A9: 45825 | B9: F | C9: 15.4
A10: 45832 | B10: T | C10: -15.46
A11: 45832 | B11: F | C11: 20.8
A12: 45832 | B12: F | C12: 9.84
A13: 45832 | B13: F | C13: 5.46
A14: 45839 | B14: E | C14: -20.8
A15: 45839 | B15: E | C15: -15.4
A16: 45839 | B16: F | C16: 41.6
... A89: 45993 | B89: E | C89: -54.85
A90: 46000 | B90: F | C90: =92.71-2.25 -> 90.46
A91: 46007 | B91: E | C91: -90.46
A92: 46007 | B92: F | C92: 75.82
A93: 46021 | B93: E | C93: -75.8
A94: 46021 | B94: F | C94: 65.79
A95: 46028 | B95: E | C95: -65.81
A96: 46028 | B96: F | C96: 52.1
A97: 46042 | B97: T | C97: -52.08
A98: 46042 | B98: F | C98: 27.6
A99: 46049 | B99: T | C99: -29.98
A100: 46049 | B100: F | C100: 75.34
A101: 46056 | B101: E | C101: -72.96
A102: 46056 | B102: F | C102: 63.67

Sheet BODEGA NAZARENO
A1: CLIENTE | B1: BODEGA NAZARENO
A2: NOMBRE | B2: CAROLINA SANCHEZ
A3: TOTALES | C3: =SUM(C$4:C$1048576) -> 305.47 | D3: =SUM(D$4:D$1048576) -> 0 | E3: =SUM(E$5:E$1048576) -> 0 | F3: =SUM(F$5:F$1048576) -> 0 | G3: =SUM(G$5:G$1048576) -> 0
A4: FECHA | B4: F- E- T- | C4: DEUDA Y ABONOS | D4: VACIO 1/4 | E4: VACIO 350 | F4: VACIO 1.25 | G4: RETECION
A5: 45813 | B5: F | C5: 17.54
A6: 45813 | B6: F | C6: 77.85
A7: 45819 | B7: T | C7: -95.39
A8: 45819 | B8: F | C8: 145.6
A9: 45819 | B9: F | C9: 15.85
A10: 45819 | B10: F | C10: 66.68
A11: 45819 | B11: F | C11: 5.15
A12: 45827 | B12: T | C12: -233.28
A13: 45826 | B13: F | C13: 26.99
A14: 45833 | B14: T | C14: -26.99
A15: 45833 | B15: F | C15: 55.66
A16: 45833 | B16: F | C16: 40.78
... A102: 46050 | B102: F | C102: 74.33

Sheet BODEGA Y PAPELERIA REY
A1: CLIENTE | B1: BODEGA Y PAPELERIA REY
A2: NOMBRE | B2: EUDES REY
A3: TOTALES | C3: =SUM(C$4:C$1048576) -> 230.945 | D3: =SUM(D$4:D$1048576) -> 0 | E3: =SUM(E$5:E$1048576) -> 0 | F3: =SUM(F$5:F$1048576) -> 0 | G3: =SUM(G$5:G$1048576) -> 0
A4: FECHA | B4: F- E- T- | C4: DEUDA Y ABONOS | D4: VACIO 1/4 | E4: VACIO 350 | F4: VACIO 1.25 | G4: RETECION
A5: 45821 | B5: F | C5: 84.8
A6: 45821 | B6: F | C6: 23.1
A7: 45821 | B7: F | C7: 83.64
A8: 45821 | B8: F | C8: 11.3
A9: 45824 | B9: T | C9: -202.86
A10: 45828 | B10: F | C10: 41.6
A11: 45828 | B11: F | C11: 159.86
A12: 45832 | B12: T | C12: -201.46
A13: 45859 | B13: T | C13: -168.73
A14: 45856 | B14: F | C14: 151.78
A15: 45856 | B15: F | C15: 16.69
A16: 45863 | B16: F | C16: 9.84
... A75: 46052 | B75: F | C75: 228.14

Sheet BODEGON AGUA LINDA
A1: CLIENTE | B1: BODEGON AGUA LINDA
A2: NOMBRE
A3: TOTALES | C3: =SUM(C$4:C$1048576) -> 171.7 | D3: =SUM(D$4:D$1048576) -> 1 | E3: =SUM(E$5:E$1048576) -> 0 | F3: =SUM(F$5:F$1048576) -> 0 | G3: =SUM(G$5:G$1048576) -> 0
A4: FECHA | B4: F- E- T- | C4: DEUDA Y ABONOS | D4: VACIO 1/4 | E4: VACIO 350 | F4: VACIO 1.25 | G4: RETECION
A5: 45818 | B5: F | C5: =75.15-G5 -> 67.38 | G5: 7.77
A6: 45818 | B6: F | C6: =187.24-G6 -> 180.36 | G6: 6.88
A7: 45827 | B7: T | C7: -242.86
A8: 45827 | B8: T | C8: -4.69
A9: 45834 | B9: F | C9: =190.36-G9 -> 183.23 | G9: 7.13
A10: 45854 | B10: F | C10: =99.14-G10 -> 58.69 | G10: 40.45
A11: 45854 | B11: F | C11: 398.06
A12: 45854 | B12: F | C12: 28.3
A13: 45855 | B13: R | G13: -14.64
A14: 45855 | B14: R | G14: -7.13
A15: 45866 | B15: R | G15: -40.46
A16: 45875 | B16: T | C16: -120.42
A17: 45875 | B17: T | C17: -14.17
A18: 45875 | B18: T | C18: -468.67
A19: 45875 | B19: T | C19: -12.91
A20: 45875 | B20: T | C20: -55.39
A21: 45883 | B21: F | C21: =108.89-G21 -> 97.63 | G21: 11.26
A22: 45883 | B22: F | C22: =252.53-G22 -> 246.93 | G22: 5.6
A23: 45883 | B23: F | C23: =70.28-G23 -> 63.01 | G23: 7.27
A24: 45897 | B24: T | C24: -383.25 | G24: -24.13
A25: 45897 | B25: T | C25: -7.98
A26: 45898 | B26: F | C26: =39.34-G26 -> 35.28 | G26: 4.06
A27: 45898 | B27: F | C27: =35.54-G27 -> 34.05 | G27: 1.49
A28: 45904 | B28: R | G28: -5.55
A29: 45909 | B29: T | C29: -68.1
A30: 45909 | B30: T | C30: -1.77
A31: 45911 | B31: F | C31: =79-G31 -> 76.52 | G31: 2.48
A32: 45918 | B32: F | C32: =143.82-G32 -> 128.95 | D32: 1 | G32: 14.87 | N32: =9098.24/243.1105 -> 37.424299
A33: 45918 | B33: F | C33: =292.13-G33 -> 279.66 | G33: 12.47
A34: 45937 | B34: T | C34: -388.38
A35: 45937 | B35: T | C35: -8.05 | G35: -2.48
A36: 45937 | B36: T | C36: -75.68
A37: 45937 | B37: T | C37: -0.75
A38: 45939 | B38: F | C38: =110.23-G38 -> 98.83 | G38: 11.4
A39: 45939 | B39: F | C39: =293.53-G39 -> 287.18 | G39: 6.35
A40: 45939 | B40: F | C40: 457.14
A41: 45957 | B41: T | C41: -457.14
A42: 45961 | B42: T | C42: -6.7 | G42: -17.75 | J42: =4494.18/219.8737 -> 20.439825
A43: 45964 | B43: T | C43: -379.94 | G43: -27.34
A44: 45988 | B44: F | C44: =461.48-G44 -> 424.69 | G44: 36.79
A45: 46008 | B45: T | C45: -415.17
A46: 46008 | B46: T | C46: -10.97 | G46: -36.79 | J46: =3315.82/325.3894 -> 10.190314
A47: 46030 | B47: F | C47: =158.44-G47 -> 148.41 | G47: 10.03
A48: 46035 | B48: R | G48: -10.03
A49: 46043 | B49: T | C49: -147.29
A50: 46043 | B50: T | C50: -3.21
A51: 46044 | B51: F | C51: =164-G51 -> 150.89 | G51: 13.11 | N51: =5186.89/352.7063 -> 14.705975
A52: 46045 | G52: -13.11

Sheet BODEGON ANDREA'S
A1: CLIENTE | B1: BODEGON ANDREA'S
A2: NOMBRE
A3: TOTALES | C3: =SUM(C$4:C$1048576) -> 0 | D3: =SUM(D$4:D$1048576) -> 0 | E3: =SUM(E$5:E$1048576) -> 0 | F3: =SUM(F$5:F$1048576) -> 0 | G3: =SUM(G$5:G$1048576) -> 0
A4: FECHA | B4: F- E- T- | C4: DEUDA Y ABONOS | D4: VACIO 1/4 | E4: VACIO 350 | F4: VACIO 1.25 | G4: RETECION
A5: 45819 | B5: F | C5: 41.09
A6: 45819 | B6: F | C6: 229.6
A7: 45819 | B7: F | C7: 28.66
A8: 45825 | B8: T | C8: -183.63
A9: 45834 | B9: T | C9: -115.72
A10: 45846 | B10: F | C10: 25.69
A11: 45846 | B11: F | C11: 72.46
A12: 45867 | B12: T | C12: -98.15
A13: 45874 | B13: F | C13: 23.35
A14: 45874 | B14: F | C14: 92.42
A15: 45874 | B15: F | C15: 11.3
A16: 45889 | B16: T | C16: -127.46
... A49: 46042 | B49: T | C49: -100

Sheet BODEGON DE ELIDA
A1: CLIENTE | B1: BODEGON DE ELIDA
A2: NOMBRE
A3: TOTALES | C3: =SUM(C$4:C$1048576) -> 41.73 | D3: =SUM(D$4:D$1048576) -> 1 | E3: =SUM(E$5:E$1048576) -> 0 | F3: =SUM(F$5:F$1048576) -> 0 | G3: =SUM(G$5:G$1048576) -> 0
A4: FECHA | B4: F- E- T- | C4: DEUDA Y ABONOS | D4: VACIO 1/4 | E4: VACIO 350 | F4: VACIO 1.25 | G4: RETECION
A5: 45820 | B5: F | C5: 147.9
A6: 45820 | B6: F | C6: 47.1
A7: 45820 | B7: F | C7: 11.76 | H7: willi
A8: 45821 | B8: T | C8: -201.02
A9: 45821 | B9: T | C9: -5.74
A10: 45825 | B10: T | C10: -1400
A11: 45826 | B11: F | C11: 1594.4
A12: 45828 | B12: F | C12: 26.76
A13: 45834 | B13: F | C13: 882.4
A14: 45838 | B14: T | C14: -882.4
A15: 45841 | B15: T | C15: -221.16
A16: 45841 | B16: T | C16: -221.45
A17: 45841 | B17: F | C17: 173.9
A18: 45841 | B18: F | C18: 47.55
A19: 45847 | B19: T | C19: -1239.04
... A30: 45862 | B30: F | C30: 41.3
A31: 46003 | B31: F | C31: 41.78 | D31: 1

Sheet BODEGON DE OLGA
A1: CLIENTE | B1: BODEGON DE OLGA
A2: NOMBRE | B2: ANTONIO DELGADO
A3: TOTALES | C3: =SUM(C$4:C$1048576) -> 344.36 | D3: =SUM(D$4:D$1048576) -> 6 | E3: =SUM(E$5:E$1048576) -> 0 | F3: =SUM(F$5:F$1048576) -> 0 | G3: =SUM(G$5:G$1048576) -> 0
A4: FECHA | B4: F- E- T- | C4: DEUDA Y ABONOS | D4: VACIO 1/4 | E4: VACIO 350 | F4: VACIO 1.25 | G4: RETECION
A5: 45820 | B5: F | C5: 147.9
A6: 45820 | B6: F | C6: 47.1
A7: 45820 | B7: F | C7: 11.76 | H7: willi
A8: 45821 | B8: T | C8: -201.02
A9: 45821 | B9: T | C9: -5.74
A10: 45825 | B10: T | C10: -1400
A11: 45826 | B11: F | C11: 1594.4
A12: 45828 | B12: F | C12: 26.76
A13: 45834 | B13: F | C13: 882.4
A14: 45838 | B14: T | C14: -882.4
A15: 45841 | B15: T | C15: -221.16
A16: 45841 | B16: T | C16: -221.45
A17: 45841 | B17: F | C17: 173.9
A18: 45841 | B18: F | C18: 47.55
A19: 45847 | B19: T | C19: -1239.04
... A30: 45862 | B30: F | C30: 41.3
A31: 45869 | B31: F | C31: 561.6 | D31: 10
A32: 45869 | B32: F | C32: 31.7
A33: 45876 | B33: T | C33: -66.36
A34: 45876 | B34: F | C34: 15
A35: 45876 | B35: F | C35: 51.36
A36: 45877 | B36: T | C36: -588.97 | D36: -10
A37: 45882 | B37: F | C37: =813.4-G37 -> 729.26 | G37: 84.14
A38: 45884 | B38: T | C38: -730.57 | G38: -84.14
A39: 45890 | B39: R | G39: -138.15
A40: 45890 | B40: F | C40: =1335.5-G40 -> 1197.35 | G40: 138.15
A41: 45890 | B41: F | C41: 32.1
A42: 45891 | B42: T | C42: -1230.7
A43: 45897 | B43: T | C43: -1000
A44: 45897 | B44: F | C44: 1166.4
A45: 45898 | B45: T | C45: -166.4
A46: 45904 | B46: F | C46: =1077.1-G46 -> 965.68 | G46: 111.42
A47: 45904 | B47: F | C47: 88.85 | G47: -111.42
A48: 45908 | B48: T | C48: -973.96
A49: 45911 | B49: F | C49: 1484.4
A50: 45911 | B50: F | C50: 24.6
A51: 45915 | B51: T | C51: -1509
A52: 45918 | B52: F | C52: 672
A53: 45918 | B53: F | C53: 47.55
A54: 45922 | B54: T | C54: -651.26
A55: 45924 | B55: T | C55: -1352.54
A56: 45924 | B56: F | C56: 1304.8
A57: 45924 | B57: F | C57: 47.55
A58: 45924 | B58: F | C58: 35.38
A59: 45931 | B59: F | C59: 1179.9
... A61: 45932 | B61: T | C61: -551.56
A62: 45937 | B62: F | C62: =1736.36-G62 -> 1556.74 | G62: 179.62
A63: 45937 | B63: F | C63: 77.86
A64: 45939 | B64: T | C64: -1636.77
A65: 45947 | B65: F | C65: 1508.32
A66: 45950 | B66: T | C66: -1508.32
A67: 45952 | B67: F | C67: =998.8-G67 -> 895.48 | G67: 103.32
A68: 45952 | B68: F | C68: 58.74
A69: 45953 | B69: T | C69: -800.06
A70: 45953 | B70: T | C70: -108.48
A71: 45953 | B71: F | C71: 42.5
A72: 45960 | B72: F | C72: 2132.47
A73: 45960 | B73: F | C73: 191.44
A74: 45960 | B74: F | C74: 10.32
A75: 45961 | B75: T | C75: -1000
A76: 45964 | B76: T | C76: -950
A77: 45966 | B77: T | C77: -10.32
A78: 45966 | B78: T | C78: -423.91
A79: 45967 | B79: F | C79: 848.05
... A81: 45971 | B81: T | C81: -861.85
A82: 45973 | B82: F | C82: =1358.8-G82 -> 1221.6 | G82: 137.2
A83: 45978 | B83: T | C83: -1223.58
A84: 45982 | B84: F | C84: 575
A85: 45985 | B85: T | C85: -571.38
A86: 45989 | B86: T | C86: -579.67 | G86: -138.79
A87: 45989 | B87: F | C87: =1795.31-G87 -> 1656.52 | G87: 138.79
A88: 45993 | B88: T | C88: -1076.96
A89: 45995 | B89: f | C89: 623.06
A90: 45996 | B90: T | C90: -1177.07
A91: 45998 | B91: F | C91: 3478.7 | D91: 22
A92: 46001 | B92: T | C92: -950
A93: 46002 | B93: F | C93: =764.66-G93 -> 687.26 | G93: 77.4
A94: 46003 | B94: T | C94: -1900
A95: 46003 | B95: F | C95: 29.12
A96: 46008 | B96: T | C96: -578
A97: 46009 | B97: T | C97: -933.92
A98: 46009 | B98: F | C98: 1003.45 | D98: -16
A99: 46010 | B99: T | C99: -1003.45
A100: 46013 | B100: R | G100: -179.62
A101: 46013 | B101: R | G101: -103.31
A102: 46013 | B102: R | G102: -137.2
A103: 46013 | B103: R | G103: -77.41
A104: 46014 | B104: T | C104: -684.79
A105: 46014 | B105: F | C105: 1192.29
A106: 46015 | B106: F | C106: 52.82
A107: 46017 | B107: T | C107: -847.54
A108: 46017 | B108: F | C108: 971.79
A109: 46020 | B109: T | C109: -124.25
A110: 46021 | B110: F | C110: =955.97-G110 -> 881.92 | G110: 74.05
A111: 46021 | B111: R | G111: -74.05
A112: 46024 | B112: T | C112: -919.86
...

Sheet BODEGON D KSA
A1: CLIENTE | B1: BODEGON D KSA
A2: NOMBRE | B2: FERNANDO HERNANDEZ
A3: TOTALES | C3: =SUM(C$4:C$1048576) -> 78.29 | D3: =SUM(D$4:D$1048576) -> 0 | E3: =SUM(E$5:E$1048576) -> 0 | F3: =SUM(F$5:F$1048576) -> 0 | G3: =SUM(G$5:G$1048576) -> 0
A4: FECHA | B4: F- E- T- | C4: DEUDA Y ABONOS | D4: VACIO 1/4 | E4: VACIO 350 | F4: VACIO 1.25 | G4: RETECION
A5: 45825 | B5: F | C5: 10
A6: 45825 | B6: F | C6: 21.3
A7: 45839 | B7: T | C7: -31.3
A8: 45839 | B8: F | C8: 9.6
A9: 45839 | B9: F | C9: 12.28
A10: 45853 | B10: T | C10: -21.88
A11: 45853 | B11: F | C11: 23.33
A12: 45867 | B12: T | C12: -23.33
A13: 45867 | B13: F | C13: 9.6
A14: 45867 | B14: F | C14: 19.86
A15: 45888 | B15: T | C15: -29.46
A16: 45888 | B16: F | C16: 15.85
... A42: 46056 | B42: F | C42: 29.87

Sheet BODEGON D Y JD
A1: CLIENTE | B1: BODEGON D Y JD
A2: NOMBRE | B2: GLORIA PERNIA
A3: TOTALES | C3: =SUM(C$4:C$1048576) -> 0 | D3: =SUM(D$4:D$1048576) -> 0 | E3: =SUM(E$5:E$1048576) -> 0 | F3: =SUM(F$5:F$1048576) -> 0 | G3: =SUM(G$5:G$1048576) -> 0
A4: FECHA | B4: F- E- T- | C4: DEUDA Y ABONOS | D4: VACIO 1/4 | E4: VACIO 350 | F4: VACIO 1.25 | G4: RETECION
A5: 45845 | B5: T | C5: -204.65
A6: 45845 | B6: T | C6: -204.65
A7: 45842 | B7: F | C7: 61.2
A8: 45842 | B8: F | C8: 55.69
A9: 45842 | B9: F | C9: 269.01
A10: 45842 | B10: F | C10: 23.4
A11: 45868 | B11: F | C11: 20.8
A12: 45868 | B12: F | C12: 15.85
A13: 45868 | B13: F | C13: 9.9
A14: 45875 | B14: E | C14: -46.58
A15: 45875 | B15: F | C15: 41.6
A16: 45875 | B16: F | C16: 19.8
... A78: 46055 | B78: T | C78: -36.12

Sheet BODEGON EL COMPADRE
A1: CLIENTE | B1: BODEGON EL COMPADRE
A2: NOMBRE
A3: TOTALES | C3: =SUM(C$4:C$1048576) -> 147.59 | D3: =SUM(D$4:D$1048576) -> 0 | E3: =SUM(E$5:E$1048576) -> 0 | F3: =SUM(F$5:F$1048576) -> 0 | G3: =SUM(G$5:G$1048576) -> 0
A4: FECHA | B4: F- E- T- | C4: DEUDA Y ABONOS | D4: VACIO 1/4 | E4: VACIO 350 | F4: VACIO 1.25 | G4: RETECION
A5: 45834 | B5: F | C5: 122.4
A6: 45834 | B6: F | C6: 15.85
A7: 45840 | B7: T | C7: -55.26
A8: 45852 | B8: T | C8: -50.01
A9: 45854 | B9: T | C9: -33
A10: 45854 | B10: F | C10: 122.4
A11: 45854 | B11: F | C11: 15.85
A12: 45866 | B12: T | C12: -50
A13: 45880 | B13: T | C13: -50
A14: 45883 | B14: T | C14: -38.25
A15: 45883 | B15: F | C15: 159.2
A16: 45883 | B16: F | C16: 15.85
... A35: 46044 | B35: T | C35: -75

Sheet BODEGON ENDER GUERRERO
A1: CLIENTE | B1: BODEGON ENDER
A2: NOMBRE | B2: ENDER GUERRERO
A3: TOTALES | C3: =SUM(C$4:C$1048576) -> 1521.34 | D3: =SUM(D$4:D$1048576) -> 0 | E3: =SUM(E$5:E$1048576) -> 0 | F3: =SUM(F$5:F$1048576) -> 0 | G3: =SUM(G$5:G$1048576) -> 0
A4: FECHA | B4: F- E- T- | C4: DEUDA Y ABONOS | D4: VACIO 1/4 | E4: VACIO 350 | F4: VACIO 1.25 | G4: RETECION
A5: 45912 | B5: T | C5: -136.82
A6: 45912 | B6: F | C6: 46.7
A7: 45912 | B7: F | C7: 90.12
A8: 45919 | B8: T | C8: -131.75
A9: 45919 | B9: F | C9: 30
A10: 45919 | B10: F | C10: 92.74
A11: 45919 | B11: F | C11: 9
A12: 45926 | B12: F | C12: 79.16
A13: 45926 | B13: T | C13: -79.16
A14: 45933 | B14: T | C14: -7.5
A15: 45940 | B15: T | C15: -84.67
A16: 45940 | B16: F | C16: 30
... A57: 46052 | B57: F | C57: 924.24

Sheet BODEGON ENZO
A1: CLIENTE | B1: BODEGON ENZO
A2: NOMBRE
A3: TOTALES | C3: =SUM(C$4:C$1048576) -> 120.58 | D3: =SUM(D$4:D$1048576) -> 0 | E3: =SUM(E$5:E$1048576) -> 0 | F3: =SUM(F$5:F$1048576) -> 0 | G3: =SUM(G$5:G$1048576) -> 0
A4: FECHA | B4: F- E- T- | C4: DEUDA Y ABONOS | D4: VACIO 1/4 | E4: VACIO 350 | F4: VACIO 1.25 | G4: RETECION
A5: 45813 | B5: F | C5: 12.8
A6: 45813 | B6: F | C6: 103.69
A7: 45819 | B7: T | C7: -116.5
A8: 45825 | B8: F | C8: 23.55
A9: 45825 | B9: F | C9: 135.74
A10: 45825 | B10: F | C10: 9.63
A11: 45832 | B11: T | C11: -104.31
A12: 45832 | B12: T | C12: -64.61
A13: 45832 | B13: F | C13: 96.07
A14: 45832 | B14: F | C14: 8.25
A15: 45839 | B15: T | C15: -104.33
A16: 45839 | B16: F | C16: 9.84
... A76: 46056 | B76: F | C76: 100.14

Sheet BODEGON EXPRESS
A1: CLIENTE | B1: BODEGON EXPRESS
A2: NOMBRE | B2: NORLAIDA
A3: TOTALES | C3: =SUM(C$4:C$1048576) -> 76.964 | D3: =SUM(D$4:D$1048576) -> 0 | E3: =SUM(E$5:E$1048576) -> 0 | F3: =SUM(F$5:F$1048576) -> 0 | G3: =SUM(G$5:G$1048576) -> 0
A4: FECHA | B4: F- E- T- | C4: DEUDA Y ABONOS | D4: VACIO 1/4 | E4: VACIO 350 | F4: VACIO 1.25 | G4: RETECION
A5: 45813 | B5: F | C5: 15.85
A6: 45813 | B6: F | C6: 43.1
A7: 45849 | B7: E | C7: -31.25
A8: 45873 | B8: T | C8: -27.7
A9: 45874 | B9: F | C9: 15.85
A10: 45874 | B10: F | C10: 22.48
A11: 45881 | B11: T | C11: -7.18
A12: 45881 | B12: E | C12: -8.97
A13: 45881 | B13: F | C13: 39.12
A14: 45902 | B14: T | C14: -20
A15: 45902 | B15: F | C15: 15.85
A16: 45902 | B16: F | C16: 24.93
... A44: 46056 | B44: F | C44: 78.55

Sheet BODEGON EXPRESS LA ESMERALDA
A1: CLIENTE | B1: BODEGON EXPRESS LA ESMERALDA
A2: NOMBRE
A3: TOTALES | C3: =SUM(C$4:C$1048576) -> 377.91 | D3: =SUM(D$4:D$1048576) -> 1 | E3: =SUM(E$5:E$1048576) -> 0 | F3: =SUM(F$5:F$1048576) -> 0 | G3: =SUM(G$5:G$1048576) -> 0
A4: FECHA | B4: F- E- T- | C4: DEUDA Y ABONOS | D4: VACIO 1/4 | E4: VACIO 350 | F4: VACIO 1.25 | G4: RETECION
A5: 45924 | B5: T | C5: -35.3
A6: 45924 | B6: F | C6: 26.54
A7: 45924 | B7: F | C7: 86.22
A8: 45931 | B8: E | C8: -77.5
A9: 45931 | B9: F | C9: 60.96
A10: 45937 | B10: T | C10: -60.92
A11: 45938 | B11: F | C11: 33.72 | D11: 1
A12: 45938 | B12: F | C12: 128.85
A13: 45945 | B13: T | C13: -45.2
A14: 45945 | B14: E | C14: -78.92
A15: 45945 | B15: F | C15: 17.34
A16: 45945 | B16: F | C16: 64.52
A17: 45952 | B17: T | C17: -31.86
A18: 45952 | B18: E | C18: -54
A19: 45952 | B19: F | C19: 36.94
A20: 45952 | B20: F | C20: 246.86
A21: 45952 | B21: F | C21: 27.84
A22: 45957 | B22: T | C22: -35
A23: 45959 | B23: E | C23: -46.29
... A42: 46050 | B42: T | C42: -7.19

Sheet BODEGON EXPRESS MARI
A1: CLIENTE | B1: BODEGON EXPRESS MOLINA
A2: NOMBRE | B2: MARIFLOR MOLINA
A3: TOTALES | C3: =SUM(C$4:C$1048576) -> 50.19 | D3: =SUM(D$4:D$1048576) -> -1 | E3: =SUM(E$5:E$1048576) -> 0 | F3: =SUM(F$5:F$1048576) -> 0 | G3: =SUM(G$5:G$1048576) -> 0
A4: FECHA | B4: F- E- T- | C4: DEUDA Y ABONOS | D4: VACIO 1/4 | E4: VACIO 350 | F4: VACIO 1.25 | G4: RETECION
A5: 45819 | B5: F | C5: 9.84
A6: 45819 | B6: F | C6: 60.83
A7: 45824 | B7: T | C7: -29.37
A8: 45825 | B8: T | C8: -29.37
A9: 45828 | B9: F | C9: 74.8
A10: 45831 | B10: T | C10: -74.8
A11: 45834 | B11: T | C11: -12.24
A12: 45834 | B12: F | C12: 24.28
A13: 45834 | B13: F | C13: 40.03
A14: 45841 | B14: F | C14: 27.18
A15: 45841 | B15: F | C15: 36.77
A16: 45842 | B16: T | C16: -27.14
... A111: 46017 | B111: E | C111: -11.28
A112: 46017 | B112: F | C112: 112.5 | D112: 2
A113: 46024 | B113: T | C113: -50
A114: 46027 | B114: T | C114: -62.5
A115: 46031 | B115: F | C115: 107.24
A116: 46037 | B116: T | C116: -107.24
A117: 46038 | B117: F | C117: 73.59
A118: 46042 | B118: T | C118: -73.59
A119: 46044 | B119: F | C119: 170.86 | D119: -3
A120: 46051 | B120: T | C120: -39
A121: 46052 | B121: T | C121: -51
A122: 46055 | B122: T | C122: -29.76

Sheet BODEGON EXPRESS GREGORI
A1: CLIENTE | B1: BODEGON EXPRESS GREGORI
A2: NOMBRE | B2: NEILA
A3: TOTALES | C3: =SUM(C$4:C$1048576) -> 223.69 | D3: =SUM(D$4:D$1048576) -> 0 | E3: =SUM(E$5:E$1048576) -> 0 | F3: =SUM(F$5:F$1048576) -> 0 | G3: =SUM(G$5:G$1048576) -> 0
A4: FECHA | B4: F- E- T- | C4: DEUDA Y ABONOS | D4: VACIO 1/4 | E4: VACIO 350 | F4: VACIO 1.25 | G4: RETECION
A5: 45814 | B5: F | C5: 32.1
A6: 45814 | B6: F | C6: 15.85
A7: 45814 | B7: F | C7: 111.36
A8: 45821 | B8: T | C8: -69.25
A9: 45827 | B9: T | C9: -89.27
A10: 45828 | B10: F | C10: 20.8
A11: 45828 | B11: F | C11: 43.1
A12: 45828 | B12: F | C12: 228.48
A13: 45828 | B13: T | C13: -47.83
A14: 45838 | B14: T | C14: -74.33
A15: 45841 | B15: T | C15: -63.77
A16: 45845 | B16: T | C16: -89.75
... A86: 46045 | B86: F | C86: 239.84

Sheet BODEGON ESQUINA PARAMILLO
A1: CLIENTE | B1: BODEGON ESQUINA PARAMILLO
A2: NOMBRE | B2: BIANCA MASERATI
A3: TOTALES | C3: =SUM(C$4:C$1048576) -> 327.72 | D3: =SUM(D$4:D$1048576) -> 0 | E3: =SUM(E$5:E$1048576) -> 0 | F3: =SUM(F$5:F$1048576) -> 0 | G3: =SUM(G$5:G$1048576) -> 0
A4: FECHA | B4: F- E- T- | C4: DEUDA Y ABONOS | D4: VACIO 1/4 | E4: VACIO 350 | F4: VACIO 1.25 | G4: RETECION
A5: 45813 | B5: F | C5: 17.43
A6: 45813 | B6: F | C6: 42.94
A7: 45813 | B7: F | C7: 109.26
A8: 45818 | B8: T | C8: -169.21
A9: 45819 | B9: F | C9: 62.4
A10: 45819 | B10: F | C10: 45.64
A11: 45819 | B11: F | C11: 56.21
A12: 45825 | B12: T | C12: -164.66
A13: 45825 | B13: F | C13: 83.2
A14: 45825 | B14: F | C14: 34.86
A15: 45825 | B15: F | C15: 87.5
A16: 45825 | B16: F | C16: 16.5
... A129: 46056 | B129: F | C129: 80.9

Sheet BODEGON GARCIAS
A1: CLIENTE | B1: BODEGON GARCIAS
A2: NOMBRE | B2: GENESIS GARCIAS
A3: TOTALES | C3: =SUM(C$4:C$1048576) -> 45.35 | D3: =SUM(D$4:D$1048576) -> 0 | E3: =SUM(E$5:E$1048576) -> 0 | F3: =SUM(F$5:F$1048576) -> 0 | G3: =SUM(G$5:G$1048576) -> 0
A4: FECHA | B4: F- E- T- | C4: DEUDA Y ABONOS | D4: VACIO 1/4 | E4: VACIO 350 | F4: VACIO 1.25 | G4: RETECION
A5: 45835 | B5: F | C5: 41.6
A6: 45835 | B6: F | C6: 9.84
A7: 45835 | B7: F | C7: 76.22
A8: 45847 | B8: T | C8: -127.66
A9: 45940 | B9: F | C9: 9.84
A10: 45940 | B10: F | C10: 77.02
A11: 45953 | B11: T | C11: -86.86
A12: 45954 | B12: F | C12: 24.6
A13: 45962 | B13: T | C13: -24.6
A14: 45961 | B14: F | C14: 36.39
A15: 45968 | B15: F | C15: 9.84
A16: 45968 | B16: F | C16: 32.37
... A23: 46052 | B23: F | C23: 44.14

Sheet BODEGON JUANCHO
A1: CLIENTE | B1: BODEGON JUANCHO
A2: NOMBRE
A3: TOTALES | C3: =SUM(C$4:C$1048576) -> 7.2 | D3: =SUM(D$4:D$1048576) -> 0 | E3: =SUM(E$5:E$1048576) -> 0 | F3: =SUM(F$5:F$1048576) -> 0 | G3: =SUM(G$5:G$1048576) -> 0
A4: FECHA | B4: F- E- T- | C4: DEUDA Y ABONOS | D4: VACIO 1/4 | E4: VACIO 350 | F4: VACIO 1.25 | G4: RETECION
A5: 45817 | B5: T | C5: -43.04
A6: 45815 | B6: F | C6: 31.7
A7: 45815 | B7: F | C7: 11.34
A8: 45835 | B8: T | C8: -15.85
A9: 45835 | B9: F | C9: 15.85
A10: 45905 | B10: T | C10: -15.85
A11: 45905 | B11: F | C11: 15.85
A12: 45940 | B12: T | C12: -16.38
A13: 45940 | B13: F | C13: 16.38
A14: 45947 | B14: T | C14: -16.38
A15: 45947 | B15: F | C15: 16.38
A16: 45968 | B16: F | C16: 36.06
... A21: 46013 | B21: T | C21: -28.86

Sheet BODEGON KATERIN
A1: CLIENTE | B1: BODEGON KATERIN
A2: NOMBRE | B2: ROMERO
A3: TOTALES | C3: =SUM(C$4:C$1048576) -> -0.96 | D3: =SUM(D$4:D$1048576) -> 0 | E3: =SUM(E$5:E$1048576) -> 0 | F3: =SUM(F$5:F$1048576) -> 0 | G3: =SUM(G$5:G$1048576) -> 0
A4: FECHA | B4: F- E- T- | C4: DEUDA Y ABONOS | D4: VACIO 1/4 | E4: VACIO 350 | F4: VACIO 1.25 | G4: RETECION
A5: 45825 | B5: F | C5: 15.85
A6: 45825 | B6: F | C6: 41.6
A7: 45831 | B7: T | C7: -25.6
A8: 45840 | B8: E | C8: -32.81

Sheet BODEGON LA ESQUINA DE LUIS
A1: CLIENTE | B1: BODEGON LA ESQUINA DE LUIS
A2: NOMBRE | B2: DIANA CALDERON
A3: TOTALES | C3: =SUM(C$4:C$1048576) -> 136.54 | D3: =SUM(D$4:D$1048576) -> 0 | E3: =SUM(E$5:E$1048576) -> 0 | F3: =SUM(F$5:F$1048576) -> 0 | G3: =SUM(G$5:G$1048576) -> 0
A4: FECHA | B4: F- E- T- | C4: DEUDA Y ABONOS | D4: VACIO 1/4 | E4: VACIO 350 | F4: VACIO 1.25 | G4: RETECION
A5: 45821 | B5: F | C5: 62.4
A6: 45821 | B6: F | C6: 15.85
A7: 45821 | B7: F | C7: 40.74
A8: 45828 | B8: T | C8: -47.83
A9: 45833 | B9: T | C9: -71.16
A10: 45835 | B10: F | C10: 41.6
A11: 45835 | B11: F | C11: 9.84
A12: 45835 | B12: F | C12: 28.34
A13: 45841 | B13: T | C13: -51.93
A14: 45841 | B14: F | C14: 41.6
A15: 45841 | B15: F | C15: 4.6
A16: 45841 | B16: F | C16: 44.16
... A45: 45918 | B45: F | C45: 57.72
A46: 45920 | B46: F | C46: 41.6 | D46: 2
A47: 45925 | B47: T | C47: -108.81
A48: 45931 | B48: T | C48: -55.73
A49: 45932 | B49: F | C49: 64.8 | D49: -2
A50: 45932 | B50: F | C50: 30.28
A51: 45932 | B51: F | C51: 49.35
A52: 45944 | B52: T | C52: -101.4
A53: 45946 | B53: F | C53: 94.87
A54: 45946 | B54: F | C54: 34.44
A55: 45946 | B55: F | C55: 50.27
A56: 45960 | B56: F | C56: 8.28
A57: 45961 | B57: F | C57: 16.38
A58: 45972 | B58: T | C58: -86.54
A59: 45986 | B59: T | C59: -61.7
A60: 45988 | B60: F | C60: 16.38
A61: 45995 | B61: T | C61: -67.49

Sheet BODEGON LINARES
A1: CLIENTE | B1: BODEGON LINARES
A2: NOMBRE | B2: JUAN PABON
A3: TOTALES | C3: =SUM(C$4:C$1048576) -> 36.07 | D3: =SUM(D$4:D$1048576) -> 1 | E3: =SUM(E$5:E$1048576) -> 0 | F3: =SUM(F$5:F$1048576) -> 0 | G3: =SUM(G$5:G$1048576) -> 0
A4: FECHA | B4: F- E- T- | C4: DEUDA Y ABONOS | D4: VACIO 1/4 | E4: VACIO 350 | F4: VACIO 1.25 | G4: RETECION
A5: 45819 | B5: F | C5: 45.78
A6: 45826 | B6: T | C6: -45.78
A7: 45827 | B7: F | C7: 15.85
A8: 45827 | B8: F | C8: 64.24
A9: 45834 | B9: T | C9: -80.09
A10: 45834 | B10: F | C10: 4.6
A11: 45834 | B11: F | C11: 30.59
A12: 45838 | B12: T | C12: -35.19
A13: 45841 | B13: F | C13: 50.64
A14: 45848 | B14: T | C14: -52.84
A15: 45848 | B15: F | C15: 23.56
A16: 45854 | B16: T | C16: -23.36
... A33: 45904 | B33: F | C33: 22.93
A34: 45912 | C34: 29.19
A35: 45919 | B35: T | C35: -29.19
A36: 45920 | B36: E | C36: -38.7
A37: 45920 | B37: F | C37: 47.89
A38: 45925 | B38: T | C38: -35.5
A39: 45926 | B39: E | C39: -12.41
A40: 45926 | B40: F | C40: 15.85
A41: 45926 | B41: F | C41: 18.04
A42: 45933 | B42: F | C42: 32.46
A43: 45936 | B43: T | C43: -34
A44: 45940 | B44: T | C44: -32.79
A45: 45940 | B45: F | C45: 16.38 | D45: 1
A46: 45940 | B46: F | C46: 20.98
A47: 45948 | B47: T | C47: -37.36
A48: 45954 | B48: F | C48: 36.93
A49: 45961 | B49: F | C49: 16.38
A50: 45961 | B50: F | C50: 21.87
A51: 45968 | B51: T | C51: -38.25
A52: 45968 | B52: F | C52: 58.4
A53: 45974 | B53: E | C53: -58.42
A54: 45974 | B54: F | C54: 25.25
A55: 45979 | B55: T | C55: -36.93
A56: 45982 | B56: T | C56: -25.25
A57: 45982 | B57: F | C57: 29.08
... A71: 46052 | B71: F | C71: 7.79

Sheet BODEGON LOS NONOS
A1: CLIENTE | B1: BODEGON LOS NONOS
A2: NOMBRE
A3: TOTALES | C3: =SUM(C$4:C$1048576) -> 2853.59 | D3: =SUM(D$4:D$1048576) -> 0 | E3: =SUM(E$5:E$1048576) -> 0 | F3: =SUM(F$5:F$1048576) -> 0 | G3: =SUM(G$5:G$1048576) -> 0
A4: FECHA | B4: F- E- T- | C4: DEUDA Y ABONOS | D4: VACIO 1/4 | E4: VACIO 350 | F4: VACIO 1.25 | G4: RETECION
A5: 45819 | B5: F | C5: 55.67
A6: 45824 | B6: T | C6: -55.67
A7: 45832 | B7: F | C7: 125.16
A8: 45832 | B8: F | C8: 36.15
A9: 45834 | B9: T | C9: -161.31
A10: 45839 | B10: F | C10: 484.2
A11: 45839 | B11: F | C11: 25.68
A12: 45845 | B12: T | C12: -55.98
A13: 45845 | B13: T | C13: -453.9
A14: 45846 | B14: F | C14: 441.68
A15: 45846 | B15: F | C15: 10.17
A16: 45853 | B16: F | C16: 396.24
... A66: 45923 | B66: F | C66: 35.53
A67: 45923 | B67: F | C67: =1180.56-7.56 -> 1173
A68: 45923 | B68: F | C68: 9.36
A69: 45930 | B69: T | C69: -165.84
A70: 45930 | B70: T | C70: -1059.61
A71: 45930 | B71: F | C71: 9
A72: 45930 | B72: F | C72: =1451.09+0.96 -> 1452.05
A73: 45936 | B73: T | C73: -860.51
A74: 45936 | B74: T | C74: -590.58
A75: 45937 | B75: F | C75: 16.38
A76: 45937 | B76: F | C76: 1552.07
A77: 45937 | B77: F | C77: 87.2
A78: 45944 | B78: T | C78: -400
A79: 45944 | B79: F | C79: 791.42
A80: 45944 | B80: F | C80: 14.16
A81: 45946 | B81: T | C81: -1255.17
A82: 45950 | B82: T | C82: -805.58
A83: 45951 | B83: F | C83: 17.34
A84: 45951 | B84: F | C84: 2105.09
... A126: 46056 | B126: F | C126: 1564.77

Sheet BODEGON MACHIRI
A1: CLIENTE | B1: BODEGON MACHIRI
A2: NOMBRE
A3: TOTALES | C3: =SUM(C$4:C$1048576) -> 0 | D3: =SUM(D$4:D$1048576) -> 0 | E3: =SUM(E$5:E$1048576) -> 0 | F3: =SUM(F$5:F$1048576) -> 0 | G3: =SUM(G$5:G$1048576) -> 0
A4: FECHA | B4: F- E- T- | C4: DEUDA Y ABONOS | D4: VACIO 1/4 | E4: VACIO 350 | F4: VACIO 1.25 | G4: RETECION
A5: 45817 | B5: F | C5: 982.4
A6: 45817 | B6: F | C6: 28.55
A7: 45820 | B7: T | C7: -149.49
A8: 45831 | B8: T | C8: -312.94
A9: 45834 | B9: T | C9: -366.67
A10: 45839 | B10: V | C10: -181.85

Sheet BODEGON MKM
A1: CLIENTE | B1: BODEGON MKM
A2: NOMBRE | B2: KARINA CHAO
A3: TOTALES | C3: =SUM(C$4:C$1048576) -> 0.69 | D3: =SUM(D$4:D$1048576) -> 2 | E3: =SUM(E$5:E$1048576) -> 0 | F3: =SUM(F$5:F$1048576) -> 0 | G3: =SUM(G$5:G$1048576) -> 0
A4: FECHA | B4: F- E- T- | C4: DEUDA Y ABONOS | D4: VACIO 1/4 | E4: VACIO 350 | F4: VACIO 1.25 | G4: RETECION
A5: 45870 | B5: F | C5: 25.69
A6: 45870 | B6: F | C6: 74.76
A7: 45888 | B7: T | C7: -100.45
A8: 45891 | B8: F | C8: 9.84
A9: 45891 | B9: F | C9: 51.99
A10: 45903 | B10: T | C10: -61.83
A11: 45905 | B11: F | C11: 25.69
A12: 45905 | B12: F | C12: 68.94
A13: 45926 | B13: T | C13: -94.57
A14: 45926 | B14: F | C14: 41.6 | D14: 2
A15: 45926 | B15: F | C15: 25.69
A16: 45926 | B16: F | C16: 137.2
A17: 45964 | B17: T | C17: -204.55
A18: 45968 | B18: F | C18: 108.32
A19: 45982 | B19: T | C19: -107.63
A20: 46017 | B20: F | C20: 154.88
A21: 46042 | B21: T | C21: -90
A22: 46056 | B22: T | C22: -64.88

Sheet BODEGON SEVILLANA
A1: CLIENTE | B1: BODEGON SEVILLANA
A2: NOMBRE | B2: YUSMARVIC
A3: TOTALES | C3: =SUM(C$4:C$1048576) -> 1198.2 | D3: =SUM(D$4:D$1048576) -> 5 | E3: =SUM(E$5:E$1048576) -> 0 | F3: =SUM(F$5:F$1048576) -> 0 | G3: =SUM(G$5:G$1048576) -> 0
A4: FECHA | B4: F- E- T- | C4: DEUDA Y ABONOS | D4: VACIO 1/4 | E4: VACIO 350 | F4: VACIO 1.25 | G4: RETECION
A5: 45813 | B5: F | C5: 891.9
A6: 45820 | B6: F | C6: 944.65 | D6: 1
A7: 45820 | B7: F | C7: 25.4
A8: 45824 | B8: T | C8: -891.9
A9: 45825 | B9: T | C9: -480
A10: 45825 | B10: T | C10: -270
A11: 45827 | B11: F | C11: 242.9 | D11: -1
A12: 45827 | B12: F | C12: 15.85
A13: 45828 | B13: T | C13: -235.9
A14: 45832 | B14: T | C14: -242.9
A15: 45833 | B15: F | C15: 499.6
A16: 45833 | B16: F | C16: 7.5
A17: 45838 | B17: T | C17: -307.61
A18: 45839 | B18: T | C18: -201.1
A19: 45841 | B19: F | C19: 24.9
A20: 45841 | B20: F | C20: 15.85
A21: 45845 | B21: T | C21: -40.75
A22: 45848 | B22: F | C22: 323
A23: 45848 | B23: F | C23: 12.5
A24: 45848 | B24: T | C24: -335.5
A25: 45854 | B25: F | C25: 619 | D25: 7
A26: 45855 | B26: T | C26: -339.97
A27: 45859 | B27: T | C27: -209
A28: 45859 | B28: T | C28: -70
A29: 45868 | B29: T | C29: =-599.97 -> -599.97
A30: 45868 | B30: F | C30: 910.5
A31: 45873 | B31: T | C31: -216.31
A32: 45874 | B32: F | C32: 1303.6
A33: 45874 | B33: F | C33: 18.6
A34: 45875 | B34: T | C34: -92.64
A35: 45875 | B35: T | C35: -160
A36: 45875 | B36: T | C36: -305
A37: 45877 | B37: T | C37: -305
A38: 45880 | B38: T | C38: -551.2
A39: 45883 | B39: F | C39: =231.8-G39 -> 207.83 | G39: 23.97
A40: 45883 | B40: F | C40: 15.85
A41: 45890 | B41: F | C41: 1010.2
A42: 45891 | B42: T | C42: -280
A43: 45891 | B43: T | C43: -644.18
A44: 45895 | B44: T | C44: -80.2
A45: 45896 | B45: T | C45: -220 | G45: -23.97
A46: 45897 | B46: F | C46: 1159.7
A47: 45897 | B47: F | C47: 23.5
A48: 45898 | B48: F | C48: 21.26
A49: 45898 | B49: T | C49: -390
A50: 45901 | B50: T | C50: -793.22
A51: 45902 | B51: T | C51: -21.26
A52: 45902 | B52: F | C52: 984.7 | D52: =-7+18 -> 11
A53: 45903 | B53: T | C53: -230
A54: 45904 | B54: F | C54: 10.99
A55: 45908 | B55: T | C55: -580
A56: 45908 | B56: T | C56: -10.99
A57: 45909 | B57: T | C57: -102.46
A58: 45911 | B58: F | C58: =296.7-G58 -> 268.66 | G58: 28.04
A59: 45911 | B59: F | C59: 30.05
A60: 45911 | B60: F | C60: 13.21
A61: 45916 | B61: T | C61: -292.95 | G61: -28.04
A62: 45918 | B62: F | C62: 746.3 | D62: -11
A63: 45918 | B63: F | C63: 4.6
A64: 45925 | B64: F | C64: 623.2
A65: 45926 | B65: F | C65: 14.38
A66: 45929 | B66: T | C66: -623.21
A67: 45929 | B67: T | C67: -14.38
A68: 45931 | B68: T | C68: -462
A69: 45932 | B69: T | C69: -750.91
A70: 45931 | B70: F | C70: 575.2
A71: 45931 | B71: F | C71: 9.6
A72: 45936 | B72: T | C72: -122.8
A73: 45939 | B73: F | C73: 1031.73
A74: 45939 | B74: F | C74: 7.5
... A112: 46017 | B112: F | C112: 34.86
A113: 46020 | B113: F | C113: 1286.04 | D113: 9
A114: 46024 | B114: T | C114: -1286.04
A115: 46035 | B115: T | C115: -1107.66
A116: 46035 | B116: F | C116: 1107.64
A117: 46038 | B117: F | C117: 104.57
A118: 46038 | B118: % | C118: -7.2
A119: 46042 | B119: T | C119: -104.57
A120: 46044 | B120: F | C120: 352.28 | D120: -16
A121: 46049 | B121: T | C121: -352.28
A122: 46052 | B122: F | C122: 17.34
A123: 46055 | B123: F | C123: 591.33 | D123: 25
A124: 46055 | B124: T | C124: -608.67
A125: 46056 | B125: T | C125: -279.49
A126: 46056 | B126: F | C126: 580.39 | D126: -20

Sheet BODEGON TERESITA
A1: CLIENTE | B1: BODEGON TERESITA
A2: NOMBRE | B2: TERESA ALBARRACIN
A3: TOTALES | C3: =SUM(C$4:C$1048576) -> -0.16 | D3: =SUM(D$4:D$1048576) -> 0 | E3: =SUM(E$5:E$1048576) -> 0 | F3: =SUM(F$5:F$1048576) -> 0 | G3: =SUM(G$5:G$1048576) -> 0
A4: FECHA | B4: F- E- T- | C4: DEUDA Y ABONOS | D4: VACIO 1/4 | E4: VACIO 350 | F4: VACIO 1.25 | G4: RETECION
A5: 45820 | B5: F | C5: 31.25
A6: 45820 | B6: F | C6: 71.78
A7: 45826 | B7: E | C7: -103.12
A8: 45826 | B8: F | C8: 17.54
A9: 45826 | B9: F | C9: 73.59
A10: 45833 | B10: E | C10: -91.15
A11: 45833 | B11: F | C11: 14.2
A12: 45833 | B12: F | C12: 58.5
A13: 45840 | B13: E | C13: -72.59
A14: 45840 | B14: F | C14: 15.85
A15: 45840 | B15: F | C15: 51.91
A16: 45847 | B16: E | C16: -67.81
... A102: 46050 | B102: F | C102: 32.37

Sheet BODEGON UNICO
A1: CLIENTE | B1: BODEGON UNICO
A2: NOMBRE
A3: TOTALES | C3: =SUM(C$4:C$1048576) -> 555.45 | D3: =SUM(D$4:D$1048576) -> 2 | E3: =SUM(E$5:E$1048576) -> 0 | F3: =SUM(F$5:F$1048576) -> 0 | G3: =SUM(G$5:G$1048576) -> 0
A4: FECHA | B4: F- E- T- | C4: DEUDA Y ABONOS | D4: VACIO 1/4 | E4: VACIO 350 | F4: VACIO 1.25 | G4: RETECION
A5: 45813 | B5: F | C5: 92.53
A6: 45813 | B6: F | C6: 493.48
A7: 45813 | B7: F | C7: 141.81
A8: 45826 | B8: T | C8: -727.84
A9: 45832 | B9: F | C9: 69.02
A10: 45832 | B10: F | C10: 502.9
A11: 45832 | B11: F | C11: 139.84
A12: 45840 | B12: T | C12: -711.35
A13: 45846 | B13: F | C13: 40.18
A14: 45846 | B14: F | C14: 685.37
A15: 45867 | B15: T | C15: -500
A16: 45868 | B16: T | C16: -225.79
... A39: 46013 | B39: T | C39: -969.39
A40: 46014 | B40: F | C40: 651.99 | D40: 1
A41: 46027 | B41: T | C41: -613.7
A42: 46028 | B42: F | C42: 1033.12 | D42: 1
A43: 46049 | B43: T | C43: -197.29
A44: 46049 | B44: T | C44: -835.83
A45: 46049 | B45: F | C45: 555.45

Sheet CAFE RACER
A1: CLIENTE | B1: CAFE RACER
A2: NOMBRE
A3: TOTALES | C3: =SUM(C$4:C$1048576) -> 434.46 | D3: =SUM(D$4:D$1048576) -> 3 | E3: =SUM(E$5:E$1048576) -> 0 | F3: =SUM(F$5:F$1048576) -> 0 | G3: =SUM(G$5:G$1048576) -> 0
A4: FECHA | B4: F- E- T- | C4: DEUDA Y ABONOS | D4: VACIO 1/4 | E4: VACIO 350 | F4: VACIO 1.25 | G4: RETECION
A5: 45853 | B5: F | C5: 684.4
A6: 45853 | B6: F | C6: 55.31
A7: 45868 | B7: T | C7: -80.72
A8: 45868 | B8: T | C8: -161.45
A9: 45869 | B9: T | C9: -160.63
A10: 45874 | B10: T | C10: -332.81
A11: 45874 | B11: F | C11: 776 | D11: 10
A12: 45874 | B12: F | C12: 7.5
A13: 45886 | B13: T | C13: -211.84
A14: 45886 | B14: T | C14: -146.1
A15: 45890 | B15: T | C15: -121.95
A16: 45890 | B16: T | C16: -64.56
A17: 45891 | B17: T | C17: -235.19
A18: 45890 | B18: F | C18: 855.8 | D18: -10
A19: 45890 | B19: V | D19: 19
A20: 45890 | B20: F | C20: 84.2
A21: 45902 | B21: T | C21: -936.66
A22: 45903 | B22: T | C22: -44.51
A23: 45902 | B23: F | C23: 662.4 | D23: =-19+18 -> -1
A24: 45902 | B24: F | C24: 44.61
A25: 45922 | B25: T | C25: -362.25
A26: 45923 | B26: F | C26: 855.8
A27: 45923 | B27: F | C27: 157.57
A28: 45930 | B28: T | C28: -64.18
A29: 45931 | B29: F | C29: 639
A30: 45932 | B30: T | C30: -165.47
A31: 45933 | B31: T | C31: -174.73
A32: 45937 | B32: T | C32: -469.86
A33: 45938 | B33: T | C33: -300.15
A34: 45940 | B34: T | C34: -139.12
A35: 45942 | B35: T | C35: -127.02
... A43: 45960 | B43: T | C43: -101.05
A44: 45961 | B44: F | C44: 460 | D44: -18
A45: 45961 | B45: F | C45: 25.3
A46: 45967 | B46: T | C46: -29.51
A47: 45966 | B47: F | C47: 1725 | D47: 46
A48: 45966 | B48: F | C48: 29.51
A49: 45971 | B49: T | C49: -190.44
A50: 45971 | B50: T | C50: -264.02
A51: 45972 | B51: T | C51: -30.86
A52: 45973 | B52: T | C52: -214.55
A53: 45973 | B53: T | C53: -190.95
A54: 45972 | B54: F | C54: 474.35
A55: 45974 | B55: T | C55: -68.85
A56: 45975 | B56: T | C56: -173.71
A57: 45975 | B57: T | C57: -93.67
A58: 45978 | B58: T | C58: -198.66
A59: 45981 | B59: T | C59: -100
A60: 45981 | B60: F | C60: 230
A61: 45982 | B61: F | C61: 1126.76 | D61: 40
A62: 45985 | B62: T | C62: -168.65
A63: 45985 | B63: T | C63: -100
A64: 45985 | B64: T | C64: -49.36
A65: 45986 | B65: T | C65: -326.39
A66: 45986 | B66: T | C66: -71.98
A67: 45986 | B67: T | C67: -287.93
A68: 45986 | B68: T | C68: -143.97
A69: 45986 | B69: T | C69: -10.61
A70: 46008 | B70: T | C70: -198.86
A71: 46009 | B71: T | C71: -89.43
A72: 46012 | B72: T | C72: -350.38
A73: 46027 | B73: T | C73: -33.18
A74: 46027 | B74: T | C74: -150
A75: 46045 | B75: V | D75: -83
A76: 46055 | B76: T | C76: -100.5

Sheet CAMPO MARKET
A1: CLIENTE | B1: CAMPO MARKET
A2: NOMBRE | B2: ESCARLET LOPEZ
A3: TOTALES | C3: =SUM(C$4:C$1048576) -> 184.73 | D3: =SUM(D$4:D$1048576) -> 0 | E3: =SUM(E$5:E$1048576) -> 0 | F3: =SUM(F$5:F$1048576) -> 0 | G3: =SUM(G$5:G$1048576) -> 0
A4: FECHA | B4: F- E- T- | C4: DEUDA Y ABONOS | D4: VACIO 1/4 | E4: VACIO 350 | F4: VACIO 1.25 | G4: RETECION
A5: 45819 | B5: F | C5: 9.84
A6: 45819 | B6: F | C6: 63.67
A7: 45826 | B7: T | C7: -73.51
A8: 45826 | B8: F | C8: 27.76
A9: 45833 | B9: T | C9: -27.76
A10: 45833 | B10: F | C10: 20.77
A11: 45833 | B11: F | C11: 25.84
A12: 45833 | B12: F | C12: 4.68
A13: 45840 | B13: T | C13: -51.29
A14: 45840 | B14: F | C14: 24.84
A15: 45840 | B15: F | C15: 70.2
A16: 45847 | B16: T | C16: -95.04
... A45: 46051 | B45: F | C45: 184.73

Sheet CARNICERIA 2009
A1: CLIENTE | B1: CARNICERIA 2009
A2: NOMBRE
A3: TOTALES | C3: =SUM(C$4:C$1048576) -> -2.107 | D3: =SUM(D$4:D$1048576) -> 0 | E3: =SUM(E$5:E$1048576) -> 0 | F3: =SUM(F$5:F$1048576) -> 0 | G3: =SUM(G$5:G$1048576) -> 0
A4: FECHA | B4: F- E- T- | C4: DEUDA Y ABONOS | D4: VACIO 1/4 | E4: VACIO 350 | F4: VACIO 1.25 | G4: RETECION
A5: 45820 | B5: F | C5: 220.55
A6: 45820 | B6: F | C6: 53.66
A7: 45825 | B7: T | C7: -274.21
A8: 45834 | B8: F | C8: 15.85
A9: 45834 | B9: F | C9: 129.32
A10: 45834 | B10: F | C10: 5.39
A11: 45841 | B11: T | C11: -77.16
A12: 45842 | B12: T | C12: -27
A13: 45847 | B13: T | C13: -46.4
A14: 45847 | B14: F | C14: 51.96
A15: 45861 | B15: T | C15: -51.48
A16: 45868 | B16: T | C16: -162.05
... A68: 46051 | B68: T | C68: -206.58

Sheet CARNICERIA KARINA
A1: CLIENTE | B1: CARNICERIA KARINA
A2: NOMBRE | B2: KARLA
A3: TOTALES | C3: =SUM(C$4:C$1048576) -> 126.63 | D3: =SUM(D$4:D$1048576) -> 0 | E3: =SUM(E$5:E$1048576) -> 0 | F3: =SUM(F$5:F$1048576) -> 0 | G3: =SUM(G$5:G$1048576) -> 0
A4: FECHA | B4: F- E- T- | C4: DEUDA Y ABONOS | D4: VACIO 1/4 | E4: VACIO 350 | F4: VACIO 1.25 | G4: RETECION
A5: 45815 | B5: F | C5: 31.7
A6: 45815 | B6: F | C6: 48.72
A7: 45821 | B7: F | C7: 40.68
A8: 45825 | B8: T | C8: -80.41
A9: 45828 | B9: F | C9: 20
A10: 45839 | B10: T | C10: -60.36
A11: 45849 | B11: F | C11: 40.28
A12: 45859 | B12: T | C12: -40.61
A13: 45856 | B13: F | C13: 109.32
A14: 45877 | B14: T | C14: -109.31
A15: 45877 | B15: F | C15: 47.4
A16: 45890 | B16: T | C16: -46.97
... A33: 46052 | B33: F | C33: 126.63

Sheet CARNICERIA MARTA
A1: CLIENTE | B1: CARNICERIA MARTA
A2: NOMBRE
A3: TOTALES | C3: =SUM(C$4:C$1048576) -> -0.01 | D3: =SUM(D$4:D$1048576) -> 0 | E3: =SUM(E$5:E$1048576) -> 0 | F3: =SUM(F$5:F$1048576) -> 0 | G3: =SUM(G$5:G$1048576) -> 0
A4: FECHA | B4: F- E- T- | C4: DEUDA Y ABONOS | D4: VACIO 1/4 | E4: VACIO 350 | F4: VACIO 1.25 | G4: RETECION
A5: 45846 | B5: F | C5: 5.67
A6: 45846 | B6: F | C6: 14.23
A7: 45848 | B7: E | C7: -19.91

Sheet CAROL KARDEIGON
A1: CLIENTE | B1: CAROL KARDEIGON
A2: NOMBRE
A3: TOTALES | C3: =SUM(C$4:C$1048576) -> 641.71 | D3: =SUM(D$4:D$1048576) -> 0 | E3: =SUM(E$5:E$1048576) -> 0 | F3: =SUM(F$5:F$1048576) -> 0 | G3: =SUM(G$5:G$1048576) -> 0
A4: FECHA | B4: F- E- T- | C4: DEUDA Y ABONOS | D4: VACIO 1/4 | E4: VACIO 350 | F4: VACIO 1.25 | G4: RETECION
A5: 45815 | B5: T | C5: -30.51
A6: 45814 | B6: F | C6: 30.69
A7: 45821 | B7: F | C7: 15.4
A8: 45821 | B8: F | C8: 81.66
A9: 45827 | B9: T | C9: -97.06
A10: 45828 | B10: F | C10: 7.7
A11: 45828 | B11: F | C11: 120.1
A12: 45831 | B12: T | C12: -127.8
A13: 45835 | B13: F | C13: 23.34
A14: 45835 | B14: F | C14: 123.72
A15: 45835 | B15: F | C15: 31.9
A16: 45839 | B16: T | C16: -100
... A155: 46052 | B155: F | C155: 145

Sheet CASA EXPRESS
A1: CLIENTE | B1: CASA EXPRESS
A2: NOMBRE | B2: DURAN
A3: TOTALES | C3: =SUM(C$4:C$1048576) -> -1.02 | D3: =SUM(D$4:D$1048576) -> 0 | E3: =SUM(E$5:E$1048576) -> 0 | F3: =SUM(F$5:F$1048576) -> 0 | G3: =SUM(G$5:G$1048576) -> 0
A4: FECHA | B4: F- E- T- | C4: DEUDA Y ABONOS | D4: VACIO 1/4 | E4: VACIO 350 | F4: VACIO 1.25 | G4: RETECION
A5: 45818 | B5: F | C5: 101.45
A6: 45818 | B6: F | C6: 18.9
A7: 45819 | B7: F | C7: 94.66
A8: 45834 | B8: T | C8: -215
A9: 45834 | B9: F | C9: 41.15
A10: 45834 | B10: F | C10: 116.26
A11: 45866 | B11: T | C11: -157.91
A12: 45874 | B12: F | C12: 15.85
A13: 45874 | B13: F | C13: 47.96
A14: 45874 | B14: F | C14: 11.42
A15: 45874 | B15: F | C15: 76.46
A16: 45896 | B16: T | C16: -151.69
... A26: 45993 | B26: T | C26: -38.82

Sheet CCP PARAMILLO
A1: CLIENTE | B1: CCP PARAMILLO
A2: NOMBRE | B2: FREDDY JAUREGY
A3: TOTALES | C3: =SUM(C$4:C$1048576) -> 118.62 | D3: =SUM(D$4:D$1048576) -> 0 | E3: =SUM(E$5:E$1048576) -> 0 | F3: =SUM(F$5:F$1048576) -> 0 | G3: =SUM(G$5:G$1048576) -> 9.84
A4: FECHA | B4: F- E- T- | C4: DEUDA Y ABONOS | D4: VACIO 1/4 | E4: VACIO 350 | F4: VACIO 1.25 | G4: RETECION
A5: 45827 | B5: F | C5: =35.85-G5 -> 32.15 | G5: 3.7
A6: 45827 | B6: F | C6: =96.77-G6 -> 94.34 | G6: 2.43
A7: 45839 | B7: T | C7: -126.49 | G7: -6.13
A8: 45842 | B8: F | C8: =57.65-G8 -> 51.69 | G8: 5.96
A9: 45862 | B9: T | C9: -51.69 | G9: -5.96
A10: 45867 | B10: F | C10: 30.05
A11: 45867 | B11: F | C11: 19.95
A12: 45895 | B12: T | C12: -45.5
A13: 45895 | B13: F | C13: =32.95-G13 -> 29.55 | G13: 3.4
A14: 45895 | B14: F | C14: =30.43-G14 -> 29.89 | G14: 0.54
A15: 45902 | B15: R | G15: -3.94
A16: 45912 | B16: T | C16: -59.43
A17: 45916 | B17: F | C17: =31.45-G17 -> 28.2 | G17: 3.25
A18: 45916 | B18: F | C18: =27.48-G18 -> 24.64 | G18: 2.84
A19: 45929 | B19: T | C19: -53.92
A20: 45944 | B20: R | G20: -6.09
A21: 45944 | B21: F | C21: =21.94-G21 -> 19.68 | G21: 2.26
A22: 45944 | B22: F | C22: =91.56-G22 -> 88.65 | G22: 2.91
A23: 45973 | B23: T | C23: -108.32 | G23: -5.17 | I23: =2411.41/267.7499 -> 9.0062032
A24: 45993 | B24: F | C24: =276.08-G24 -> 267.08 | G24: 9
A25: 46007 | B25: R | G25: -9
A26: 46030 | B26: T | C26: -233.62
A27: 46035 | B27: T | C27: -36.9
A28: 46035 | B28: F | C28: =128.46-G28 -> 118.62 | G28: 9.84

Sheet CECILIA EMPANADAS
A1: CLIENTE | B1: CECILIA EMPANADAS
A2: NOMBRE
A3: TOTALES | C3: =SUM(C$4:C$1048576) -> 29 | D3: =SUM(D$4:D$1048576) -> 0 | E3: =SUM(E$5:E$1048576) -> 0 | F3: =SUM(F$5:F$1048576) -> 0 | G3: =SUM(G$5:G$1048576) -> 0
A4: FECHA | B4: F- E- T- | C4: DEUDA Y ABONOS | D4: VACIO 1/4 | E4: VACIO 350 | F4: VACIO 1.25 | G4: RETECION
A5: 46031 | B5: T | C5: -32.76
A6: 46030 | B6: F | C6: 32.76
A7: 46051 | B7: T | C7: -34.92
A8: 46051 | B8: F | C8: 34.92
A9: 46052 | B9: F | C9: 29

Sheet CEMUCA
A1: CLIENTE | B1: CEMUCA
A2: NOMBRE
A3: TOTALES | C3: =SUM(C$4:C$1048576) -> 0.26 | D3: =SUM(D$4:D$1048576) -> 0 | E3: =SUM(E$5:E$1048576) -> 0 | F3: =SUM(F$5:F$1048576) -> 0 | G3: =SUM(G$5:G$1048576) -> 0
A4: FECHA | B4: F- E- T- | C4: DEUDA Y ABONOS | D4: VACIO 1/4 | E4: VACIO 350 | F4: VACIO 1.25 | G4: RETECION
A5: 45937 | B5: F | C5: 25.06
A6: 45937 | B6: F | C6: 9.2
A7: 45942 | B7: T | C7: -34
B8: F

Sheet CHARCUTERIA LA TOICA
A1: CLIENTE | B1: CHARCUTERIA LA TOICA
A2: NOMBRE | B2: YELSI CAMARGO
A3: TOTALES | C3: =SUM(C$4:C$1048576) -> 297.01 | D3: =SUM(D$4:D$1048576) -> 0 | E3: =SUM(E$5:E$1048576) -> 0 | F3: =SUM(F$5:F$1048576) -> 0 | G3: =SUM(G$5:G$1048576) -> 0
A4: FECHA | B4: F- E- T- | C4: DEUDA Y ABONOS | D4: VACIO 1/4 | E4: VACIO 350 | F4: VACIO 1.25 | G4: RETECION
A5: 45819 | B5: F | C5: 25.69
A6: 45819 | B6: F | C6: 42.16
A7: 45825 | B7: T | C7: -67.85
A8: 45827 | B8: F | C8: 9.84
A9: 45827 | B9: F | C9: 69.66
A10: 45833 | B10: T | C10: -79.5
A11: 45834 | B11: F | C11: 9.84
A12: 45834 | B12: F | C12: 134.39
A13: 45841 | B13: T | C13: -144.23
A14: 45842 | B14: F | C14: 19.46
A15: 45842 | B15: F | C15: 109.4
A16: 45848 | B16: T | C16: -128.86
... A132: 46052 | B132: F | C132: 297.01

Sheet CHACARO CREAM
A1: CLIENTE | B1: CHACARO CREAM
A2: NOMBRE
A3: TOTALES | C3: =SUM(C$4:C$1048576) -> 0 | D3: =SUM(D$4:D$1048576) -> 1 | E3: =SUM(E$5:E$1048576) -> 0 | F3: =SUM(F$5:F$1048576) -> 0 | G3: =SUM(G$5:G$1048576) -> 0
A4: FECHA | B4: F- E- T- | C4: DEUDA Y ABONOS | D4: VACIO 1/4 | E4: VACIO 350 | F4: VACIO 1.25 | G4: RETECION
A5: 45989 | B5: F | C5: 26.22 | D5: 1
A6: 46010 | B6: F | C6: 19.68
A7: 46012 | B7: T | C7: -26.22
A8: 46050 | B8: T | C8: -19.68

Sheet COLEGIO SANTISIMA TRINIDAD
A1: CLIENTE | B1: COLEGIO SANTISIMA TRINIDAD
A2: NOMBRE
A3: TOTALES | C3: =SUM(C$4:C$1048576) -> 3.42 | D3: =SUM(D$4:D$1048576) -> 0 | E3: =SUM(E$5:E$1048576) -> 0 | F3: =SUM(F$5:F$1048576) -> 0 | G3: =SUM(G$5:G$1048576) -> 0
A4: FECHA | B4: F- E- T- | C4: DEUDA Y ABONOS | D4: VACIO 1/4 | E4: VACIO 350 | F4: VACIO 1.25 | G4: RETECION
A5: 45835 | B5: F | C5: 31.7 | D5: 1
A6: 45842 | B6: T | C6: -31.7
A7: 45912 | B7: F | C7: 31.7 | D7: 2
A8: 45926 | B8: E | C8: -31.71 | D8: -2
A9: 45926 | B9: F | C9: 63.4
A10: 45933 | B10: E | C10: -63.38
A11: 45933 | B11: E | C11: -4.61 | D11: -1
A12: 45933 | B12: F | C12: 31.7
A13: 45940 | B13: F | C13: 32.76 | D13: 2
A14: 45946 | B14: T | C14: -31.7
A15: 45947 | B15: F | C15: 49.14 | D15: -2
A16: 45954 | B16: T | C16: -32.76
A17: 45954 | B17: F | C17: 32.76
A18: 45961 | B18: T | C18: -49.14
A19: 45968 | B19: T | C19: -32.76
A20: 45968 | B20: F | C20: 49.14
A21: 45968 | B21: F | C21: 3.19
A22: 45975 | B22: F | C22: 32.76
A23: 45989 | B23: F | C23: 65.52
A24: 46003 | B24: T | C24: -32.76
A25: 46037 | B25: T | C25: -44.31
A26: 46052 | B26: T | C26: -65.52

Sheet COLEGIO SANTO CRISTO
A1: CLIENTE | B1: COLEGIO SANTO CRISTO
A2: NOMBRE
A3: TOTALES | C3: =SUM(C$4:C$1048576) -> 0 | D3: =SUM(D$4:D$1048576) -> 0 | E3: =SUM(E$5:E$1048576) -> 0 | F3: =SUM(F$5:F$1048576) -> 0 | G3: =SUM(G$5:G$1048576) -> 0
A4: FECHA | B4: F- E- T- | C4: DEUDA Y ABONOS | D4: VACIO 1/4 | E4: VACIO 350 | F4: VACIO 1.25 | G4: RETECION
A5: 45961 | B5: F | C5: 49.14
A6: 45978 | B6: T | C6: -49.14

Sheet COMERCIALIZADORA ALFONSO PEREZ
A1: CLIENTE | B1: COMERCIALIZADORA ALFONSO PEREZ
A2: NOMBRE | B2: ALONDRA PEREZ
A3: TOTALES | C3: =SUM(C$4:C$1048576) -> 74.75 | D3: =SUM(D$4:D$1048576) -> 0 | E3: =SUM(E$5:E$1048576) -> 0 | F3: =SUM(F$5:F$1048576) -> 0 | G3: =SUM(G$5:G$1048576) -> 0
A4: FECHA | B4: F- E- T- | C4: DEUDA Y ABONOS | D4: VACIO 1/4 | E4: VACIO 350 | F4: VACIO 1.25 | G4: RETECION
A5: 45863 | B5: T | C5: -25.46
A6: 45863 | B6: F | C6: 25.45
A7: 45875 | B7: F | C7: 9
A8: 45875 | B8: F | C8: 67.56
A9: 45881 | B9: T | C9: -24.19
A10: 45884 | B10: T | C10: -22.85
A11: 45884 | B11: F | C11: 39.6
A12: 45887 | B12: T | C12: -50.43
A13: 45890 | B13: T | C13: -18.69
A14: 45890 | B14: F | C14: 10.92
A15: 45890 | B15: F | C15: 56.3
A16: 45910 | B16: T | C16: -31.97
... A34: 46042 | B34: T | C34: -29.03

Sheet COMERCIALIZADORA FLOREZ
A1: CLIENTE | B1: COMERCIALIZADORA FLOREZ
A2: NOMBRE
A3: TOTALES | C3: =SUM(C$4:C$1048576) -> -4.3454 | D3: =SUM(D$4:D$1048576) -> 0 | E3: =SUM(E$5:E$1048576) -> 0 | F3: =SUM(F$5:F$1048576) -> 0 | G3: =SUM(G$5:G$1048576) -> 0
A4: FECHA | B4: F- E- T- | C4: DEUDA Y ABONOS | D4: VACIO 1/4 | E4: VACIO 350 | F4: VACIO 1.25 | G4: RETECION
A5: 45847 | B5: T | C5: -82.91
A6: 45847 | B6: F | C6: 19.68
A7: 45847 | B7: F | C7: 21.72
A8: 45847 | B8: F | C8: 41.51
A9: 45875 | B9: T | C9: -473.95
A10: 45875 | B10: F | C10: 31.7
A11: 45875 | B11: F | C11: 358.5
A12: 45875 | B12: F | C12: 83.7
A13: 45876 | B13: T | C13: -181.9
A14: 45876 | B14: F | C14: 99.41
A15: 45876 | B15: F | C15: 82.41
A16: 45904 | B16: T | C16: -285.76
... A21: 45918 | B21: F | C21: 63.4
A22: 45919 | B22: F | D22: 1
A23: 45919 | B23: F | C23: 518.8
A24: 45919 | B24: F | C24: 631.17
A25: 45922 | B25: T | C25: -1149.97
A26: 45924 | B26: F | C26: 80.12
A27: 45924 | B27: F | C27: 113.34
A28: 45925 | B28: T | C28: -193.46
A29: 45930 | B29: T | C29: -2183.63 | I29: PENDIENTE LA VENTA DE WILLY EL 1.5 %
A30: 45930 | B30: F | C30: =-2205.69*1.5%+2205.69 -> 2172.6047
A31: 45933 | B31: F | C31: 122.8 | J31: =2205.69*1.5% -> 33.08535
A32: 45937 | B32: T | C32: -600.03 | J32: =2205.69-J31 -> 2172.6047
A33: 45937 | B33: T | C33: -747.51
A34: 45937 | B34: F | C34: =123.22*0.985 -> 121.3717
A35: 45937 | B35: F | C35: =-1444.64*1.5%+1444.64 -> 1422.9704 | J35: =1444.64-C35 -> 21.6696
A36: 45938 | B36: T | C36: -301.15
A37: 45944 | B37: F | C37: =48.5*0.985 -> 47.7725
A38: 45944 | B38: F | C38: =-301.38*1.5%+301.38 -> 296.8593 | J38: =301.38-C38 -> 4.5207
A39: 45950 | B39: T | C39: -349.88
A40: 45951 | B40: T | C40: -509.97
A41: 45951 | B41: F | C41: =102.78*0.985 -> 101.2383
A42: 45951 | B42: F | C42: =-400.26*1.5%+400.26 -> 394.2561
A43: 45951 | B43: F | C43: =14.7*0.985 -> 14.4795
A44: 45952 | B44: T | C44: -685.56
A45: 45952 | B45: F | C45: =-696*1.5%+696 -> 685.56
A46: 45958 | B46: T | C46: -1340.69
A47: 45958 | B47: F | C47: =75.48*0.985 -> 74.3478
A48: 45958 | B48: F | C48: =-1242.55*1.5%+1242.55 -> 1223.9117
A49: 45958 | B49: F | C49: =42.6*0.985 -> 41.961
A50: 45965 | B50: T | C50: -461.79
A51: 45965 | B51: F | C51: =-389.32*1.5%+389.32 -> 383.4802 | I51: =389.32-C51 -> 5.8398
A52: 45965 | B52: F | C52: =79.5*0.985 -> 78.3075
A53: 45972 | B53: T | C53: -717.57
A54: 45972 | B54: F | C54: =728.5*0.985 -> 717.5725 | I54: =728.5-C54 -> 10.9275
A55: 45973 | B55: T | C55: -1159.66
A56: 45973 | B56: T | C56: -37.5
A57: 45973 | B57: F | C57: 1214.82
A58: 45979 | B58: F | C58: =1754.46*0.985 -> 1728.1431 | I58: =1754.46-C58 -> 26.3169
A59: 45980 | B59: T | C59: -1728.14
A60: 45986 | B60: F | C60: =743.32*0.985 -> 732.1702 | D60: -1 | I60: =743.32-C60 -> 11.1498
A61: 45993 | B61: T | C61: -732.17
A62: 45993 | B62: T | C62: -705.65
A63: 45993 | B63: F | C63: =716.4*0.985 -> 705.654 | I63: =716.4-C63 -> 10.746
A64: 46000 | B64: T | C64: -1483.06
A65: 46000 | B65: F | C65: =1505.65*0.985 -> 1483.0653 | I65: =1505.65-C65 -> 22.58475
A66: 46007 | B66: T | C66: -181.68
A67: 46007 | B67: F | C67: =181.68*0.985 -> 178.9548 | I67: =+C67-181.68 -> -2.7252
A68: 46014 | B68: F | C68: =1624.86*0.985 -> 1600.4871 | I68: =1624.86-C68 -> 24.3729
A69: 46015 | B69: F | C69: =128*0.985 -> 126.08 | I69: =128-C69 -> 1.92
A70: 46017 | B70: T | C70: -1170
A71: 46017 | B71: T | C71: -555.72
A72: 46021 | B72: T | C72: -451.76
A73: 46021 | B73: F | C73: =458.64*0.985 -> 451.7604 | I73: =458.64-C73 -> 6.8796 | O73: PENDIENTE LA VENTA DE WILLY EL 1.5 %
A74: 46028 | B74: T | C74: -837.89
A75: 46028 | B75: F | C75: =850.65*0.985 -> 837.89025 | I75: =850.65-C75 -> 12.75975
A76: 46035 | B76: T | C76: -371.57
A77: 46035 | B77: F | C77: =377.23*0.985 -> 371.57155 | I77: =+C77-377.23 -> -5.65845
A78: 46043 | B78: T | C78: -980.04
A79: 46043 | B79: F | C79: =994.96*0.985 -> 980.0356 | I79: =994.96-C79 -> 14.9244
A80: 46049 | B80: T | C80: -17.38
A81: 46049 | B81: F | C81: =570.51*0.985 -> 561.95235 | I81: =570.51-C81 -> 8.55765
A82: 46050 | B82: T | C82: -561.95
A83: 46050 | B83: T | C83: -380.54
A84: 46050 | B84: F | C84: =386.34*0.985 -> 380.5449 | I84: =+C84-386.34 -> -5.7951
A85: 46052 | B85: F | C85: =290*0.985 -> 285.65 | I85: =290-C85 -> 4.35
A86: 46055 | B86: T | C86: -290
A87: 46056 | B87: T | C87: -780
A88: 46056 | B88: T | C88: -676.36
A89: 46056 | B89: F | C89: =1478.54*0.985 -> 1456.3619 | I89: =+C89-1478.54 -> -22.1781

Sheet COMERCIALIZADORA JEALKA
A1: CLIENTE | B1: COMERCIALIZADORA JEALKA
A2: NOMBRE | B2: GONZALO
A3: TOTALES | C3: =SUM(C$4:C$1048576) -> 89.56 | D3: =SUM(D$4:D$1048576) -> 0 | E3: =SUM(E$5:E$1048576) -> 0 | F3: =SUM(F$5:F$1048576) -> 0 | G3: =SUM(G$5:G$1048576) -> 0
A4: FECHA | B4: F- E- T- | C4: DEUDA Y ABONOS | D4: VACIO 1/4 | E4: VACIO 350 | F4: VACIO 1.25 | G4: RETECION
A5: 45815 | B5: F | C5: 20.8
A6: 45815 | B6: F | C6: 35.54
A7: 45826 | B7: T | C7: -56.34
A8: 45828 | B8: F | C8: 20
A9: 45831 | B9: T | C9: -20
A10: 45835 | B10: F | C10: 9.6
A11: 45840 | B11: T | C11: -9.53
A12: 45849 | B12: F | C12: 37.1
A13: 45856 | B13: T | C13: -51.44
A14: 45856 | B14: F | C14: 14.34
A15: 45863 | B15: F | C15: 27.64
A16: 45870 | B16: F | C16: 15
... A52: 46052 | B52: F | C52: 89.54

Sheet COMERCIALIZADORA MULTIMASS
A1: CLIENTE | B1: COMERCIALIZADORA MULTIMASS
A2: NOMBRE | B2: KEVIN RAMIREZ
A3: TOTALES | C3: =SUM(C$4:C$1048576) -> 84.5 | D3: =SUM(D$4:D$1048576) -> 0 | E3: =SUM(E$5:E$1048576) -> 0 | F3: =SUM(F$5:F$1048576) -> 0 | G3: =SUM(G$5:G$1048576) -> 0
A4: FECHA | B4: F- E- T- | C4: DEUDA Y ABONOS | D4: VACIO 1/4 | E4: VACIO 350 | F4: VACIO 1.25 | G4: RETECION
A5: 45814 | B5: F | C5: 25.69
A6: 45817 | B6: T | C6: -25.69
A7: 45818 | B7: F | C7: 15.85
A8: 45825 | B8: T | C8: -15.85
A9: 45825 | B9: F | C9: 35.2
A10: 45832 | B10: T | C10: -35.2
A11: 45832 | B11: F | C11: 25.69
A12: 45838 | B12: T | C12: -25.69
A13: 45839 | B13: F | C13: 15.85
A14: 45842 | B14: T | C14: -15.85
A15: 45846 | B15: T | C15: -9.84
A16: 45846 | B16: F | C16: 9.84
... A67: 46056 | B67: F | C67: 57.38

Sheet COMERCIALIZADORA ORZY RUZY
A1: CLIENTE | B1: COMERCIALIZADORA ORZY RUZY
A2: NOMBRE | B2: GLADYS RUIZ
A3: TOTALES | C3: =SUM(C$4:C$1048576) -> 0 | D3: =SUM(D$4:D$1048576) -> 0 | E3: =SUM(E$5:E$1048576) -> 0 | F3: =SUM(F$5:F$1048576) -> 0 | G3: =SUM(G$5:G$1048576) -> 0
A4: FECHA | B4: F- E- T- | C4: DEUDA Y ABONOS | D4: VACIO 1/4 | E4: VACIO 350 | F4: VACIO 1.25 | G4: RETECION
A5: 45850 | B5: T | C5: -20
A6: 45849 | B6: F | C6: 20
A7: 45883 | B7: T | C7: -33.15
A8: 45882 | B8: F | C8: 33.39
A9: 45903 | B9: T | C9: -35.35
A10: 45902 | B10: F | C10: 15.85
A11: 45902 | B11: F | C11: 19.8
A12: 45911 | B12: E | C12: -0.54
A13: 45933 | B13: T | C13: -74.22
A14: 45933 | B14: F | C14: 9.84
A15: 45933 | B15: F | C15: 64.38

Sheet COMERCIALIZADORA YUDI
A1: CLIENTE | B1: COMERCIALIZADORA YUDI
A2: NOMBRE
A3: TOTALES | C3: =SUM(C$4:C$1048576) -> 962.4 | D3: =SUM(D$4:D$1048576) -> 0 | E3: =SUM(E$5:E$1048576) -> 0 | F3: =SUM(F$5:F$1048576) -> 0 | G3: =SUM(G$5:G$1048576) -> 0
A4: FECHA | B4: F- E- T- | C4: DEUDA Y ABONOS | D4: VACIO 1/4 | E4: VACIO 350 | F4: VACIO 1.25 | G4: RETECION
A5: 45814 | B5: F | C5: 62.18
A6: 45814 | B6: F | C6: 326.14
A7: 45814 | B7: F | C7: 28.72
A8: 45819 | B8: T | C8: -417.05
A9: 45819 | B9: F | C9: 55.68
A10: 45819 | B10: F | C10: 368.06
A11: 45819 | B11: F | C11: 10.88
A12: 45819 | B12: F | C12: 34.8
A13: 45820 | B13: F | C13: 136.3
A14: 45820 | B14: F | C14: 56.52
A15: 45825 | B15: T | C15: -219.36
A16: 45825 | B16: T | C16: -401.34
... A119: 45982 | B119: T | C119: -208.63
A120: 45986 | B120: F | C120: =439.52 -> 439.52
A121: 45987 | B121: T | C121: -328.08
A122: 45988 | B122: T | C122: -730.79
A123: 45988 | B123: T | C123: -1231.67
A124: 45992 | B124: T | C124: -293
A125: 45993 | B125: F | C125: 248.04
A126: 45995 | B126: F | C126: 119.25
A127: 46001 | B127: T | C127: -763.06
A128: 46002 | B128: F | C128: 658.03
A129: 46009 | B129: T | C129: -536.55
A130: 46009 | B130: F | C130: 398.53
A131: 46013 | B131: F | C131: 330.33
A132: 46013 | B132: T | C132: -1051.15
... A149: 46056 | B149: F | C149: 352.64

Sheet COMPINCHOS
A1: CLIENTE | B1: COMPINCHOS
A2: NOMBRE
A3: TOTALES | C3: =SUM(C$4:C$1048576) -> -0.02 | D3: =SUM(D$4:D$1048576) -> 0 | E3: =SUM(E$5:E$1048576) -> 0 | F3: =SUM(F$5:F$1048576) -> 0 | G3: =SUM(G$5:G$1048576) -> 0
A4: FECHA | B4: F- E- T- | C4: DEUDA Y ABONOS | D4: VACIO 1/4 | E4: VACIO 350 | F4: VACIO 1.25 | G4: RETECION
A5: 45862 | B5: F | C5: 30
A6: 45876 | B6: E | C6: -30
A7: 45876 | B7: F | C7: 37.5
A8: 45876 | B8: F | C8: 41.6
A9: 45891 | B9: F | C9: 15
A10: 45894 | B10: T | C10: -79.1
A11: 45897 | B11: E | C11: -15
A12: 45897 | B12: F | C12: 22.5
A13: 45905 | B13: T | C13: -22.34
A14: 45918 | B14: F | C14: 30
A15: 45925 | B15: E | C15: -30
A16: 45932 | B16: F | C16: 30
... A25: 45988 | B25: E | C25: -22.5

Sheet COPAS DE PACO
A1: CLIENTE | B1: COPAS DE PACO
A2: NOMBRE
A3: TOTALES | C3: =SUM(C$4:C$1048576) -> 1239.8 | D3: =SUM(D$4:D$1048576) -> 30 | E3: =SUM(E$5:E$1048576) -> 0 | F3: =SUM(F$5:F$1048576) -> 0 | G3: =SUM(G$5:G$1048576) -> 0
A4: FECHA | B4: F- E- T- | C4: DEUDA Y ABONOS | D4: VACIO 1/4 | E4: VACIO 350 | F4: VACIO 1.25 | G4: RETECION
A5: 45821 | B5: F | C5: 166.4
A6: 45821 | B6: F | C6: 42.75
A7: 45828 | B7: F | C7: 166.4
A8: 45832 | B8: T | C8: -375.53
A9: 45839 | B9: F | C9: 395.2
A10: 45839 | B10: F | C10: 15
A11: 45846 | B11: T | C11: -448.95
A12: 45846 | B12: F | C12: 332.8
A13: 45862 | B13: F | C13: 335.2
A14: 45862 | B14: F | C14: 15.85
A15: 45873 | B15: T | C15: -640.72
A16: 45870 | B16: F | C16: 40
... A36: 45998 | B36: T | C36: -279.33
A37: 46002 | B37: F | C37: 1467.39 | D37: 30

Sheet CONSUELO MENDOZA
A1: CLIENTE | B1: CONSUELO MENDOZA
A2: NOMBRE
A3: TOTALES | C3: =SUM(C$4:C$1048576) -> 1.4210855e-14 | D3: =SUM(D$4:D$1048576) -> -2 | E3: =SUM(E$5:E$1048576) -> 0 | F3: =SUM(F$5:F$1048576) -> 0 | G3: =SUM(G$5:G$1048576) -> 0
A4: FECHA | B4: F- E- T- | C4: DEUDA Y ABONOS | D4: VACIO 1/4 | E4: VACIO 350 | F4: VACIO 1.25 | G4: RETECION
A5: 45826 | B5: F | C5: 41.6
A6: 45828 | B6: T | C6: -41.6
A7: 45833 | B7: F | C7: 20.8
A8: 45833 | B8: F | C8: 22.5
A9: 45833 | B9: F | C9: 62.08
A10: 45834 | B10: T | C10: -105.38
A11: 45854 | B11: T | C11: -56.84
A12: 45854 | B12: F | C12: 9.84
A13: 45854 | B13: F | C13: 41.6
A14: 45854 | B14: F | C14: 5.4
A15: 45864 | B15: T | C15: -110.96
A16: 45863 | B16: F | C16: 62.4 | D16: 1
A17: 45863 | B17: F | C17: 7.5
A18: 45863 | B18: F | C18: 31.74
A19: 45868 | B19: T | C19: -20.8
A20: 45868 | B20: F | C20: 20.8 | D20: -1
A21: 45868 | B21: F | C21: 9.32
A22: 45882 | B22: F | C22: 20.8 | D22: 1
A23: 45882 | B23: F | C23: 30.85
A24: 45882 | B24: F | C24: 25.62
A25: 45889 | B25: E | C25: -77.29
A26: 45889 | B26: F | C26: 6.9
A27: 45897 | B27: E | C27: -6.93
A28: 45897 | B28: F | C28: 24.84
A29: 45897 | B29: F | C29: 14.4
A30: 45903 | B30: E | C30: -39.25
A31: 45903 | B31: F | C31: 7.5
A32: 45910 | B32: E | C32: -7.51
A33: 45926 | B33: F | C33: 41.6
A34: 45926 | B34: F | C34: 30.85 | D34: 1
A35: 45931 | B35: E | C35: -72.38
A36: 45945 | B36: F | D36: -2
A37: 45966 | B37: V | D37: -2
A38: 46001 | B38: T | C38: -33.78
A39: 46001 | B39: F | C39: 33.78
A40: 46043 | B40: T | C40: -15.32
A41: 46043 | B41: F | C41: 15.32

Sheet CREACIONES YAKY
A1: CLIENTE | B1: CREACIONES YAKY
A2: NOMBRE | B2: YAKELIN VILLAMIZAR
A3: TOTALES | C3: =SUM(C$4:C$1048576) -> 0 | D3: =SUM(D$4:D$1048576) -> 2 | E3: =SUM(E$5:E$1048576) -> 0 | F3: =SUM(F$5:F$1048576) -> 0 | G3: =SUM(G$5:G$1048576) -> 0
A4: FECHA | B4: F- E- T- | C4: DEUDA Y ABONOS | D4: VACIO 1/4 | E4: VACIO 350 | F4: VACIO 1.25 | G4: RETECION
A5: 45828 | B5: F | C5: 41.6 | D5: 2
A6: 45835 | B6: E | C6: -41.6 | D6: -2
A7: 45848 | B7: F | C7: 41.6 | D7: 2
A8: 45855 | B8: E | C8: -41.62
A9: 45855 | B9: F | C9: 41.6 | D9: 1
A10: 45876 | B10: E | C10: -41.59
A11: 45876 | B11: F | C11: 41.6 | D11: -1
A12: 45890 | B12: T | C12: -20.8
A13: 45890 | B13: F | C13: 41.6
A14: 45904 | B14: E | C14: -62.41
A15: 45904 | B15: F | C15: 41.6
A16: 45920 | B16: E | C16: -41.58

Sheet DANIEL VERSIONES DURAN
A1: CLIENTE | B1: DANIEL VERSIONES DURAN
A2: NOMBRE
A3: TOTALES | C3: =SUM(C$4:C$1048576) -> 0 | D3: =SUM(D$4:D$1048576) -> 0 | E3: =SUM(E$5:E$1048576) -> 0 | F3: =SUM(F$5:F$1048576) -> 0 | G3: =SUM(G$5:G$1048576) -> 0
A4: FECHA | B4: F- E- T- | C4: DEUDA Y ABONOS | D4: VACIO 1/4 | E4: VACIO 350 | F4: VACIO 1.25 | G4: RETECION
A5: 45904 | B5: T | C5: -14.5
A6: 45904 | B6: F | C6: 14.5

Sheet DARIANA ESCALANTE
A1: CLIENTE | B1: DARIANA ESCALANTE
A2: NOMBRE
A3: TOTALES | C3: =SUM(C$4:C$1048576) -> 86.22 | D3: =SUM(D$4:D$1048576) -> 0 | E3: =SUM(E$5:E$1048576) -> -2 | F3: =SUM(F$5:F$1048576) -> -3 | G3: =SUM(G$5:G$1048576) -> 0
A4: FECHA | B4: F- E- T- | C4: DEUDA Y ABONOS | D4: VACIO 1/4 | E4: VACIO 350 | F4: VACIO 1.25 | G4: RETECION
A5: 45856 | B5: F | C5: 15.85
A6: 45856 | B6: F | C6: 25
A7: 45861 | B7: T | C7: -40.85
A8: 45870 | B8: F | C8: 33.96
A9: 45877 | B9: F | C9: 38.98
A10: 45882 | B10: T | C10: -37.13
A11: 45883 | B11: T | C11: -38.7
A12: 45883 | B12: F | C12: 26.1
A13: 45883 | B13: F | C13: 32.88
A14: 45888 | B14: T | C14: -28.96
A15: 45891 | B15: T | C15: -26.89
A16: 45891 | B16: F | C16: 24
... A37: 45936 | B37: F | C37: 86.11
A38: 45940 | B38: F | C38: 15 | E38: -1 | F38: -2
A39: 45940 | B39: F | C39: 8.73
A40: 45940 | B40: T | C40: -66.58
A41: 45945 | B41: F | C41: 40.38 | D41: 1
A42: 45945 | B42: F | C42: 90.83
A43: 45947 | B43: T | C43: -117.8
A44: 45951 | B44: T | C44: -96.2
A45: 45951 | B45: F | C45: 15
A46: 45951 | B46: F | C46: 125.01
A47: 45954 | B47: F | D47: -1 | E47: -1 | F47: -1
A48: 45954 | B48: F | C48: 110.63
A49: 45967 | B49: T | C49: -72.51
A50: 45968 | B50: F | C50: 24
A51: 45968 | B51: F | C51: 108.52
A52: 45980 | B52: T | C52: -124.83
A53: 45981 | B53: T | C53: -37.26
A54: 45982 | B54: T | C54: 130.92
A55: 45989 | B55: T | C55: -81.41
A56: 46001 | B56: T | C56: -114.46
A57: 46001 | B57: T | C57: -38.77
A58: 46007 | B58: T | C58: -91.38
A59: 46008 | B59: F | C59: 173.15
... A67: 46052 | B67: F | C67: 86.22

Sheet DAVID DIAZ
A1: CLIENTE | B1: DAVID DIAZ
A2: NOMBRE
A3: TOTALES | C3: =SUM(C$4:C$1048576) -> 153.91 | D3: =SUM(D$4:D$1048576) -> 2 | E3: =SUM(E$5:E$1048576) -> 1 | F3: =SUM(F$5:F$1048576) -> 0 | G3: =SUM(G$5:G$1048576) -> 0
A4: FECHA | B4: F- E- T- | C4: DEUDA Y ABONOS | D4: VACIO 1/4 | E4: VACIO 350 | F4: VACIO 1.25 | G4: RETECION
A5: 45959 | B5: F | C5: 73.78 | D5: 1 | E5: 1
A6: 45959 | B6: F | C6: 181.62
A7: 45959 | B7: F | C7: 94.98
A8: 45961 | B8: T | C8: -335.35
A9: 45961 | B9: T | C9: -15.03
A10: 45966 | B10: F | C10: 19.68
A11: 45966 | B11: F | C11: 550.28
A12: 45968 | B12: T | C12: -43.77
A13: 45971 | B13: T | C13: -38.95
A14: 45971 | B14: T | C14: -38.95
A15: 45972 | B15: T | C15: -51.93
A16: 45973 | B16: T | C16: -21.46
A17: 45980 | B17: F | C17: 167.28
... A28: 45993 | B28: T | C28: -16.01
A29: 45994 | B29: F | C29: 593.02 | D29: 1
A30: 45999 | B30: T | C30: -155.08
A31: 46000 | B31: T | C31: -38.77
A32: 46001 | B32: T | C32: -57.23
A33: 46002 | B33: T | C33: -41.5
A34: 46003 | B34: T | C34: -74.7
A35: 46004 | B35: T | C35: -44.31
A36: 46006 | B36: T | C36: -88.63
A37: 46007 | B37: T | C37: -51.17
A38: 46008 | B38: T | C38: -41.65
A39: 46008 | B39: F | C39: 632.92
A40: 46009 | B40: T | C40: -143.08
A41: 46012 | B41: T | C41: -210.23
... A75: 46052 | B75: F | C75: 58

Sheet DAVID MORALES
A1: CLIENTE | B1: DAVID MORALES
A2: NOMBRE
A3: TOTALES | C3: =SUM(C$4:C$1048576) -> 358.03 | D3: =SUM(D$4:D$1048576) -> 7 | E3: =SUM(E$5:E$1048576) -> 0 | F3: =SUM(F$5:F$1048576) -> 0 | G3: =SUM(G$5:G$1048576) -> 0
A4: FECHA | B4: F- E- T- | C4: DEUDA Y ABONOS | D4: VACIO 1/4 | E4: VACIO 350 | F4: VACIO 1.25 | G4: RETECION
A5: 45742 | B5: F | C5: 83.94
A6: 45742 | B6: F | C6: 24.01
A7: 45751 | C7: 33.69
A8: 45751 | B8: F | C8: 28.8
A9: 45755 | B9: T | C9: -107.95
A10: 45757 | B10: F | C10: 12.28
A11: 45771 | B11: T | C11: -46
A12: 45772 | B12: F | C12: 132.17
A13: 45775 | B13: T | C13: -28.8
A14: 45783 | B14: F | C14: 55.05
A15: 45783 | B15: F | C15: 43.9
A16: 45786 | B16: T | C16: -50
A17: 45790 | B17: T | C17: -50
A18: 45792 | B18: T | C18: -32.14
A19: 45797 | B19: T | C19: -50
... A24: 45821 | B24: T | C24: -40
A25: 45825 | B25: V | D25: 1
A26: 45826 | B26: F | C26: 5.15
A27: 45831 | B27: T | C27: -62
A28: 45832 | B28: F | C28: 57.52
A29: 45832 | B29: F | C29: 5.66
A30: 45833 | B30: F | C30: 69
A31: 45833 | B31: F | C31: 16.41
A32: 45847 | B32: T | C32: -80.31
A33: 45852 | B33: T | C33: -80.31
A34: 45853 | B34: F | C34: 84.46
A35: 45853 | B35: F | C35: 38.78
A36: 45861 | B36: F | C36: 69
A37: 45862 | B37: T | C37: -80
... A50: 45893 | B50: T | C50: -50
A51: 45891 | B51: F | C51: 41.6 | D51: 2
A52: 45896 | B52: F | C52: 67.04
A53: 45896 | B53: F | C53: 14
A54: 45896 | B54: F | C54: 69
A55: 45896 | B55: F | C55: 12.06
A56: 45903 | B56: T | C56: -50
A57: 45904 | B57: T | C57: -50
A58: 45906 | B58: T | C58: -49.61
A59: 45909 | B59: T | C59: -92.01
A60: 45910 | B60: F | C60: 63.52
A61: 45912 | B61: F | C61: 69
A62: 45916 | B62: T | C62: -50
A63: 45917 | B63: F | C63: 16.7
... A103: 46017 | B103: F | C103: 322.75
A104: 46017 | B104: V | D104: 2
A105: 46020 | B105: T | C105: -61.4
A106: 46021 | B106: V | D106: 2
A107: 46024 | B107: T | C107: -322
A108: 46028 | B108: F | C108: 60.24
A109: 46028 | B109: F | C109: 322
A110: 46035 | B110: T | C110: -82.94
A111: 46036 | B111: F | C111: 90
A112: 46036 | B112: % | C112: -7.2
A113: 46038 | B113: F | C113: 55.8
A114: 46042 | B114: F | C114: 16.96
A115: 46050 | B115: T | C115: -82.99
A116: 46050 | B116: F | C116: 93.48
A117: 46050 | B117: % | C117: -7.2
A118: 46056 | B118: F | C118: 142.18
A119: 46056 | B119: F | C119: 78.24

Sheet MINIABASTO SANTO CRISTO
A1: CLIENTE | B1: MINIABASTO SANTO CRISTO
A2: NOMBRE | B2: LUIS DELGADO
A3: TOTALES | C3: =SUM(C$4:C$1048576) -> 263.034 | D3: =SUM(D$4:D$1048576) -> 0 | E3: =SUM(E$5:E$1048576) -> 0 | F3: =SUM(F$5:F$1048576) -> 0 | G3: =SUM(G$5:G$1048576) -> 0
A4: FECHA | B4: F- E- T- | C4: DEUDA Y ABONOS | D4: VACIO 1/4 | E4: VACIO 350 | F4: VACIO 1.25 | G4: RETECION
A5: 45828 | B5: F | C5: 9.84
A6: 45828 | B6: F | C6: 89.76
A7: 45828 | B7: F | C7: 34.86
A8: 45833 | B8: T | C8: -134.46
A9: 45838 | B9: T | C9: -210.12
A10: 45835 | B10: F | C10: 9.884
A11: 45835 | B11: F | C11: 200.28
A12: 45845 | B12: T | C12: -90.41
A13: 45842 | B13: F | C13: 15.85
A14: 45842 | B14: F | C14: 74.56
A15: 45849 | B15: T | C15: -24.62
A16: 45849 | B16: F | C16: 7.5
... A18: 45856 | B18: F | C18: 7.5
A19: 45856 | B19: F | C19: =57.18+0.36 -> 57.54
A20: 45861 | B20: T | C20: -65.04
A21: 45863 | B21: F | C21: 7.5
A22: 45863 | B22: F | C22: 294.4
A23: 45863 | B23: F | C23: 7.42
A24: 45863 | B24: F | C24: 34.86
A25: 45866 | B25: T | C25: -285.86
A26: 45866 | B26: T | C26: -57
A27: 45870 | B27: F | C27: 115.84
A28: 45870 | B28: F | C28: 17.43
A29: 45874 | B29: T | C29: -133.27
A30: 45877 | B30: F | C30: 56.54
A31: 45877 | B31: F | C31: 147.5
... A87: 46056 | B87: T | C87: -104.28

Sheet DE PANA
A1: CLIENTE | B1: DE PANA
A2: NOMBRE | B2: KEVIN HERNANDEZ
A3: TOTALES | C3: =SUM(C$4:C$1048576) -> -1.4210855e-14 | D3: =SUM(D$4:D$1048576) -> 0 | E3: =SUM(E$5:E$1048576) -> 0 | F3: =SUM(F$5:F$1048576) -> 0 | G3: =SUM(G$5:G$1048576) -> 0
A4: FECHA | B4: F- E- T- | C4: DEUDA Y ABONOS | D4: VACIO 1/4 | E4: VACIO 350 | F4: VACIO 1.25 | G4: RETECION
A5: 45835 | B5: F | C5: 33.19
A6: 45839 | B6: T | C6: -33.19
A7: 45841 | B7: F | C7: 23.3
A8: 45848 | B8: E | C8: -23.31
A9: 45848 | B9: F | C9: 12.1
A10: 45855 | B10: E | C10: -12.5
A11: 45855 | B11: F | C11: 14.56
A12: 45862 | B12: F | C12: 28.39
A13: 45869 | B13: E | C13: -42.54
A14: 45869 | B14: F | C14: 14.44
A15: 45869 | B15: F | C15: 44.46
A16: 45876 | B16: F | C16: 15
... A26: 45996 | B26: E | C26: -4.75

Sheet DELMIRA RAMIREZ
A1: CLIENTE | B1: DELMIRA RAMIREZ
A2: NOMBRE
A3: TOTALES | C3: =SUM(C$4:C$1048576) -> 30.62 | D3: =SUM(D$4:D$1048576) -> 0 | E3: =SUM(E$5:E$1048576) -> 0 | F3: =SUM(F$5:F$1048576) -> 0 | G3: =SUM(G$5:G$1048576) -> 0
A4: FECHA | B4: F- E- T- | C4: DEUDA Y ABONOS | D4: VACIO 1/4 | E4: VACIO 350 | F4: VACIO 1.25 | G4: RETECION
A5: 45899 | B5: F | C5: 28.11
A6: 45905 | B6: T | C6: -28.11
A7: 45905 | B7: F | C7: 15.85
A8: 45905 | B8: F | C8: 14.7
A9: 45911 | B9: T | C9: -30.55
A10: 45911 | B10: F | C10: 9.84
A11: 45911 | B11: F | C11: 8.79
A12: 45920 | B12: E | C12: -1.93
A13: 45920 | B13: F | C13: 7.5
A14: 45920 | B14: F | C14: 21.09
A15: 45922 | B15: T | C15: -16.81
A16: 45926 | B16: T | C16: -28.17
... A47: 46037 | B47: F | C47: 30.75

Sheet DISTRIBUIDO DE DOS
A1: CLIENTE | B1: DISTRIBUIDO DE DOS
A2: NOMBRE
A3: TOTALES | C3: =SUM(C$4:C$1048576) -> 0 | D3: =SUM(D$4:D$1048576) -> 0 | E3: =SUM(E$5:E$1048576) -> 0 | F3: =SUM(F$5:F$1048576) -> 0 | G3: =SUM(G$5:G$1048576) -> 0
A4: FECHA | B4: F- E- T- | C4: DEUDA Y ABONOS | D4: VACIO 1/4 | E4: VACIO 350 | F4: VACIO 1.25 | G4: RETECION
A5: 45925 | B5: F | C5: 63.4
A6: 45925 | B6: F | C6: 138.48
A7: 45926 | B7: T | C7: -201.88
A8: 45930 | B8: T | C8: -321
A9: 45930 | B9: F | C9: 321
A10: 45937 | B10: F | C10: 81.9
A11: 45937 | B11: F | C11: 98.24
A12: 45938 | B12: F | C12: 120
A13: 45940 | B13: T | C13: -300.14
A14: 45951 | B14: F | C14: 137.64
A15: 45953 | B15: T | C15: -137.64
A16: 45966 | B16: F | C16: 104.88
... A30: 46056 | B30: F | C30: 123.36

Sheet DISTRIBUIDORA LUCHENI
A1: CLIENTE | B1: DISTRIBUIDORA LUCHENI
A2: NOMBRE | B2: YORMAN COLMENARES
A3: TOTALES | C3: =SUM(C$4:C$1048576) -> 0 | D3: =SUM(D$4:D$1048576) -> 0 | E3: =SUM(E$5:E$1048576) -> 2 | F3: =SUM(F$5:F$1048576) -> 0 | G3: =SUM(G$5:G$1048576) -> 0
A4: FECHA | B4: F- E- T- | C4: DEUDA Y ABONOS | D4: VACIO 1/4 | E4: VACIO 350 | F4: VACIO 1.25 | G4: RETECION
A5: 45853 | B5: F | C5: 15.85
A6: 45856 | B6: E | C6: -15.85
A7: 45856 | B7: F | C7: 168.96
A8: 45861 | B8: T | C8: -168.96
A9: 45863 | B9: F | C9: 58.5
A10: 45870 | B10: T | C10: -58.5
A11: 45870 | B11: F | C11: 54.34 | E11: 2
A12: 45870 | B12: F | C12: 37.38
A13: 45877 | B13: T | C13: -91.72
A14: 45877 | B14: F | C14: 98.16
A15: 45877 | B15: F | C15: 28.02
A16: 45886 | B16: T | C16: -43.83
A17: 45887 | B17: T | C17: -82.35
A18: 45891 | B18: F | C18: 30.85
A19: 45891 | B19: F | C19: 129.71
A20: 45891 | B20: F | C20: 26.29
A21: 45900 | B21: T | C21: -107.78
A22: 45903 | B22: T | C22: -79.07
A23: 45905 | B23: F | C23: 82.35
... A49: 46017 | B49: T | C49: -41.78

Sheet DISTRIPOLLO LOS ANDES
A1: CLIENTE | B1: DISTRIPOLLO LOS ANDES
A2: NOMBRE | B2: JUAN CARLOS CHACON
A3: TOTALES | C3: =SUM(C$4:C$1048576) -> 211.32 | D3: =SUM(D$4:D$1048576) -> 0 | E3: =SUM(E$5:E$1048576) -> 0 | F3: =SUM(F$5:F$1048576) -> 0 | G3: =SUM(G$5:G$1048576) -> 0
A4: FECHA | B4: F- E- T- | C4: DEUDA Y ABONOS | D4: VACIO 1/4 | E4: VACIO 350 | F4: VACIO 1.25 | G4: RETECION
A5: 45897 | B5: F | C5: 41.54
A6: 45897 | B6: F | C6: 201.06
A7: 45904 | B7: T | C7: -98.64
A8: 45911 | B8: T | C8: -86.86
A9: 45912 | B9: T | C9: -57.14
A10: 45916 | B10: F | C10: 56.55
A11: 45916 | B11: F | C11: 102.75
A12: 45938 | B12: T | C12: -157.69
A13: 45938 | B13: F | C13: 13.5
A14: 45938 | B14: F | C14: 97.22
A15: 45947 | B15: T | C15: -110.72
A16: 45951 | B16: F | C16: 50.96
... A37: 46049 | B37: F | C37: 209.76

Sheet DON HECTOR
A1: CLIENTE | B1: DON HECTOR
A2: NOMBRE
A3: TOTALES | C3: =SUM(C$4:C$1048576) -> 0 | D3: =SUM(D$4:D$1048576) -> 0 | E3: =SUM(E$5:E$1048576) -> 0 | F3: =SUM(F$5:F$1048576) -> 0 | G3: =SUM(G$5:G$1048576) -> 0
A4: FECHA | B4: F- E- T- | C4: DEUDA Y ABONOS | D4: VACIO 1/4 | E4: VACIO 350 | F4: VACIO 1.25 | G4: RETECION
A5: 45828 | B5: F | C5: 35.85
A6: 45831 | B6: T | C6: -35.85

Sheet DON LEO
A1: CLIENTE | B1: DON LEO
A2: NOMBRE
A3: TOTALES | C3: =SUM(C$4:C$1048576) -> 7.89 | D3: =SUM(D$4:D$1048576) -> 1 | E3: =SUM(E$5:E$1048576) -> 0 | F3: =SUM(F$5:F$1048576) -> 0 | G3: =SUM(G$5:G$1048576) -> 0
A4: FECHA | B4: F- E- T- | C4: DEUDA Y ABONOS | D4: VACIO 1/4 | E4: VACIO 350 | F4: VACIO 1.25 | G4: RETECION
A5: 45815 | B5: F | C5: 15.4
A6: 45815 | B6: F | C6: 25.37
A7: 45815 | B7: F | C7: 8.16
A8: 45825 | B8: T | C8: -48.93
A9: 45828 | B9: F | C9: 47.57
A10: 45828 | B10: F | C10: 5.44
A11: 45828 | B11: F | C11: 20.8
A12: 45831 | B12: T | C12: -33.81
A13: 45832 | B13: T | C13: -35
A14: 45835 | B14: T | C14: -10.67 | I14: 5.67
A15: 45835 | B15: F | C15: 20.8
A16: 45835 | B16: F | C16: 9.84
A17: 45835 | B17: F | C17: 33.24
A18: 45835 | B18: F | C18: 10.79
A19: 45839 | B19: T | C19: -17
A20: 45841 | B20: T | C20: -10
A21: 45842 | B21: F | C21: 18.48
A22: 45842 | B22: F | C22: 8.16
A23: 45842 | B23: F | C23: 41.6
A24: 45846 | B24: T | C24: -42
A25: 45849 | B25: T | C25: -68.21
A26: 45849 | B26: F | C26: 13.35
A27: 45849 | B27: F | C27: 41.6
A28: 45856 | B28: T | C28: -54.95 | I28: 0
A29: 45856 | B29: F | C29: 15.85
A30: 45856 | B30: F | C30: 8.16
A31: 45856 | B31: F | C31: 20.8
A32: 45856 | B32: F | C32: 44.94
A33: 45863 | B33: T | C33: -58
A34: 45863 | B34: F | C34: 7.5
A35: 45863 | B35: F | C35: 58.86
A36: 45866 | B36: T | C36: -31.75
A37: 45873 | B37: T | C37: -107.6
A38: 45870 | B38: F | C38: 9.84
A39: 45870 | B39: F | C39: 32.33
A40: 45870 | B40: F | C40: 41.6
... A42: 45876 | B42: T | C42: -15
A43: 45877 | B43: F | C43: 7.5 | I43: -0.94
A44: 45877 | B44: F | C44: 57.02
A45: 45877 | B45: F | C45: 5.91
A46: 45877 | B46: F | C46: 20.8
A47: 45880 | B47: T | C47: -56.54
A48: 45884 | B48: F | C48: 37.67
A49: 45884 | B49: F | C49: 8.16
A50: 45884 | B50: F | C50: 20.8
A51: 45887 | B51: T | C51: -81.32
A52: 45887 | B52: T | C52: -10 | I52: 1.56
A53: 45891 | B53: F | C53: 72.32
A54: 45898 | B54: E | C54: -30
A55: 45898 | B55: F | C55: 41.66
A56: 45902 | B56: T | C56: -15.88
A57: 45905 | B57: F | C57: 17.34
A58: 45905 | B58: F | C58: 41.33
A59: 45905 | B59: F | C59: 23.94
A60: 45912 | B60: E | C60: -36
A61: 45912 | B61: F | C61: 40.53
A62: 45912 | B62: F | C62: 20.8
A63: 45916 | B63: T | C63: -49.86
A64: 45917 | B64: T | C64: -20
... A71: 45925 | B71: T | C71: -15
A72: 45926 | B72: T | C72: -50 | I72: 0
A73: 45926 | B73: F | C73: 44.26
A74: 45926 | B74: F | C74: 18.18
A75: 45926 | B75: F | C75: 41.6
A76: 45933 | B76: T | C76: -12.82
A77: 45933 | B77: E | C77: -41.54 | I77: =SUM(C73:C77) -> 49.68
A78: 45933 | B78: F | C78: 34.21
A79: 45933 | B79: F | C79: 6.92
A80: 45933 | B80: F | C80: 41.6
A81: 45939 | B81: T | C81: -32
A82: 45940 | B82: E | C82: -22 | I82: =SUM(C78:C82) -> 28.73
A83: 45940 | B83: F | C83: 21.84
A84: 45940 | B84: F | C84: 44.9
A85: 45940 | B85: F | C85: 10.38
A86: 45940 | B86: F | C86: 46
A87: 45947 | B87: T | C87: -13.62
A88: 45947 | B88: E | C88: -101.15 | I88: =SUM(C83:C88) -> 8.35
A89: 45947 | B89: F | C89: 16.38
A90: 45947 | B90: F | C90: 60.81
A91: 45947 | B91: F | C91: 14.76
A92: 45947 | B92: F | C92: 46
A93: 45951 | B93: T | C93: -65.95
A94: 45952 | B94: T | C94: -72 | I94: =SUM(C89:C94) -> 0
A95: 45954 | B95: F | C95: 7.5
A96: 45954 | B96: F | C96: 26.91
A97: 45954 | B97: F | C97: 2.92
A98: 45954 | B98: F | C98: 46
A99: 45958 | B99: T | C99: -44.33 | I99: =SUM(C95:C99) -> 39
A100: 45959 | B100: F | C100: 69
A101: 45961 | B101: T | C101: -11
A102: 45961 | B102: E | C102: -28 | I102: =SUM(C100:C102) -> 30
A103: 45961 | B103: F | C103: 9.84
A104: 45961 | B104: F | C104: 39.87
A105: 45961 | B105: F | C105: 6.92
A106: 45966 | B106: T | C106: -17.63
A107: 45968 | B107: T | C107: -7
...

Sheet DONDE QUIERA FOOD HOUSE
A1: CLIENTE | B1: DONDE QUIERA FOOD HOUSE
A2: NOMBRE | B2: RAFAEL RUIZ
A3: TOTALES | C3: =SUM(C$4:C$1048576) -> 11.64 | D3: =SUM(D$4:D$1048576) -> 0 | E3: =SUM(E$5:E$1048576) -> 0 | F3: =SUM(F$5:F$1048576) -> 0 | G3: =SUM(G$5:G$1048576) -> 0
A4: FECHA | B4: F- E- T- | C4: DEUDA Y ABONOS | D4: VACIO 1/4 | E4: VACIO 350 | F4: VACIO 1.25 | G4: RETECION
A5: 45827 | B5: F | C5: 56.42
A6: 45841 | B6: F | C6: 9.84
A7: 45841 | B7: F | C7: 84.75
A8: 45842 | B8: T | C8: -40.7
A9: 45842 | B9: T | C9: -15.71
A10: 45863 | B10: T | C10: -94.59
A11: 45862 | B11: F | C11: 47.68
A12: 45877 | B12: T | C12: -47.69
A13: 45877 | B13: F | C13: 9.89
A14: 45877 | B14: F | C14: 13.97
A15: 45881 | B15: F | C15: 25.38
A16: 45887 | B16: T | C16: -49.19
... A35: 46052 | B35: F | C35: 11.64

Sheet DONDE MIGUEL
A1: CLIENTE | B1: DONDE MIGUEL
A2: NOMBRE
A3: TOTALES | C3: =SUM(C$4:C$1048576) -> 858.41 | D3: =SUM(D$4:D$1048576) -> 1 | E3: =SUM(E$5:E$1048576) -> 0 | F3: =SUM(F$5:F$1048576) -> 0 | G3: =SUM(G$5:G$1048576) -> 0
A4: FECHA | B4: F- E- T- | C4: DEUDA Y ABONOS | D4: VACIO 1/4 | E4: VACIO 350 | F4: VACIO 1.25 | G4: RETECION
A5: 46017 | B5: F | C5: 262.22
A6: 46024 | B6: T | C6: -262.22
A7: 46031 | B7: F | C7: 336.75
A8: 46038 | B8: T | C8: -234.09
A9: 46038 | B9: F | C9: 512.27
A10: 46049 | B10: T | C10: -83.58
A11: 46050 | B11: T | C11: -55.33
A12: 46051 | B12: T | C12: -98.99
A13: 46052 | B13: T | C13: -100.73
A14: 46052 | B14: T | C14: -108.9
A15: 46052 | B15: F | C15: 691.01 | D15: 1

Sheet DONDE YENNY
A1: CLIENTE | B1: DONDE YENNY
A2: NOMBRE | B2: YENNY CASANDUA
A3: TOTALES | C3: =SUM(C$4:C$1048576) -> 177.82 | D3: =SUM(D$4:D$1048576) -> 0 | E3: =SUM(E$5:E$1048576) -> 0 | F3: =SUM(F$5:F$1048576) -> 0 | G3: =SUM(G$5:G$1048576) -> 0
A4: FECHA | B4: F- E- T- | C4: DEUDA Y ABONOS | D4: VACIO 1/4 | E4: VACIO 350 | F4: VACIO 1.25 | G4: RETECION
A5: 45834 | B5: F | C5: 21.94
A6: 45834 | B6: F | C6: 122.38
A7: 45855 | B7: T | C7: -144.32
A8: 45855 | B8: F | C8: 52.15
A9: 45855 | B9: F | C9: 167.95
A10: 45855 | B10: F | C10: 35.27
A11: 45875 | B11: T | C11: -100
A12: 45889 | B12: T | C12: -99.09
A13: 45896 | B13: T | C13: -63
A14: 45898 | B14: F | C14: 20.8
A15: 45898 | B15: F | C15: 133.64
A16: 45898 | B16: F | C16: 346.31
... A43: 46051 | B43: F | C43: 46

Sheet DORIS CAICEDO
A1: CLIENTE | B1: DORIS CAICEDO
A2: NOMBRE
A3: TOTALES | C3: =SUM(C$4:C$1048576) -> -75.66 | D3: =SUM(D$4:D$1048576) -> 0 | E3: =SUM(E$5:E$1048576) -> 0 | F3: =SUM(F$5:F$1048576) -> 0 | G3: =SUM(G$5:G$1048576) -> 0
F4: VACIO 1.25 | G4: RETECION
A5: 45870 | B5: F | C5: 15.85
A6: 45870 | B6: F | C6: 86.96
A7: 45884 | B7: E | C7: -102.81
A8: 45884 | B8: F | C8: 23.7
A9: 45884 | B9: F | C9: 51.3
A10: 45891 | B10: E | C10: -75
A11: 45905 | B11: F | C11: 15.85
A12: 45905 | B12: F | C12: 55.05
A13: 45912 | B13: E | C13: -70.96
A14: 45919 | B14: F | C14: 67.92
A15: 45926 | B15: E | C15: -68
A16: 45933 | B16: F | C16: 26.7
... A31: 46055 | B31: T | C31: -72.57

Sheet DORIS MOGOLLON
A1: CLIENTE | B1: DORIS MOGOLLON
A2: NOMBRE
A3: TOTALES | C3: =SUM(C$4:C$1048576) -> 239.26 | D3: =SUM(D$4:D$1048576) -> 0 | E3: =SUM(E$5:E$1048576) -> 0 | F3: =SUM(F$5:F$1048576) -> 0 | G3: =SUM(G$5:G$1048576) -> 0
A4: FECHA | B4: F- E- T- | C4: DEUDA Y ABONOS | D4: VACIO 1/4 | E4: VACIO 350 | F4: VACIO 1.25 | G4: RETECION
A5: 45812 | B5: F | C5: 208
A6: 45812 | B6: F | C6: 15.85
A7: 45820 | B7: E | C7: -93.75
A8: 45827 | B8: E | C8: -130.1
A9: 45834 | B9: F | C9: 40.05
A10: 45834 | B10: F | C10: 69.84
A11: 45841 | B11: E | C11: -15.85
A12: 45841 | B12: E | C12: -94.06
A13: 45841 | B13: F | C13: 55.9
A14: 45841 | B14: F | C14: 20
A15: 45848 | B15: E | C15: -62.5
A16: 45870 | B16: F | C16: 7.5
... A32: 45944 | B32: F | C32: 32.76
A33: 45947 | B33: F | C33: 69 | D33: 3
A34: 45961 | B34: E | C34: -129.62
A35: 45961 | B35: F | C35: 32.76 | D35: -3
A36: 45961 | B36: F | C36: 40.02
A37: 45972 | B37: E | C37: -53.57
A38: 45979 | B38: E | C38: -43.21
A39: 45979 | B39: F | C39: 32.76
A40: 46008 | B40: F | C40: 58.16
A41: 46014 | B41: T | C41: -58.16
A42: 46014 | B42: F | C42: 56.96
A43: 46020 | B43: E | C43: -84
A44: 46021 | B44: F | C44: 66.5
A45: 46031 | B45: F | C45: 60.72
A46: 46036 | B46: F | C46: 90
A47: 46036 | B47: % | C47: -7.2
... A49: 46052 | B49: F | C49: 72.56

Sheet EDICSON HERRERA
A1: CLIENTE | B1: EDICSON HERRERA
A2: NOMBRE
A3: TOTALES | C3: =SUM(C$4:C$1048576) -> -0.02 | D3: =SUM(D$4:D$1048576) -> 0 | E3: =SUM(E$5:E$1048576) -> 0 | F3: =SUM(F$5:F$1048576) -> 0 | G3: =SUM(G$5:G$1048576) -> 0
A4: FECHA | B4: F- E- T- | C4: DEUDA Y ABONOS | D4: VACIO 1/4 | E4: VACIO 350 | F4: VACIO 1.25 | G4: RETECION
A5: 45896 | B5: F | C5: 20.8
A6: 45896 | B6: F | C6: 59.24
A7: 45896 | B7: F | C7: 12.8
A8: 45903 | B8: E | C8: -96.77
A9: 45903 | B9: F | C9: 41.6
A10: 45903 | B10: F | C10: 21.94
A11: 45903 | B11: F | C11: 63.4
A12: 45903 | B12: F | C12: 29.1
A13: 45910 | B13: E | C13: -152.12
A14: 45910 | B14: F | C14: 60.64
A15: 45910 | B15: F | C15: 43.33
A16: 45910 | B16: F | C16: 69.37
... A27: 45938 | B27: E | C27: -73.65

Sheet EDUAR GARCIA
A1: CLIENTE | B1: EDUAR GARCIA
A2: NOMBRE | B2: GENERICOS
A3: TOTALES | C3: =SUM(C$4:C$1048576) -> 0.13 | D3: =SUM(D$4:D$1048576) -> 0 | E3: =SUM(E$5:E$1048576) -> 0 | F3: =SUM(F$5:F$1048576) -> 0 | G3: =SUM(G$5:G$1048576) -> 0
A4: FECHA | B4: F- E- T- | C4: DEUDA Y ABONOS | D4: VACIO 1/4 | E4: VACIO 350 | F4: VACIO 1.25 | G4: RETECION
A5: 45869 | B5: T | C5: -15.85
A6: 45869 | B6: F | C6: 15.85
A7: 45884 | B7: T | C7: -26.77
A8: 45883 | B8: F | C8: 26.9
A9: 45925 | B9: F | C9: 15.85
A10: 45930 | B10: T | C10: -15.85
A11: 45953 | B11: T | C11: -23.33
A12: 45953 | B12: F | C12: 23.33
A13: 45974 | B13: T | C13: -45
A14: 45974 | B14: F | C14: 57
A15: 45975 | B15: T | C15: -12
A16: 45981 | B16: T | C16: -33.89
... A21: 46010 | B21: T | C21: -23.14

Sheet EL ATAJO CAFE
A1: CLIENTE | B1: EL ATAJO CAFE
A2: NOMBRE | B2: NERSA CONTRERAS
A3: TOTALES | C3: =SUM(C$4:C$1048576) -> 61.12 | D3: =SUM(D$4:D$1048576) -> 0 | E3: =SUM(E$5:E$1048576) -> 0 | F3: =SUM(F$5:F$1048576) -> 0 | G3: =SUM(G$5:G$1048576) -> 0
A4: FECHA | B4: F- E- T- | C4: DEUDA Y ABONOS | D4: VACIO 1/4 | E4: VACIO 350 | F4: VACIO 1.25 | G4: RETECION
A5: 45848 | B5: F | C5: 12.8
A6: 45848 | B6: F | C6: 25.45
A7: 45861 | B7: T | C7: -24.91 | L7: 273.05
A8: 45861 | B8: E | C8: -13.34 | L8: =+L6+L7 -> 273.05
A9: 45870 | B9: F | C9: 15.85 | L9: =25.45-32.95 -> -7.5
A10: 45870 | B10: F | C10: 14.04 | L10: =+L8+L9 -> 265.55
A11: 45870 | B11: F | C11: 1.65
A12: 45884 | B12: T | C12: -31.25
A13: 45884 | B13: F | C13: 15.02
A14: 45897 | B14: T | C14: -15.31
A15: 45897 | B15: F | C15: 25.45
A16: 45905 | B16: F | C16: 17.7
A17: 45916 | B17: F | C17: 15.85
A18: 45917 | B18: T | C18: -25.45
A19: 45917 | B19: T | C19: -17.7
A20: 45938 | B20: T | C20: -15.85
A21: 45938 | B21: F | C21: 9.6
A22: 45938 | B22: F | C22: 5.53
... A29: 46043 | B29: F | C29: 61.12

Sheet EL GRONE GOMEZ
A1: CLIENTE | B1: EL GRONE GOMEZ
A2: NOMBRE | B2: JESUS GOMEZ
A3: TOTALES | C3: =SUM(C$4:C$1048576) -> 84.37 | D3: =SUM(D$4:D$1048576) -> 0 | E3: =SUM(E$5:E$1048576) -> 0 | F3: =SUM(F$5:F$1048576) -> 0 | G3: =SUM(G$5:G$1048576) -> 0
A4: FECHA | B4: F- E- T- | C4: DEUDA Y ABONOS | D4: VACIO 1/4 | E4: VACIO 350 | F4: VACIO 1.25 | G4: RETECION
A5: 45820 | B5: F | C5: 20.8
A6: 45820 | B6: F | C6: 23.55
A7: 45827 | B7: T | C7: -44.35
A8: 45827 | B8: F | C8: 62.4
A9: 45856 | B9: T | C9: -46.5
A10: 45856 | B10: T | C10: -15.9
A11: 45856 | B11: F | C11: 104
A12: 45856 | B12: F | C12: 60.85
A13: 45884 | B13: T | C13: -102.48
A14: 45891 | B14: T | C14: -62.37
A15: 45891 | B15: T | C15: -163.51
A16: 45891 | B16: F | C16: 83.2
... A33: 46038 | B33: T | C33: -35.11

Sheet EL REY CACHAPA
A1: CLIENTE | B1: EL REY CACHAPA
A2: NOMBRE
A3: TOTALES | C3: =SUM(C$4:C$1048576) -> -0.83 | D3: =SUM(D$4:D$1048576) -> 0 | E3: =SUM(E$5:E$1048576) -> 0 | F3: =SUM(F$5:F$1048576) -> 0 | G3: =SUM(G$5:G$1048576) -> 0
A4: FECHA | B4: F- E- T- | C4: DEUDA Y ABONOS | D4: VACIO 1/4 | E4: VACIO 350 | F4: VACIO 1.25 | G4: RETECION
A5: 45815 | B5: F | C5: 107.55
A6: 45815 | B6: F | C6: 99.36
A7: 45821 | B7: T | C7: -206.91
A8: 45821 | B8: F | C8: 133.8
A9: 45828 | B9: T | C9: -133.8
A10: 45835 | B10: F | C10: 148
A11: 45835 | B11: F | C11: 20
A12: 45859 | B12: T | C12: -167.99
A13: 45891 | B13: F | C13: 256.65
A14: 45891 | B14: F | C14: 55.92
A15: 45906 | B15: T | C15: -300.08
A16: 45905 | B16: F | C16: 43.44
... A21: 46045 | B21: T | C21: -235

Sheet EL RINCON DEL DULCE
A1: CLIENTE | B1: EL RINCON DEL DULCE
A2: NOMBRE | B2: PEDRO GARCIA
A3: TOTALES | C3: =SUM(C$4:C$1048576) -> -0.03 | D3: =SUM(D$4:D$1048576) -> 0 | E3: =SUM(E$5:E$1048576) -> 0 | F3: =SUM(F$5:F$1048576) -> 0 | G3: =SUM(G$5:G$1048576) -> 0
A4: FECHA | B4: F- E- T- | C4: DEUDA Y ABONOS | D4: VACIO 1/4 | E4: VACIO 350 | F4: VACIO 1.25 | G4: RETECION
A5: 45883 | B5: F | C5: 53.85
A6: 45883 | B6: F | C6: 35.16
A7: 45884 | B7: F | C7: 12.1
A8: 45890 | B8: E | C8: -101.12
A9: 45890 | B9: F | C9: 53
A10: 45899 | B10: E | C10: -53
A11: 45899 | B11: F | C11: 69.7
A12: 45899 | B12: F | C12: 125.04
A13: 45912 | B13: E | C13: -194.74
A14: 45912 | B14: F | C14: 19.6
A15: 45912 | B15: F | C15: 35.16
A16: 45929 | B16: E | C16: -54.77
... A19: 45996 | B19: E | C19: -3.39

Sheet EMPANADA ANA RAMIREZ
A1: CLIENTE | B1: EMPANADA ANA RAMIREZ
A2: NOMBRE
A3: TOTALES | C3: =SUM(C$4:C$1048576) -> 0 | D3: =SUM(D$4:D$1048576) -> 0 | E3: =SUM(E$5:E$1048576) -> 0 | F3: =SUM(F$5:F$1048576) -> 0 | G3: =SUM(G$5:G$1048576) -> 0
A4: FECHA | B4: F- E- T- | C4: DEUDA Y ABONOS | D4: VACIO 1/4 | E4: VACIO 350 | F4: VACIO 1.25 | G4: RETECION
A5: 45918 | B5: F | C5: 13.45
A6: 45926 | B6: E | C6: -13.45

Sheet EMPANADA BELKIS ZAMBRANO
A1: CLIENTE | B1: EMPANADA BELKIS ZAMBRANO
A2: NOMBRE
A3: TOTALES | C3: =SUM(C$4:C$1048576) -> 0 | D3: =SUM(D$4:D$1048576) -> 0 | E3: =SUM(E$5:E$1048576) -> 0 | F3: =SUM(F$5:F$1048576) -> 0 | G3: =SUM(G$5:G$1048576) -> 0
A4: FECHA | B4: F- E- T- | C4: DEUDA Y ABONOS | D4: VACIO 1/4 | E4: VACIO 350 | F4: VACIO 1.25 | G4: RETECION
A5: 46013 | B5: F | C5: 55.76
A6: 46013 | B6: T | C6: -55.76

Sheet EMPANADA LIAM
A1: CLIENTE | B1: EMPANADA LIAM
A2: NOMBRE
A3: TOTALES | C3: =SUM(C$4:C$1048576) -> 0 | D3: =SUM(D$4:D$1048576) -> 0 | E3: =SUM(E$5:E$1048576) -> 0 | F3: =SUM(F$5:F$1048576) -> 0 | G3: =SUM(G$5:G$1048576) -> 0
A4: FECHA | B4: F- E- T- | C4: DEUDA Y ABONOS | D4: VACIO 1/4 | E4: VACIO 350 | F4: VACIO 1.25 | G4: RETECION
A5: 46051 | B5: F | C5: 34.56
A6: 46056 | B6: T | C6: -34.56

Sheet EMPANA LAS NONAS
A1: CLIENTE | B1: EMPANADAS LAS NONAS
A2: NOMBRE
A3: TOTALES | C3: =SUM(C$4:C$1048576) -> 42.23 | D3: =SUM(D$4:D$1048576) -> 0 | E3: =SUM(E$5:E$1048576) -> 0 | F3: =SUM(F$5:F$1048576) -> 0 | G3: =SUM(G$5:G$1048576) -> 0
A4: FECHA | B4: F- E- T- | C4: DEUDA Y ABONOS | D4: VACIO 1/4 | E4: VACIO 350 | F4: VACIO 1.25 | G4: RETECION
A5: 45821 | B5: F | C5: 63.15
A6: 45825 | B6: T | C6: -63.14
A7: 45832 | B7: F | C7: 55.35
A8: 45833 | B8: T | C8: -55.34
A9: 45835 | B9: F | C9: 31.45
A10: 45842 | B10: T | C10: -31.47
A11: 45842 | B11: F | C11: 49.8
A12: 45849 | B12: F | C12: 47.3
A13: 45853 | B13: T | C13: -47.3
A14: 45859 | B14: T | C14: -49.8
A15: 45856 | B15: F | C15: 63.15
A16: 45862 | B16: T | C16: -63.15
... A95: 46055 | B95: T | C95: -166.08

Sheet EMPANA SANTA TERESA
A1: CLIENTE | B1: EMPANA SANTA TERESA
A2: NOMBRE
A3: TOTALES | C3: =SUM(C$4:C$1048576) -> -0.78 | D3: =SUM(D$4:D$1048576) -> 0 | E3: =SUM(E$5:E$1048576) -> 0 | F3: =SUM(F$5:F$1048576) -> 0 | G3: =SUM(G$5:G$1048576) -> 0
A4: FECHA | B4: F- E- T- | C4: DEUDA Y ABONOS | D4: VACIO 1/4 | E4: VACIO 350 | F4: VACIO 1.25 | G4: RETECION
A5: 45867 | B5: F | C5: 23.64
A6: 45869 | B6: E | C6: -24.42

Sheet EMPRENDIMIENTO EDGAR
A1: CLIENTE | B1: EMPRENDIMIENTO EDGAR
A2: NOMBRE
A3: TOTALES | C3: =SUM(C$4:C$1048576) -> 0 | D3: =SUM(D$4:D$1048576) -> 0 | E3: =SUM(E$5:E$1048576) -> 0 | F3: =SUM(F$5:F$1048576) -> 0 | G3: =SUM(G$5:G$1048576) -> 0
A4: FECHA | B4: F- E- T- | C4: DEUDA Y ABONOS | D4: VACIO 1/4 | E4: VACIO 350 | F4: VACIO 1.25 | G4: RETECION
A5: 45834 | B5: T | C5: -15.85
A6: 45833 | B6: F | C6: 15.85

Sheet EMPRENDIMIENTO LARRY
A1: CLIENTE | B1: EMPRENDIMIENTO LARRY
A2: NOMBRE | B2: LARRY SANCHEZ
A3: TOTALES | C3: =SUM(C$4:C$1048576) -> 449.97 | D3: =SUM(D$4:D$1048576) -> 3 | E3: =SUM(E$5:E$1048576) -> 0 | F3: =SUM(F$5:F$1048576) -> 0 | G3: =SUM(G$5:G$1048576) -> 0
A4: FECHA | B4: F- E- T- | C4: DEUDA Y ABONOS | D4: VACIO 1/4 | E4: VACIO 350 | F4: VACIO 1.25 | G4: RETECION
A5: 45826 | B5: F | C5: 15.85
A6: 45826 | B6: F | C6: 41.6
A7: 45833 | B7: T | C7: -8.53
A8: 45833 | B8: T | C8: -48.92
A9: 45833 | B9: F | C9: 41.6
A10: 45833 | B10: F | C10: 15.85
A11: 45840 | B11: T | C11: -57.45
A12: 45840 | B12: F | C12: 15.85
A13: 45840 | B13: F | C13: 69.32
A14: 45840 | B14: F | C14: 41.6
A15: 45847 | B15: T | C15: -118.76
A16: 45847 | B16: T | C16: -8.1
... A41: 45889 | B41: T | C41: -109.57
A42: 45889 | B42: F | C42: 116.75 | I42: AQUI COMIENZA
A43: 45889 | B43: F | C43: 131.41
A44: 45889 | B44: F | C44: 37.65
A45: 45889 | B45: F | C45: 41.6
A46: 45896 | B46: T | C46: -85.89
A47: 45896 | B47: T | C47: -150.03
A48: 45896 | B48: F | C48: 24.85
A49: 45896 | B49: F | C49: 47.31
A50: 45896 | B50: F | C50: 46.27
A51: 45896 | B51: F | C51: 41.6
A52: 45903 | B52: F | C52: 53.29
A53: 45903 | B53: F | C53: 136.15
A54: 45903 | B54: F | C54: 10.35
... A118: 46017 | B118: T | C118: -19.91
A119: 46017 | B119: F | C119: 238.23 | D119: 2
A120: 46024 | B120: T | C120: -99.55
A121: 46024 | B121: T | C121: -39.82
A122: 46024 | B122: T | C122: -41.78
A123: 46027 | B123: T | C123: -98.46
A124: 46029 | B124: F | C124: 287.47
A125: 46036 | B125: T | C125: -40.12
A126: 46036 | B126: T | C126: -104.02
A127: 46036 | B127: F | C127: 187.91 | D127: 1
A128: 46042 | B128: T | C128: -117.05
A129: 46043 | B129: T | C129: -37.44
A130: 46043 | B130: F | C130: 176.14
A131: 46049 | B131: T | C131: -139.3
A132: 46050 | B132: T | C132: -69.16
A133: 46050 | B133: F | C133: 312.36

Sheet EMPRENDIMIENTO MAIBEL
A1: CLIENTE | B1: EMPRENDIMIENTO MAIBEL
A2: NOMBRE | B2: MAIBEL MOLINA
A3: TOTALES | C3: =SUM(C$4:C$1048576) -> -0.01 | D3: =SUM(D$4:D$1048576) -> 1 | E3: =SUM(E$5:E$1048576) -> -1 | F3: =SUM(F$5:F$1048576) -> 0 | G3: =SUM(G$5:G$1048576) -> 0
A4: FECHA | B4: F- E- T- | C4: DEUDA Y ABONOS | D4: VACIO 1/4 | E4: VACIO 350 | F4: VACIO 1.25 | G4: RETECION
A5: 45834 | B5: T | C5: -67.85
A6: 45834 | B6: F | C6: 42.48
A7: 45834 | B7: F | C7: 25.38
A8: 45840 | B8: F | C8: 15.85
A9: 45840 | B9: F | C9: 68.98
A10: 45842 | B10: T | C10: -84.83
A11: 45848 | B11: F | C11: 15.85
A12: 45848 | B12: F | C12: 73.13
A13: 45848 | B13: F | C13: 16.32
A14: 45849 | B14: T | C14: -105.3
A15: 45855 | B15: T | C15: -93.12
A16: 45855 | B16: F | C16: 36.7 | E16: 1
A17: 45855 | B17: F | C17: 56.42
A18: 45862 | B18: V | E18: -1
A19: 45869 | B19: F | C19: 51.39
A20: 45869 | B20: F | C20: 103.89
A21: 45869 | B21: F | C21: 45.39
A22: 45876 | B22: E | C22: -140.64
A23: 45876 | B23: F | C23: 7.5
A24: 45876 | B24: F | C24: 57.32
A25: 45876 | B25: F | C25: 19.26
A26: 45883 | B26: E | C26: -86.78
A27: 45883 | B27: F | C27: 34.45
A28: 45883 | B28: F | C28: 56.76
A29: 45883 | B29: F | C29: 16.32
A30: 45887 | B30: T | C30: -107.53
... A42: 45917 | B42: T | C42: -152.06
A43: 45919 | B43: F | C43: 45.4 | D43: 1 | E43: -1
A44: 45919 | B44: F | C44: 104.64
A45: 45924 | B45: T | C45: -133.04
A46: 45924 | B46: T | C46: -17.22
A47: 45926 | B47: T | C47: -60
A48: 45926 | B48: F | C48: 16.5 | D48: -1
A49: 45926 | B49: F | C49: 143.36
A50: 45932 | B50: T | C50: -102.34
A51: 45933 | B51: T | C51: -100
A52: 45933 | B52: F | C52: 220.44
A53: 45933 | B53: F | C53: 38.28
A54: 45933 | B54: F | C54: 41.6
A55: 45936 | B55: T | C55: -129.99
A56: 45938 | B56: T | C56: -70.32
A57: 45940 | B57: F | C57: 37.36 | D57: 1
A58: 45940 | B58: F | C58: 95.28
A59: 45940 | B59: F | C59: 25.05
A60: 45945 | B60: T | C60: -80
A61: 45947 | B61: T | C61: -14.72
A62: 45947 | B62: T | C62: -67.47
A63: 45947 | B63: F | C63: 90.24
A64: 45947 | B64: F | C64: 29.57
A65: 45950 | B65: T | C65: -124.31
A66: 45954 | B66: F | C66: 38.94
A67: 45954 | B67: F | C67: 50.4
A68: 45954 | B68: F | C68: 46
A69: 45960 | B69: T | C69: -42.91
... A106: 46050 | B106: T | C106: -30

Sheet EMPRENDIMIENTO MANZO
A1: CLIENTE | B1: EMPRENDIMIENTO MANZO
A2: NOMBRE
A3: TOTALES | C3: =SUM(C$4:C$1048576) -> 0.78 | D3: =SUM(D$4:D$1048576) -> 0 | E3: =SUM(E$5:E$1048576) -> 0 | F3: =SUM(F$5:F$1048576) -> 0 | G3: =SUM(G$5:G$1048576) -> 0
A4: FECHA | B4: F- E- T- | C4: DEUDA Y ABONOS | D4: VACIO 1/4 | E4: VACIO 350 | F4: VACIO 1.25 | G4: RETECION
A5: 45813 | B5: F | C5: 25.69
A6: 45813 | B6: F | C6: 19
A7: 45826 | B7: T | C7: -44.69
A8: 45846 | B8: F | C8: 25.69
A9: 45846 | B9: F | C9: 36.72
A10: 45859 | B10: T | C10: -61.96
A11: 45867 | B11: F | C11: 17.34
A12: 45867 | B12: F | C12: 61.44
A13: 45888 | B13: E | C13: -78.78
A14: 45888 | B14: F | C14: 15
A15: 45888 | B15: F | C15: 77.76
A16: 45902 | B16: E | C16: -92.75
... A26: 46052 | B26: T | C26: -77.36

Sheet EMPRENDIMIENTO MARIA ROMERO
A1: CLIENTE | B1: EMPRENDIMIENTO MARIA ROMERO
A2: NOMBRE
A3: TOTALES | C3: =SUM(C$4:C$1048576) -> 0.01 | D3: =SUM(D$4:D$1048576) -> 0 | E3: =SUM(E$5:E$1048576) -> 0 | F3: =SUM(F$5:F$1048576) -> 0 | G3: =SUM(G$5:G$1048576) -> 0
A4: FECHA | B4: F- E- T- | C4: DEUDA Y ABONOS | D4: VACIO 1/4 | E4: VACIO 350 | F4: VACIO 1.25 | G4: RETECION
A5: 45910 | B5: F | C5: 150.05
A6: 45915 | B6: T | C6: -150.04
A7: 45924 | B7: F | C7: 15
A8: 45924 | B8: F | C8: 51
A9: 45930 | B9: T | C9: -66
A10: 45938 | B10: F | C10: 49.5
A11: 45938 | B11: F | C11: 73.49
A12: 45944 | B12: T | C12: -122.98
A13: 45944 | B13: F | C13: 23.4
A14: 45950 | B14: T | C14: -23.4
A15: 45953 | B15: F | C15: 70.04
A16: 45965 | B16: F | C16: 7.5
... A29: 46051 | B29: T | C29: -74.44

Sheet EMPRENDIMIENTO MIRLEY
A1: CLIENTE | B1: EMPRENDIMIENTO MIRLEY
A2: NOMBRE
A3: TOTALES | C3: =SUM(C$4:C$1048576) -> 239.21 | D3: =SUM(D$4:D$1048576) -> -1 | E3: =SUM(E$5:E$1048576) -> 0 | F3: =SUM(F$5:F$1048576) -> -1 | G3: =SUM(G$5:G$1048576) -> 0
A4: FECHA | B4: F- E- T- | C4: DEUDA Y ABONOS | D4: VACIO 1/4 | E4: VACIO 350 | F4: VACIO 1.25 | G4: RETECION
A5: 45813 | B5: F | C5: 15.85
A6: 45813 | B6: F | C6: 10.68
A7: 45819 | B7: F | C7: 26.16
A8: 45825 | B8: T | C8: -26.53
A9: 45825 | B9: T | C9: -26.16
A10: 45832 | B10: F | C10: 15.85
A11: 45832 | B11: F | C11: 5.04
A12: 45839 | B12: F | C12: 9.84
A13: 45839 | B13: F | C13: 8.6
A14: 45846 | B14: T | C14: -39.33
A15: 45846 | B15: F | C15: 33.19
A16: 45846 | B16: F | C16: 32.91
... A63: 45947 | B63: T | C63: -134.88
A64: 45947 | B64: F | C64: 4.5 | D64: -1
A65: 45951 | B65: T | C65: -119.76
A66: 45951 | B66: F | C66: 9
A67: 45951 | B67: F | C67: 46.65
A68: 45951 | B68: F | C68: 26.7
A69: 45953 | B69: T | C69: -59.7
A70: 45958 | B70: F | C70: 41.38
A71: 45958 | B71: F | C71: 41.43
A72: 45958 | B72: F | C72: 4.08
A73: 45960 | B73: T | C73: -73.68
A74: 45965 | B74: T | C74: -59.7
A75: 45965 | B75: F | C75: 29.34
A76: 45965 | B76: F | C76: 151.49
... A89: 46000 | B89: T | C89: -191
A90: 46000 | B90: F | C90: 260.06 | F90: -1
A91: 46007 | B91: F | C91: 249.86
A92: 46013 | B92: F | C92: 101.22
A93: 46013 | B93: T | C93: -77.08
A94: 46013 | B94: T | C94: -182.97
A95: 46024 | B95: T | C95: -249.86
A96: 46027 | B96: T | C96: -101.22
A97: 46028 | B97: F | C97: 117.3
A98: 46035 | B98: F | C98: 137.84
A99: 46036 | B99: T | C99: -117.3
A100: 46042 | B100: T | C100: -137.84
A101: 46042 | B101: F | C101: 125.56
A102: 46048 | B102: T | C102: -125.56
... A106: 46056 | B106: F | C106: 221.66

Sheet EMPRENDIMIENTO RAKEL ROJAS
A1: CLIENTE | B1: EMPRENDIMIENTO RAKEL ROJAS
A2: NOMBRE
A3: TOTALES | C3: =SUM(C$4:C$1048576) -> -6 | D3: =SUM(D$4:D$1048576) -> 0 | E3: =SUM(E$5:E$1048576) -> 0 | F3: =SUM(F$5:F$1048576) -> 0 | G3: =SUM(G$5:G$1048576) -> 0
A4: FECHA | B4: F- E- T- | C4: DEUDA Y ABONOS | D4: VACIO 1/4 | E4: VACIO 350 | F4: VACIO 1.25 | G4: RETECION
A5: 45881 | B5: E V | C5: -6 | D5: -1
A6: 45881 | B6: V | D6: 1

Sheet EMPRENDIMIENTO YAHIBE MOLINA
A1: CLIENTE | B1: EMPRENDIMIENTO YAHIBE MOLINA
A2: NOMBRE
A3: TOTALES | C3: =SUM(C$4:C$1048576) -> 96.65 | D3: =SUM(D$4:D$1048576) -> 0 | E3: =SUM(E$5:E$1048576) -> 0 | F3: =SUM(F$5:F$1048576) -> 0 | G3: =SUM(G$5:G$1048576) -> 0
A4: FECHA | B4: F- E- T- | C4: DEUDA Y ABONOS | D4: VACIO 1/4 | E4: VACIO 350 | F4: VACIO 1.25 | G4: RETECION
A5: 45813 | B5: F | C5: 15.85
A6: 45819 | B6: T | C6: -15.45
A7: 45819 | B7: F | C7: 126.93
A8: 45827 | B8: T | C8: -57.84
A9: 45828 | B9: T | C9: -69.53
A10: 45832 | B10: F | C10: 15.85
A11: 45832 | B11: F | C11: 67.31
A12: 45832 | B12: F | C12: 22.1
A13: 45849 | B13: T | C13: -84.84
A14: 45852 | B14: T | C14: -20.38
A15: 45853 | B15: F | C15: 25.69
A16: 45853 | B16: F | C16: 83.86
... A46: 45930 | B46: F | C46: 83.88
A47: 45930 | B47: F | C47: =37.74+2.42 -> 40.16
A48: 45944 | B48: T | C48: -88.72
A49: 45944 | B49: F | C49: 56.7
A50: 45944 | B50: F | C50: 85.4
A51: 45944 | B51: F | C51: 27.68
A52: 45947 | B52: T | C52: -92.85
A53: 45950 | B53: T | C53: -53.48
A54: 45951 | B54: T | C54: -116.87
A55: 45951 | B55: F | C55: 24.64
A56: 45951 | B56: F | C56: 111.02
A57: 45951 | B57: F | C57: 24.22
A58: 45958 | B58: T | C58: -100.29
A59: 45958 | B59: F | C59: 26.22
... A86: 46056 | B86: F | C86: 79.58

Sheet EMPRENDIMIENTO YOSMAR GANBOA
A1: CLIENTE | B1: EMPRENDIMIENTO YOSMAR GANBOA
A2: NOMBRE
A3: TOTALES | C3: =SUM(C$4:C$1048576) -> 170.79 | D3: =SUM(D$4:D$1048576) -> 0 | E3: =SUM(E$5:E$1048576) -> 0 | F3: =SUM(F$5:F$1048576) -> 0 | G3: =SUM(G$5:G$1048576) -> 0
A4: FECHA | B4: F- E- T- | C4: DEUDA Y ABONOS | D4: VACIO 1/4 | E4: VACIO 350 | F4: VACIO 1.25 | G4: RETECION
A5: 46010 | B5: F | C5: 617.46
A6: 46017 | B6: T | C6: -91.1
A7: 46017 | B7: T | C7: -137.29
A8: 46017 | B8: T | C8: -34.24
A9: 46021 | B9: T | C9: -97.98
A10: 46024 | B10: T | C10: -19.3
A11: 46029 | B11: T | C11: -77.1
A12: 46029 | B12: T | C12: -82.05
A13: 46031 | B13: T | C13: -77.98
A14: 46031 | B14: F | C14: 213.64
A15: 46048 | B15: T | C15: -59.06
A16: 46048 | B16: T | C16: -64.69
... A19: 46052 | B19: F | C19: 204.52

Sheet ERIKA DIAMANTE EXPRESS
A1: CLIENTE | B1: ERIKA DIAMANTE EXPRESS
A2: NOMBRE
A3: TOTALES | C3: =SUM(C$4:C$1048576) -> 0 | D3: =SUM(D$4:D$1048576) -> 0 | E3: =SUM(E$5:E$1048576) -> 0 | F3: =SUM(F$5:F$1048576) -> 0 | G3: =SUM(G$5:G$1048576) -> 0
A4: FECHA | B4: F- E- T- | C4: DEUDA Y ABONOS | D4: VACIO 1/4 | E4: VACIO 350 | F4: VACIO 1.25 | G4: RETECION
A5: 45980 | B5: T | C5: -26.22
A6: 45981 | B6: F | C6: 26.22

Sheet EVENTO SENIAT
A1: CLIENTE | B1: EVENTO SENIAT
A2: NOMBRE
A3: TOTALES | C3: =SUM(C$4:C$1048576) -> 0 | D3: =SUM(D$4:D$1048576) -> 40 | E3: =SUM(E$5:E$1048576) -> 0 | F3: =SUM(F$5:F$1048576) -> 0 | G3: =SUM(G$5:G$1048576) -> 0
A4: FECHA | B4: F- E- T- | C4: DEUDA Y ABONOS | D4: VACIO 1/4 | E4: VACIO 350 | F4: VACIO 1.25 | G4: RETECION
A5: 46009 | B5: F | D5: 100
A6: 46011 | B6: V | D6: -60

Sheet EVENTUAL NELSON
A1: CLIENTE | B1: EVENTUAL NELSON
A2: NOMBRE
A3: TOTALES | C3: =SUM(C$4:C$1048576) -> -0.01 | D3: =SUM(D$4:D$1048576) -> 0 | E3: =SUM(E$5:E$1048576) -> 0 | F3: =SUM(F$5:F$1048576) -> 0 | G3: =SUM(G$5:G$1048576) -> 0
A4: FECHA | B4: F- E- T- | C4: DEUDA Y ABONOS | D4: VACIO 1/4 | E4: VACIO 350 | F4: VACIO 1.25 | G4: RETECION
A5: 45968 | B5: F | C5: 25
A6: 45968 | B6: F | C6: 37.35
A7: 45974 | B7: T | C7: -16.27
A8: 46010 | B8: T | C8: -46.09

Sheet FARMA BIEN
A1: CLIENTE | B1: FARMA BIEN
A2: NOMBRE
A3: TOTALES | C3: =SUM(C$4:C$1048576) -> 239.08 | D3: =SUM(D$4:D$1048576) -> 0 | E3: =SUM(E$5:E$1048576) -> 0 | F3: =SUM(F$5:F$1048576) -> 0 | G3: =SUM(G$5:G$1048576) -> 22.43
A4: FECHA | B4: F- E- T- | C4: DEUDA Y ABONOS | D4: VACIO 1/4 | E4: VACIO 350 | F4: VACIO 1.25 | G4: RETECION
A5: 45825 | B5: F | C5: =54.77-G5 -> 49.11 | G5: 5.66
A6: 45825 | B6: F | C6: 15.94
A7: 45827 | B7: T | C7: -65.04 | G7: -5.66
A8: 45846 | B8: F | C8: =19.46-G8 -> 17.07 | G8: 2.39
A9: 45846 | B9: F | C9: 10.01
A10: 45853 | B10: T | C10: -26.86 | G10: -2.39
A11: 45860 | B11: F | C11: =35.31-G11 -> 31.31 | G11: 4
A12: 45860 | B12: F | C12: 3.39
A13: 45861 | B13: T | C13: -34.49 | G13: -4
A14: 45874 | B14: F | C14: =20.5-G14 -> 18.38 | G14: 2.12
A15: 45874 | B15: F | C15: =12.3-G15 -> 11.93 | G15: 0.37
A16: 45874 | B16: F | C16: =6.78-G16 -> 6.08 | G16: 0.7
A17: 45888 | B17: T | C17: -36.06 | G17: -3.19
A18: 45888 | B18: F | C18: =38.92-G18 -> 34.52 | G18: 4.4
A19: 45888 | B19: F | C19: 11.87
A20: 45902 | B20: T | C20: -45.97 | G20: -4.4
A21: 45902 | B21: F | C21: =35.31-G21 -> 31.66 | G21: 3.65
A22: 45902 | B22: F | C22: 12.5
A23: 45906 | B23: T | C23: -43.77 | G23: -3.65
A24: 45923 | B24: F | C24: =35.31-G24 -> 31.66 | G24: 3.65
A25: 45923 | B25: F | C25: 2.14
A26: 45923 | B26: F | C26: =4.59-G26 -> 4.13 | G26: 0.46
A27: 45930 | B27: T | C27: -37.56 | G27: -4.11
A28: 45944 | B28: F | C28: =55.3-G28 -> 49.58 | G28: 5.72
A29: 45944 | B29: F | C29: =20.77-G29 -> 20.56 | G29: 0.21 | I29: =1768.53/218.17 -> 8.1062016
A30: 45946 | B30: T | C30: -69.46 | G30: -5.93
A31: 45958 | B31: F | C31: =73.22-G31 -> 65.65 | G31: 7.57
A32: 45958 | B32: F | C32: =5.14-G32 -> 4.61 | G32: 0.53
A33: 45960 | B33: T | C33: -69.71 | G33: -8.1
A34: 45982 | B34: F | C34: =87.12-G34 -> 79.96 | G34: 7.16
A35: 45993 | B35: T | C35: -79.45
A36: 45996 | B36: F | C36: =49.14-G36 -> 46.67 | G36: 2.47 | K36: =628.24/254.8705 -> 2.4649381
A37: 46010 | B37: T | C37: -3.65
A38: 46010 | B38: T | C38: -46.01 | G38: -2.47
A39: 46024 | B39: R | G39: -7.16
A40: 46031 | B40: F | C40: =132.7-G40 -> 119.65 | G40: 13.05
A41: 46037 | B41: T | C41: -119.65 | G41: -13.05
A42: 46049 | B42: F | C42: =263.95-G42 -> 241.52 | G42: 22.43
A43: 46051 | B43: T | C43: -3.14

Sheet FISICO
A1: CLIENTE | B1: FISICO
A2: NOMBRE | B2: JHONATAN
A3: TOTALES | C3: =SUM(C$4:C$1048576) -> 8.54 | D3: =SUM(D$4:D$1048576) -> 0 | E3: =SUM(E$5:E$1048576) -> 0 | F3: =SUM(F$5:F$1048576) -> 0 | G3: =SUM(G$5:G$1048576) -> 0
A4: FECHA | B4: F- E- T- | C4: DEUDA Y ABONOS | D4: VACIO 1/4 | E4: VACIO 350 | F4: VACIO 1.25 | G4: RETECION
A5: 45827 | B5: T | C5: -15.6
A6: 45827 | B6: F | C6: =92.4-G6 -> 84.46 | G6: 7.94
A7: 45828 | B7: T | C7: -67.73
A8: 45841 | B8: F | C8: =19.2-G8 -> 17.22 | G8: 1.98
A9: 45846 | B9: R | G9: -7.94
A10: 45848 | B10: T | C10: -16.61
A11: 45849 | B11: R | G11: -1.98
A12: 45849 | B12: F | C12: =76.8-G12 -> 68.86 | G12: 7.94
A13: 45855 | B13: R | G13: -7.94
A14: 45862 | B14: T | C14: -68.31
A15: 45862 | B15: F | C15: =57.6-G15 -> 51.65 | G15: 5.95
A16: 45866 | B16: T | C16: -51.59 | G16: -5.95
A17: 45876 | B17: F | C17: =76.8-G17 -> 68.86 | G17: 7.94
A18: 45880 | B18: T | C18: -67.77 | G18: -3.97
A19: 45881 | B19: T | G19: -3.97
A20: 45890 | B20: T | C20: -23.19
A21: 45890 | B21: F | C21: =100.2-G21 -> 92.26 | G21: 7.94
A22: 45891 | B22: T | C22: -68.24
A23: 45895 | B23: R | G23: -3.97
A24: 45895 | B24: R | G24: -3.97
A25: 45911 | B25: F | C25: =96-G25 -> 86.07 | G25: 9.93
A26: 45932 | B26: T | C26: -85.42
A27: 45932 | B27: T | C27: -4.27 | G27: -9.93
A28: 45932 | B28: F | C28: =57.6-G28 -> 51.65 | G28: 5.95
A29: 45938 | B29: T | C29: -49.47 | G29: -5.95
A30: 45946 | B30: F | C30: =57.6-G30 -> 51.65 | G30: 5.95
A31: 45946 | B31: F | C31: 15.6
A32: 45948 | B32: T | C32: -50.58 | G32: -5.95
A33: 45953 | B33: F | C33: =38.4-G33 -> 34.43 | G33: 3.97
A34: 45953 | B34: F | C34: 23.5
A35: 45960 | B35: R | G35: -3.97
A36: 45966 | B36: T | C36: -16.35
A37: 45967 | B37: T | C37: -23.35
A38: 45967 | B38: F | C38: =76.8-G38 -> 69.06 | G38: 7.74
A39: 45974 | B39: T | C39: -16.35 | I39: =+C38/1.16 -> 59.534483 | L39: =400.16/201.4665 -> 1.9862359
A40: 45998 | B40: T | C40: -33.08 | G40: -7.74 | I40: =+I39*0.16 -> 9.5255172 | L40: =800.31/201.4665 -> 3.9724222
A41: 45998 | B41: T | C41: -33.08 | I41: =+I40*0.75 -> 7.1441379
A42: 46001 | B42: T | C42: -15.74
K44: =903.95/233.5576 -> 3.8703515
K45: 3.87

Sheet FLOR ASOGATA
A1: CLIENTE | B1: FLOR ASOGATA
A2: NOMBRE
A3: TOTALES | C3: =SUM(C$4:C$1048576) -> 0 | D3: =SUM(D$4:D$1048576) -> 0 | E3: =SUM(E$5:E$1048576) -> 0 | F3: =SUM(F$5:F$1048576) -> 0 | G3: =SUM(G$5:G$1048576) -> 0
A4: FECHA | B4: F- E- T- | C4: DEUDA Y ABONOS | D4: VACIO 1/4 | E4: VACIO 350 | F4: VACIO 1.25 | G4: RETECION
A5: 45962 | B5: T | C5: -37.35
A6: 45961 | B6: F | C6: 37.35
L39: =400.16/201.4665 -> 1.9862359
L40: =800.31/201.4665 -> 3.9724222

Sheet FLORES DEL TRIGO
A1: CLIENTE | B1: FLORES DEL TRIGO
A2: NOMBRE | B2: CRISTIAN HERNANDEZ
A3: TOTALES | C3: =SUM(C$4:C$1048576) -> 17.25 | D3: =SUM(D$4:D$1048576) -> 1 | E3: =SUM(E$5:E$1048576) -> 0 | F3: =SUM(F$5:F$1048576) -> 0 | G3: =SUM(G$5:G$1048576) -> 0
A4: FECHA | B4: F- E- T- | C4: DEUDA Y ABONOS | D4: VACIO 1/4 | E4: VACIO 350 | F4: VACIO 1.25 | G4: RETECION
A5: 45821 | B5: F | C5: 31.7
A6: 45834 | B6: T | C6: -31.7
A7: 45840 | B7: F | C7: 31.7
A8: 45854 | B8: T | C8: -31.7
A9: 45854 | B9: F | C9: 15.85
A10: 45876 | B10: T | C10: -15.75
A11: 45877 | B11: F | C11: 15.85
A12: 45882 | B12: F | C12: 15.85
A13: 45897 | B13: T | C13: -31.8
A14: 45903 | B14: F | C14: 31.7
A15: 45915 | B15: T | C15: -31.82
A16: 45918 | B16: F | C16: 15.85
... A25: 46009 | B25: T | C25: -16.4
A26: 46014 | B26: F | C26: 16.38 | D26: 1
A27: 46030 | B27: T | C27: -16
A28: 46036 | B28: F | C28: 17.28

Sheet FLORESK & CAFE
A1: CLIENTE | B1: FLORESK & CAFE
A2: NOMBRE
A3: TOTALES | C3: =SUM(C$4:C$1048576) -> 15.7 | D3: =SUM(D$4:D$1048576) -> 1 | E3: =SUM(E$5:E$1048576) -> 0 | F3: =SUM(F$5:F$1048576) -> 0 | G3: =SUM(G$5:G$1048576) -> 0
A4: FECHA | B4: F- E- T- | C4: DEUDA Y ABONOS | D4: VACIO 1/4 | E4: VACIO 350 | F4: VACIO 1.25 | G4: RETECION
A5: 46035 | B5: F | C5: 27.28 | D5: 1
A6: 46037 | B6: T | C6: -27.28
A7: 46042 | B7: F | C7: 10
A8: 46049 | B8: T | C8: -10
A9: 46049 | B9: F | C9: 25.74
A10: 46056 | B10: T | C10: -25.74
A11: 46056 | B11: F | C11: 15.7

Sheet FOCACIA
A1: CLIENTE | B1: FOCACIA
A2: NOMBRE | B2: FRANKLIN FOCACIO
A3: TOTALES | C3: =SUM(C$4:C$1048576) -> 73.77 | D3: =SUM(D$4:D$1048576) -> 0 | E3: =SUM(E$5:E$1048576) -> 0 | F3: =SUM(F$5:F$1048576) -> 0 | G3: =SUM(G$5:G$1048576) -> 0
A4: FECHA | B4: F- E- T- | C4: DEUDA Y ABONOS | D4: VACIO 1/4 | E4: VACIO 350 | F4: VACIO 1.25 | G4: RETECION
A5: 45820 | B5: F | C5: 47.38
A6: 45827 | B6: T | C6: -47.04
A7: 45827 | B7: F | C7: 68.53
A8: 45833 | B8: F | C8: 72
A9: 45835 | B9: T | C9: -68.55
A10: 45840 | B10: F | C10: 72
A11: 45842 | B11: T | C11: -71.82
A12: 45848 | B12: T | C12: -72.53
A13: 45848 | B13: F | C13: 157.8
A14: 45859 | B14: T | C14: -92.32
A15: 45861 | B15: T | C15: -65.6
A16: 45861 | B16: F | C16: 115.8
... A46: 46051 | B46: T | C46: -71.44

Sheet FRESCURA DE MI TIERRA
A1: CLIENTE | B1: FRESCURA DE MI TIERRA
A2: NOMBRE | B2: RAMON
A3: TOTALES | C3: =SUM(C$4:C$1048576) -> 286.04 | D3: =SUM(D$4:D$1048576) -> 0 | E3: =SUM(E$5:E$1048576) -> 0 | F3: =SUM(F$5:F$1048576) -> 0 | G3: =SUM(G$5:G$1048576) -> 0
A4: FECHA | B4: F- E- T- | C4: DEUDA Y ABONOS | D4: VACIO 1/4 | E4: VACIO 350 | F4: VACIO 1.25 | G4: RETECION
A5: 45814 | B5: F | C5: 20.8
A6: 45814 | B6: F | C6: 17.54
A7: 45814 | B7: F | C7: 14.64
A8: 45821 | B8: T | C8: -52.98
A9: 45821 | B9: F | C9: 20.8
A10: 45821 | B10: F | C10: 86.66
A11: 45828 | B11: F | C11: 15.85
A12: 45828 | B12: F | C12: 60.68
A13: 45835 | B13: T | C13: -168.44
A14: 45835 | B14: F | C14: 20.8
A15: 45835 | B15: F | C15: 244.87
A16: 45841 | B16: F | C16: 41.6
... A58: 46037 | B58: E | C58: -22

Sheet FRIGORIFICO GABISCAR
A1: CLIENTE | B1: FRIGORIFICO GABISCAR
A2: NOMBRE
A3: TOTALES | C3: =SUM(C$4:C$1048576) -> 208.04 | D3: =SUM(D$4:D$1048576) -> 0 | E3: =SUM(E$5:E$1048576) -> 0 | F3: =SUM(F$5:F$1048576) -> 0 | G3: =SUM(G$5:G$1048576) -> 0
A4: FECHA | B4: F- E- T- | C4: DEUDA Y ABONOS | D4: VACIO 1/4 | E4: VACIO 350 | F4: VACIO 1.25 | G4: RETECION
A5: 45989 | B5: F | C5: 131.26
A6: 45995 | B6: T | C6: -129.86
A7: 46002 | B7: F | C7: 142.65
A8: 46015 | B8: T | C8: -143.93
A9: 46015 | B9: T | C9: -55.52
A10: 46015 | B10: F | C10: 55.52
A11: 46030 | B11: T | C11: -60.08
A12: 46030 | B12: F | C12: 60.08
A13: 46038 | B13: F | C13: 156.12
A14: 46047 | B14: T | C14: -156.12
A15: 46052 | B15: F | C15: 207.92

Sheet FRIGORIFICO OROZCO
A1: CLIENTE | B1: FRIGORIFICO OROZCO
A2: NOMBRE
A3: TOTALES | C3: =SUM(C$4:C$1048576) -> 0.09 | D3: =SUM(D$4:D$1048576) -> 0 | E3: =SUM(E$5:E$1048576) -> 0 | F3: =SUM(F$5:F$1048576) -> 0 | G3: =SUM(G$5:G$1048576) -> 0
A4: FECHA | B4: F- E- T- | C4: DEUDA Y ABONOS | D4: VACIO 1/4 | E4: VACIO 350 | F4: VACIO 1.25 | G4: RETECION
A5: 45982 | B5: F | C5: 55.99
A6: 45986 | B6: T | C6: -55.99
A7: 46031 | B7: F | C7: 121.4
A8: 46032 | B8: T | C8: -119.57
C9: -1.83
A10: 46038 | B10: F | C10: 10.76
A11: 46042 | B11: T | C11: -10.67

Sheet FRUTAS Y VERDURAS DON OMAR
A1: CLIENTE | B1: FRUTAS Y VERDURAS DON OMAR
A2: NOMBRE
A3: TOTALES | C3: =SUM(C$4:C$1048576) -> -0.13 | D3: =SUM(D$4:D$1048576) -> 0 | E3: =SUM(E$5:E$1048576) -> 0 | F3: =SUM(F$5:F$1048576) -> 0 | G3: =SUM(G$5:G$1048576) -> 0
A4: FECHA | B4: F- E- T- | C4: DEUDA Y ABONOS | D4: VACIO 1/4 | E4: VACIO 350 | F4: VACIO 1.25 | G4: RETECION
A5: 45947 | B5: F | C5: 174.8
A6: 45950 | B6: T | C6: -72
A7: 45952 | B7: T | C7: -15.99
A8: 45953 | B8: T | C8: -28
A9: 45954 | B9: F | C9: 181.53
A10: 45958 | B10: T | C10: -62.39
A11: 45960 | B11: T | C11: -94.7
A12: 45960 | B12: T | C12: -24.58
A13: 45961 | B13: T | C13: -58.81
A14: 45961 | B14: F | C14: 116.93
A15: 45967 | B15: T | C15: -87.89
A16: 45967 | B16: T | C16: -29.03
... A19: 45974 | B19: T | C19: -59.34

Sheet FRUTAS Y VERDURAS PALO GORDO
A1: CLIENTE | B1: FRUTAS Y VERDURAS PALO GORDO
A2: NOMBRE | B2: DARCY CONTRERAS
A3: TOTALES | C3: =SUM(C$4:C$1048576) -> 0.96 | D3: =SUM(D$4:D$1048576) -> 0 | E3: =SUM(E$5:E$1048576) -> 0 | F3: =SUM(F$5:F$1048576) -> 0 | G3: =SUM(G$5:G$1048576) -> 0
A4: FECHA | B4: F- E- T- | C4: DEUDA Y ABONOS | D4: VACIO 1/4 | E4: VACIO 350 | F4: VACIO 1.25 | G4: RETECION
A5: 45819 | B5: F | C5: 23.55
A6: 45819 | B6: F | C6: 91.62
A7: 45819 | B7: T | C7: -59.8
A8: 45824 | B8: T | C8: -51.88
A9: 45826 | B9: T | C9: -57.84
A10: 45826 | B10: F | C10: 17.54
A11: 45826 | B11: F | C11: 122.57
A12: 45826 | B12: F | C12: 10.55
A13: 45828 | B13: T | C13: -47.83
A14: 45831 | B14: T | C14: -33.19
A15: 45834 | B15: T | C15: -14.28
A16: 45833 | B16: F | C16: 63.94
... A104: 46009 | B104: T | C104: -24.11

Sheet FRUTERIA MI PEQUENA AURIYASMIN
A1: CLIENTE | B1: FRUTERIA MI PEQUENA AURIYASMIN
A2: NOMBRE
A3: TOTALES | C3: =SUM(C$4:C$1048576) -> 0 | D3: =SUM(D$4:D$1048576) -> 0 | E3: =SUM(E$5:E$1048576) -> 0 | F3: =SUM(F$5:F$1048576) -> 0 | G3: =SUM(G$5:G$1048576) -> 0
A4: FECHA | B4: F- E- T- | C4: DEUDA Y ABONOS | D4: VACIO 1/4 | E4: VACIO 350 | F4: VACIO 1.25 | G4: RETECION
A5: 45961 | B5: T | C5: -9.84
A6: 45961 | B6: F | C6: 9.84

Sheet FRUTITAS
A1: CLIENTE | B1: FRUTITAS
A2: NOMBRE | B2: LORENA MENDEZ
A3: TOTALES | C3: =SUM(C$4:C$1048576) -> -0.02 | D3: =SUM(D$4:D$1048576) -> 0 | E3: =SUM(E$5:E$1048576) -> 0 | F3: =SUM(F$5:F$1048576) -> 0 | G3: =SUM(G$5:G$1048576) -> 0
A4: FECHA | B4: F- E- T- | C4: DEUDA Y ABONOS | D4: VACIO 1/4 | E4: VACIO 350 | F4: VACIO 1.25 | G4: RETECION
A5: 45835 | B5: F | C5: 21.48
A6: 45842 | B6: E | C6: -21.5
B7: F
B8: T

Sheet FRUTERIA LA COLINA
A1: CLIENTE | B1: FRUTERIA LA COLINA
A2: NOMBRE | B2: MAIKOL CONTRERAS
A3: TOTALES | C3: =SUM(C$4:C$1048576) -> 12.61 | D3: =SUM(D$4:D$1048576) -> 0 | E3: =SUM(E$5:E$1048576) -> 0 | F3: =SUM(F$5:F$1048576) -> 0 | G3: =SUM(G$5:G$1048576) -> 0
A4: FECHA | B4: F- E- T- | C4: DEUDA Y ABONOS | D4: VACIO 1/4 | E4: VACIO 350 | F4: VACIO 1.25 | G4: RETECION
A5: 45945 | B5: F | C5: 67.11
A6: 45947 | B6: T | C6: -60
A7: 45950 | B7: T | C7: -7.11
A8: 45952 | B8: F | C8: 100.75
A9: 45960 | B9: T | C9: -26.16
A10: 45961 | B10: T | C10: -31
A11: 45964 | B11: T | C11: -43.75
A12: 45966 | B12: F | C12: 136.51
A13: 45966 | B13: F | C13: 9.81
A14: 45978 | B14: T | C14: -38.91
A15: 45978 | B15: T | C15: -41.02
A16: 45979 | B16: T | C16: -52.36
... A18: 45995 | B18: D | C18: -122.2

Sheet FUSION SPORT BAR
A1: CLIENTE | B1: FUSION SPORT BAR
A2: NOMBRE
A3: TOTALES | C3: =SUM(C$4:C$1048576) -> 476.88 | D3: =SUM(D$4:D$1048576) -> 0 | E3: =SUM(E$5:E$1048576) -> 0 | F3: =SUM(F$5:F$1048576) -> 0 | G3: =SUM(G$5:G$1048576) -> 0
A4: FECHA | B4: F- E- T- | C4: DEUDA Y ABONOS | D4: VACIO 1/4 | E4: VACIO 350 | F4: VACIO 1.25 | G4: RETECION
A5: 46013 | B5: F | C5: 476.88

Sheet GABRIELA LANDINEZ
A1: CLIENTE | B1: GABRIELA LANDINEZ
A2: NOMBRE
A3: TOTALES | C3: =SUM(C$4:C$1048576) -> 17.28 | D3: =SUM(D$4:D$1048576) -> 0 | E3: =SUM(E$5:E$1048576) -> 0 | F3: =SUM(F$5:F$1048576) -> 0 | G3: =SUM(G$5:G$1048576) -> 0
A4: FECHA | B4: F- E- T- | C4: DEUDA Y ABONOS | D4: VACIO 1/4 | E4: VACIO 350 | F4: VACIO 1.25 | G4: RETECION
A5: 46052 | B5: F | C5: 17.28

Sheet GERZON CHACON GUERRERO
A1: CLIENTE | B1: GERZON CHACON GUERRERO
A2: NOMBRE
A3: TOTALES | C3: =SUM(C$4:C$1048576) -> 52.63 | D3: =SUM(D$4:D$1048576) -> 0 | E3: =SUM(E$5:E$1048576) -> 0 | F3: =SUM(F$5:F$1048576) -> 0 | G3: =SUM(G$5:G$1048576) -> 0
A4: FECHA | B4: F- E- T- | C4: DEUDA Y ABONOS | D4: VACIO 1/4 | E4: VACIO 350 | F4: VACIO 1.25 | G4: RETECION
A5: 45853 | B5: F | C5: 102.42
A6: 45862 | B6: E | C6: -102.42
A7: 45862 | B7: F | C7: 22.8
A8: 45862 | B8: F | C8: 62.38
A9: 45862 | B9: F | C9: 6.78
A10: 45869 | B10: T | C10: -91.96
A11: 45869 | B11: F | C11: 38.14
A12: 45869 | B12: F | C12: 86.16
A13: 45869 | B13: F | C13: 55.86
A14: 45876 | B14: T | C14: -100
A15: 45876 | B15: E | C15: -82.75
A16: 45876 | B16: F | C16: 40.8
... A71: 46051 | B71: F | C71: 51.56

Sheet GLADIS PERNIA
A1: CLIENTE | B1: GLADIS PERNIA
A2: NOMBRE | B2: TOLDO VERDE
A3: TOTALES | C3: =SUM(C$4:C$1048576) -> 1.28 | D3: =SUM(D$4:D$1048576) -> 0 | E3: =SUM(E$5:E$1048576) -> 0 | F3: =SUM(F$5:F$1048576) -> 0 | G3: =SUM(G$5:G$1048576) -> 0
A4: FECHA | B4: F- E- T- | C4: DEUDA Y ABONOS | D4: VACIO 1/4 | E4: VACIO 350 | F4: VACIO 1.25 | G4: RETECION
A5: 45814 | B5: T | C5: -91.93
A6: 45813 | B6: F | C6: 28.65
A7: 45813 | B7: F | C7: 100.33
A8: 45821 | B8: T | C8: -36.78
A9: 45826 | B9: F | C9: 69.96
A10: 45831 | B10: T | C10: -47.41
